<DOMSymbolItem xmlns:xsi="http://www.w3.org/2001/XMLSchema-instance" xmlns="http://ns.adobe.com/xfl/2008/" name="MovieClips/Weapons/Parts/WPN.M9" itemID="5248e833-00002508" lastModified="1424226823" lastUniqueIdentifier="198">
  <timeline>
    <DOMTimeline name="WPN.M9" currentFrame="30">
      <layers>
        <DOMLayer name="actions" color="#9933CC" locked="true" current="true" isSelected="true" autoNamed="false">
          <frames>
            <DOMFrame index="0" keyMode="9728">
              <Actionscript>
                <script><![CDATA[stop();
dispatchEvent(new Event("updateHands"));
dispatchEvent(new Event("updateMag"));]]></script>
              </Actionscript>
              <elements/>
            </DOMFrame>
            <DOMFrame index="1" duration="7" name="fire" labelType="name" keyMode="9728">
              <elements/>
            </DOMFrame>
            <DOMFrame index="8" keyMode="9728">
              <Actionscript>
                <script><![CDATA[dispatchEvent(new Event("weaponFired"));]]></script>
              </Actionscript>
              <elements/>
            </DOMFrame>
            <DOMFrame index="9" duration="5" name="empty" labelType="name" keyMode="9728">
              <elements/>
            </DOMFrame>
            <DOMFrame index="14" duration="4" name="reload" labelType="name" keyMode="9728">
              <elements/>
            </DOMFrame>
            <DOMFrame index="18" duration="8" keyMode="9728">
              <Actionscript>
                <script><![CDATA[dispatchEvent(new Event("reloadMagOut"));
dispatchEvent(new Event("createMag"));]]></script>
              </Actionscript>
              <elements/>
            </DOMFrame>
            <DOMFrame index="26" duration="4" keyMode="9728">
              <Actionscript>
                <script><![CDATA[dispatchEvent(new Event("updateHands"));]]></script>
              </Actionscript>
              <elements/>
            </DOMFrame>
            <DOMFrame index="30" duration="8" keyMode="9728">
              <Actionscript>
                <script><![CDATA[dispatchEvent(new Event("updateHands"));
dispatchEvent(new Event("updateMag"));]]></script>
              </Actionscript>
              <elements/>
            </DOMFrame>
            <DOMFrame index="38" duration="4" keyMode="9728">
              <Actionscript>
                <script><![CDATA[dispatchEvent(new Event("reloadMagIn"));]]></script>
              </Actionscript>
              <elements/>
            </DOMFrame>
            <DOMFrame index="42" duration="8" keyMode="9728">
              <Actionscript>
                <script><![CDATA[dispatchEvent(new Event("updateHands"));]]></script>
              </Actionscript>
              <elements/>
            </DOMFrame>
            <DOMFrame index="50" duration="13" keyMode="9728">
              <Actionscript>
                <script><![CDATA[dispatchEvent(new Event("reloadSlideBack"));]]></script>
              </Actionscript>
              <elements/>
            </DOMFrame>
            <DOMFrame index="63" keyMode="9728">
              <Actionscript>
                <script><![CDATA[dispatchEvent(new Event("reloadComplete"));]]></script>
              </Actionscript>
              <elements/>
            </DOMFrame>
          </frames>
        </DOMLayer>
        <DOMLayer name="mc_hand" color="#FF800A" autoNamed="false">
          <frames>
            <DOMFrame index="0" keyMode="9728">
              <elements/>
            </DOMFrame>
            <DOMFrame index="1" duration="3" tweenType="motion" motionTweenSnap="true" hasCustomEase="true" keyMode="22017" acceleration="100">
              <tweens>
                <CustomEase target="all">
                  <Point/>
                  <Point x="0.333333333333333"/>
                  <Point x="0.666666666666667" y="0.333333333333333"/>
                  <Point x="1" y="1"/>
                </CustomEase>
              </tweens>
              <elements/>
            </DOMFrame>
            <DOMFrame index="4" duration="4" tweenType="motion" motionTweenSnap="true" hasCustomEase="true" keyMode="22017" acceleration="-100">
              <tweens>
                <CustomEase target="all">
                  <Point/>
                  <Point x="0.333333333333333" y="0.666666666666667"/>
                  <Point x="0.666666666666667" y="1"/>
                  <Point x="1" y="1"/>
                </CustomEase>
              </tweens>
              <elements/>
            </DOMFrame>
            <DOMFrame index="8" keyMode="9728">
              <elements/>
            </DOMFrame>
            <DOMFrame index="9" duration="5" keyMode="9728">
              <elements/>
            </DOMFrame>
            <DOMFrame index="14" duration="4" tweenType="motion" motionTweenSnap="true" hasCustomEase="true" keyMode="22017" acceleration="100">
              <tweens>
                <CustomEase target="all">
                  <Point/>
                  <Point x="0.333333333333333"/>
                  <Point x="0.666666666666667" y="0.333333333333333"/>
                  <Point x="1" y="1"/>
                </CustomEase>
              </tweens>
              <elements/>
            </DOMFrame>
            <DOMFrame index="18" duration="3" tweenType="motion" motionTweenSnap="true" hasCustomEase="true" keyMode="22017" acceleration="-100">
              <tweens>
                <CustomEase target="all">
                  <Point/>
                  <Point x="0.333333333333333" y="0.666666666666667"/>
                  <Point x="0.666666666666667" y="1"/>
                  <Point x="1" y="1"/>
                </CustomEase>
              </tweens>
              <elements/>
            </DOMFrame>
            <DOMFrame index="21" duration="5" tweenType="motion" motionTweenSnap="true" hasCustomEase="true" keyMode="22017" acceleration="100">
              <tweens>
                <CustomEase target="all">
                  <Point/>
                  <Point x="0.333333333333333"/>
                  <Point x="0.666666666666667" y="0.333333333333333"/>
                  <Point x="1" y="1"/>
                </CustomEase>
              </tweens>
              <elements/>
            </DOMFrame>
            <DOMFrame index="26" duration="4" tweenType="motion" motionTweenSnap="true" hasCustomEase="true" keyMode="22017" acceleration="-100">
              <tweens>
                <CustomEase target="all">
                  <Point/>
                  <Point x="0.333333333333333" y="0.666666666666667"/>
                  <Point x="0.666666666666667" y="1"/>
                  <Point x="1" y="1"/>
                </CustomEase>
              </tweens>
              <elements/>
            </DOMFrame>
            <DOMFrame index="30" duration="4" tweenType="motion" motionTweenSnap="true" hasCustomEase="true" keyMode="22017" acceleration="100">
              <tweens>
                <CustomEase target="all">
                  <Point/>
                  <Point x="0.333333333333333"/>
                  <Point x="0.666666666666667" y="0.333333333333333"/>
                  <Point x="1" y="1"/>
                </CustomEase>
              </tweens>
              <elements/>
            </DOMFrame>
            <DOMFrame index="34" duration="4" tweenType="motion" motionTweenSnap="true" hasCustomEase="true" keyMode="22017" acceleration="-100">
              <tweens>
                <CustomEase target="all">
                  <Point/>
                  <Point x="0.333333333333333" y="0.666666666666667"/>
                  <Point x="0.666666666666667" y="1"/>
                  <Point x="1" y="1"/>
                </CustomEase>
              </tweens>
              <elements/>
            </DOMFrame>
            <DOMFrame index="38" duration="3" tweenType="motion" motionTweenSnap="true" hasCustomEase="true" keyMode="22017" acceleration="99">
              <tweens>
                <CustomEase target="all">
                  <Point/>
                  <Point x="0.333333333333333" y="0.00333333333333334"/>
                  <Point x="0.666666666666667" y="0.336666666666667"/>
                  <Point x="1" y="1"/>
                </CustomEase>
              </tweens>
              <elements/>
            </DOMFrame>
            <DOMFrame index="41" tweenType="motion" motionTweenSnap="true" keyMode="22017">
              <elements/>
            </DOMFrame>
            <DOMFrame index="42" duration="4" tweenType="motion" motionTweenSnap="true" hasCustomEase="true" keyMode="22017" acceleration="-100">
              <tweens>
                <CustomEase target="all">
                  <Point/>
                  <Point x="0.333333333333333" y="0.666666666666667"/>
                  <Point x="0.666666666666667" y="1"/>
                  <Point x="1" y="1"/>
                </CustomEase>
              </tweens>
              <elements/>
            </DOMFrame>
            <DOMFrame index="46" duration="4" tweenType="motion" motionTweenSnap="true" hasCustomEase="true" keyMode="22017" acceleration="100">
              <tweens>
                <CustomEase target="all">
                  <Point/>
                  <Point x="0.333333333333333"/>
                  <Point x="0.666666666666667" y="0.333333333333333"/>
                  <Point x="1" y="1"/>
                </CustomEase>
              </tweens>
              <elements/>
            </DOMFrame>
            <DOMFrame index="50" tweenType="motion" motionTweenSnap="true" keyMode="22017">
              <elements/>
            </DOMFrame>
            <DOMFrame index="51" duration="4" tweenType="motion" motionTweenSnap="true" hasCustomEase="true" keyMode="22017" acceleration="-100">
              <tweens>
                <CustomEase target="all">
                  <Point/>
                  <Point x="0.333333333333333" y="0.666666666666667"/>
                  <Point x="0.666666666666667" y="1"/>
                  <Point x="1" y="1"/>
                </CustomEase>
              </tweens>
              <elements/>
            </DOMFrame>
            <DOMFrame index="55" duration="4" tweenType="motion" motionTweenSnap="true" hasCustomEase="true" keyMode="22017" acceleration="100">
              <tweens>
                <CustomEase target="all">
                  <Point/>
                  <Point x="0.333333333333333"/>
                  <Point x="0.666666666666667" y="0.333333333333333"/>
                  <Point x="1" y="1"/>
                </CustomEase>
              </tweens>
              <elements/>
            </DOMFrame>
            <DOMFrame index="59" duration="4" tweenType="motion" motionTweenSnap="true" hasCustomEase="true" keyMode="22017" acceleration="-100">
              <tweens>
                <CustomEase target="all">
                  <Point/>
                  <Point x="0.333333333333333" y="0.666666666666667"/>
                  <Point x="0.666666666666667" y="1"/>
                  <Point x="1" y="1"/>
                </CustomEase>
              </tweens>
              <elements/>
            </DOMFrame>
            <DOMFrame index="63" keyMode="9728">
              <elements/>
            </DOMFrame>
          </frames>
        </DOMLayer>
        <DOMLayer name="mc_trigger" color="#FF4FFF" autoNamed="false">
          <frames>
            <DOMFrame index="0" keyMode="9728">
              <elements/>
            </DOMFrame>
            <DOMFrame index="1" duration="3" tweenType="motion" motionTweenSnap="true" hasCustomEase="true" keyMode="22017" acceleration="100">
              <tweens>
                <CustomEase target="all">
                  <Point/>
                  <Point x="0.333333333333333"/>
                  <Point x="0.666666666666667" y="0.333333333333333"/>
                  <Point x="1" y="1"/>
                </CustomEase>
              </tweens>
              <elements/>
            </DOMFrame>
            <DOMFrame index="4" duration="4" tweenType="motion" motionTweenSnap="true" hasCustomEase="true" keyMode="22017" acceleration="-100">
              <tweens>
                <CustomEase target="all">
                  <Point/>
                  <Point x="0.333333333333333" y="0.666666666666667"/>
                  <Point x="0.666666666666667" y="1"/>
                  <Point x="1" y="1"/>
                </CustomEase>
              </tweens>
              <elements/>
            </DOMFrame>
            <DOMFrame index="8" keyMode="9728">
              <elements/>
            </DOMFrame>
            <DOMFrame index="9" duration="5" keyMode="9728">
              <elements/>
            </DOMFrame>
            <DOMFrame index="14" duration="4" tweenType="motion" motionTweenSnap="true" hasCustomEase="true" keyMode="22017" acceleration="100">
              <tweens>
                <CustomEase target="all">
                  <Point/>
                  <Point x="0.333333333333333"/>
                  <Point x="0.666666666666667" y="0.333333333333333"/>
                  <Point x="1" y="1"/>
                </CustomEase>
              </tweens>
              <elements/>
            </DOMFrame>
            <DOMFrame index="18" duration="3" tweenType="motion" motionTweenSnap="true" hasCustomEase="true" keyMode="22017" acceleration="-100">
              <tweens>
                <CustomEase target="all">
                  <Point/>
                  <Point x="0.333333333333333" y="0.666666666666667"/>
                  <Point x="0.666666666666667" y="1"/>
                  <Point x="1" y="1"/>
                </CustomEase>
              </tweens>
              <elements/>
            </DOMFrame>
            <DOMFrame index="21" duration="5" tweenType="motion" motionTweenSnap="true" hasCustomEase="true" keyMode="22017" acceleration="100">
              <tweens>
                <CustomEase target="all">
                  <Point/>
                  <Point x="0.333333333333333"/>
                  <Point x="0.666666666666667" y="0.333333333333333"/>
                  <Point x="1" y="1"/>
                </CustomEase>
              </tweens>
              <elements/>
            </DOMFrame>
            <DOMFrame index="26" duration="4" tweenType="motion" motionTweenSnap="true" hasCustomEase="true" keyMode="22017" acceleration="-100">
              <tweens>
                <CustomEase target="all">
                  <Point/>
                  <Point x="0.333333333333333" y="0.666666666666667"/>
                  <Point x="0.666666666666667" y="1"/>
                  <Point x="1" y="1"/>
                </CustomEase>
              </tweens>
              <elements/>
            </DOMFrame>
            <DOMFrame index="30" duration="4" tweenType="motion" motionTweenSnap="true" hasCustomEase="true" keyMode="22017" acceleration="100">
              <tweens>
                <CustomEase target="all">
                  <Point/>
                  <Point x="0.333333333333333"/>
                  <Point x="0.666666666666667" y="0.333333333333333"/>
                  <Point x="1" y="1"/>
                </CustomEase>
              </tweens>
              <elements/>
            </DOMFrame>
            <DOMFrame index="34" duration="4" tweenType="motion" motionTweenSnap="true" hasCustomEase="true" keyMode="22017" acceleration="-100">
              <tweens>
                <CustomEase target="all">
                  <Point/>
                  <Point x="0.333333333333333" y="0.666666666666667"/>
                  <Point x="0.666666666666667" y="1"/>
                  <Point x="1" y="1"/>
                </CustomEase>
              </tweens>
              <elements/>
            </DOMFrame>
            <DOMFrame index="38" duration="3" tweenType="motion" motionTweenSnap="true" hasCustomEase="true" keyMode="22017" acceleration="99">
              <tweens>
                <CustomEase target="all">
                  <Point/>
                  <Point x="0.333333333333333" y="0.00333333333333334"/>
                  <Point x="0.666666666666667" y="0.336666666666667"/>
                  <Point x="1" y="1"/>
                </CustomEase>
              </tweens>
              <elements/>
            </DOMFrame>
            <DOMFrame index="41" tweenType="motion" motionTweenSnap="true" keyMode="22017">
              <elements/>
            </DOMFrame>
            <DOMFrame index="42" duration="4" tweenType="motion" motionTweenSnap="true" hasCustomEase="true" keyMode="22017" acceleration="-100">
              <tweens>
                <CustomEase target="all">
                  <Point/>
                  <Point x="0.333333333333333" y="0.666666666666667"/>
                  <Point x="0.666666666666667" y="1"/>
                  <Point x="1" y="1"/>
                </CustomEase>
              </tweens>
              <elements/>
            </DOMFrame>
            <DOMFrame index="46" duration="4" tweenType="motion" motionTweenSnap="true" hasCustomEase="true" keyMode="22017" acceleration="100">
              <tweens>
                <CustomEase target="all">
                  <Point/>
                  <Point x="0.333333333333333"/>
                  <Point x="0.666666666666667" y="0.333333333333333"/>
                  <Point x="1" y="1"/>
                </CustomEase>
              </tweens>
              <elements/>
            </DOMFrame>
            <DOMFrame index="50" tweenType="motion" motionTweenSnap="true" keyMode="22017">
              <elements/>
            </DOMFrame>
            <DOMFrame index="51" duration="4" tweenType="motion" motionTweenSnap="true" hasCustomEase="true" keyMode="22017" acceleration="-100">
              <tweens>
                <CustomEase target="all">
                  <Point/>
                  <Point x="0.333333333333333" y="0.666666666666667"/>
                  <Point x="0.666666666666667" y="1"/>
                  <Point x="1" y="1"/>
                </CustomEase>
              </tweens>
              <elements/>
            </DOMFrame>
            <DOMFrame index="55" duration="4" tweenType="motion" motionTweenSnap="true" hasCustomEase="true" keyMode="22017" acceleration="100">
              <tweens>
                <CustomEase target="all">
                  <Point/>
                  <Point x="0.333333333333333"/>
                  <Point x="0.666666666666667" y="0.333333333333333"/>
                  <Point x="1" y="1"/>
                </CustomEase>
              </tweens>
              <elements/>
            </DOMFrame>
            <DOMFrame index="59" duration="4" tweenType="motion" motionTweenSnap="true" hasCustomEase="true" keyMode="22017" acceleration="-100">
              <tweens>
                <CustomEase target="all">
                  <Point/>
                  <Point x="0.333333333333333" y="0.666666666666667"/>
                  <Point x="0.666666666666667" y="1"/>
                  <Point x="1" y="1"/>
                </CustomEase>
              </tweens>
              <elements/>
            </DOMFrame>
            <DOMFrame index="63" keyMode="9728">
              <elements/>
            </DOMFrame>
          </frames>
        </DOMLayer>
        <DOMLayer name="mc_slide" color="#4FFFFF" autoNamed="false">
          <frames>
            <DOMFrame index="0" keyMode="9728">
              <elements>
                <DOMSymbolInstance libraryItemName="MovieClips/Weapons/Parts/WPN.M9.Slide" name="mc_slide" centerPoint3DX="0.25" centerPoint3DY="-8.55">
                  <matrix>
                    <Matrix tx="0.25" ty="-8.55"/>
                  </matrix>
                  <transformationPoint>
                    <Point/>
                  </transformationPoint>
                </DOMSymbolInstance>
              </elements>
            </DOMFrame>
            <DOMFrame index="1" duration="3" tweenType="motion" motionTweenSnap="true" hasCustomEase="true" keyMode="22017" acceleration="100">
              <tweens>
                <CustomEase target="all">
                  <Point/>
                  <Point x="0.333333333333333"/>
                  <Point x="0.666666666666667" y="0.333333333333333"/>
                  <Point x="1" y="1"/>
                </CustomEase>
              </tweens>
              <elements>
                <DOMSymbolInstance libraryItemName="MovieClips/Weapons/Parts/WPN.M9.Slide" name="mc_slide" centerPoint3DX="-15.4" centerPoint3DY="-12.75">
                  <matrix>
                    <Matrix a="0.9984130859375" b="-0.0563201904296875" c="0.0563201904296875" d="0.9984130859375" tx="-14.05" ty="-11.9"/>
                  </matrix>
                  <transformationPoint>
                    <Point/>
                  </transformationPoint>
                </DOMSymbolInstance>
              </elements>
            </DOMFrame>
            <DOMFrame index="4" duration="4" tweenType="motion" motionTweenSnap="true" hasCustomEase="true" keyMode="22017" acceleration="-100">
              <tweens>
                <CustomEase target="all">
                  <Point/>
                  <Point x="0.333333333333333" y="0.666666666666667"/>
                  <Point x="0.666666666666667" y="1"/>
                  <Point x="1" y="1"/>
                </CustomEase>
              </tweens>
              <elements>
                <DOMSymbolInstance libraryItemName="MovieClips/Weapons/Parts/WPN.M9.Slide" name="mc_slide" centerPoint3DX="-2.2" centerPoint3DY="-10.9">
                  <matrix>
                    <Matrix a="0.991455078125" b="0.130340576171875" c="-0.130340576171875" d="0.991455078125" tx="-1.5" ty="-8.35"/>
                  </matrix>
                  <transformationPoint>
                    <Point/>
                  </transformationPoint>
                </DOMSymbolInstance>
              </elements>
            </DOMFrame>
            <DOMFrame index="8" keyMode="9728">
              <elements>
                <DOMSymbolInstance libraryItemName="MovieClips/Weapons/Parts/WPN.M9.Slide" name="mc_slide" centerPoint3DX="0.25" centerPoint3DY="-8.55">
                  <matrix>
                    <Matrix tx="0.25" ty="-8.55"/>
                  </matrix>
                  <transformationPoint>
                    <Point/>
                  </transformationPoint>
                </DOMSymbolInstance>
              </elements>
            </DOMFrame>
            <DOMFrame index="9" duration="5" keyMode="9728">
              <elements>
                <DOMSymbolInstance libraryItemName="MovieClips/Weapons/Parts/WPN.M9.Slide" name="mc_slide" centerPoint3DX="-6.75" centerPoint3DY="-8.55">
                  <matrix>
                    <Matrix tx="-6.75" ty="-8.55"/>
                  </matrix>
                  <transformationPoint>
                    <Point/>
                  </transformationPoint>
                </DOMSymbolInstance>
              </elements>
            </DOMFrame>
            <DOMFrame index="14" duration="4" tweenType="motion" motionTweenSnap="true" hasCustomEase="true" keyMode="22017" acceleration="100">
              <tweens>
                <CustomEase target="all">
                  <Point/>
                  <Point x="0.333333333333333"/>
                  <Point x="0.666666666666667" y="0.333333333333333"/>
                  <Point x="1" y="1"/>
                </CustomEase>
              </tweens>
              <elements>
                <DOMSymbolInstance libraryItemName="MovieClips/Weapons/Parts/WPN.M9.Slide" name="mc_slide" centerPoint3DX="-6.75" centerPoint3DY="-8.55">
                  <matrix>
                    <Matrix tx="-6.75" ty="-8.55"/>
                  </matrix>
                  <transformationPoint>
                    <Point/>
                  </transformationPoint>
                </DOMSymbolInstance>
              </elements>
            </DOMFrame>
            <DOMFrame index="18" duration="3" tweenType="motion" motionTweenSnap="true" hasCustomEase="true" keyMode="22017" acceleration="-100">
              <tweens>
                <CustomEase target="all">
                  <Point/>
                  <Point x="0.333333333333333" y="0.666666666666667"/>
                  <Point x="0.666666666666667" y="1"/>
                  <Point x="1" y="1"/>
                </CustomEase>
              </tweens>
              <elements>
                <DOMSymbolInstance libraryItemName="MovieClips/Weapons/Parts/WPN.M9.Slide" name="mc_slide" centerPoint3DX="-8.7" centerPoint3DY="-11.2">
                  <matrix>
                    <Matrix a="0.9891357421875" b="-0.146942138671875" c="0.146942138671875" d="0.9891357421875" tx="-8.95" ty="-11.15"/>
                  </matrix>
                  <transformationPoint>
                    <Point/>
                  </transformationPoint>
                </DOMSymbolInstance>
              </elements>
            </DOMFrame>
            <DOMFrame index="21" duration="5" tweenType="motion" motionTweenSnap="true" hasCustomEase="true" keyMode="22017" acceleration="100">
              <tweens>
                <CustomEase target="all">
                  <Point/>
                  <Point x="0.333333333333333"/>
                  <Point x="0.666666666666667" y="0.333333333333333"/>
                  <Point x="1" y="1"/>
                </CustomEase>
              </tweens>
              <elements>
                <DOMSymbolInstance libraryItemName="MovieClips/Weapons/Parts/WPN.M9.Slide" name="mc_slide" centerPoint3DX="-8.3" centerPoint3DY="-18.7">
                  <matrix>
                    <Matrix a="0.994552612304688" b="0.104141235351563" c="-0.104141235351563" d="0.994552612304688" tx="-8.35" ty="-18.7"/>
                  </matrix>
                  <transformationPoint>
                    <Point/>
                  </transformationPoint>
                </DOMSymbolInstance>
              </elements>
            </DOMFrame>
            <DOMFrame index="26" duration="4" tweenType="motion" motionTweenSnap="true" hasCustomEase="true" keyMode="22017" acceleration="-100">
              <tweens>
                <CustomEase target="all">
                  <Point/>
                  <Point x="0.333333333333333" y="0.666666666666667"/>
                  <Point x="0.666666666666667" y="1"/>
                  <Point x="1" y="1"/>
                </CustomEase>
              </tweens>
              <elements>
                <DOMSymbolInstance libraryItemName="MovieClips/Weapons/Parts/WPN.M9.Slide" name="mc_slide" centerPoint3DX="-11.4" centerPoint3DY="-5.6">
                  <matrix>
                    <Matrix a="0.99993896484375" b="0.0081634521484375" c="-0.0081634521484375" d="0.99993896484375" tx="-11.7" ty="-5.75"/>
                  </matrix>
                  <transformationPoint>
                    <Point/>
                  </transformationPoint>
                </DOMSymbolInstance>
              </elements>
            </DOMFrame>
            <DOMFrame index="30" duration="4" tweenType="motion" motionTweenSnap="true" hasCustomEase="true" keyMode="22017" acceleration="100">
              <tweens>
                <CustomEase target="all">
                  <Point/>
                  <Point x="0.333333333333333"/>
                  <Point x="0.666666666666667" y="0.333333333333333"/>
                  <Point x="1" y="1"/>
                </CustomEase>
              </tweens>
              <elements>
                <DOMSymbolInstance libraryItemName="MovieClips/Weapons/Parts/WPN.M9.Slide" name="mc_slide" centerPoint3DX="-8.05" centerPoint3DY="8.8">
                  <matrix>
                    <Matrix a="0.85076904296875" b="0.525482177734375" c="-0.525482177734375" d="0.85076904296875" tx="-9.4" ty="8.9"/>
                  </matrix>
                  <transformationPoint>
                    <Point/>
                  </transformationPoint>
                </DOMSymbolInstance>
              </elements>
            </DOMFrame>
            <DOMFrame index="34" duration="4" tweenType="motion" motionTweenSnap="true" hasCustomEase="true" keyMode="22017" acceleration="-100">
              <tweens>
                <CustomEase target="all">
                  <Point/>
                  <Point x="0.333333333333333" y="0.666666666666667"/>
                  <Point x="0.666666666666667" y="1"/>
                  <Point x="1" y="1"/>
                </CustomEase>
              </tweens>
              <elements>
                <DOMSymbolInstance libraryItemName="MovieClips/Weapons/Parts/WPN.M9.Slide" name="mc_slide" centerPoint3DX="-1" centerPoint3DY="9.1">
                  <matrix>
                    <Matrix a="0.545944213867188" b="0.8377685546875" c="-0.8377685546875" d="0.545944213867188" tx="-2.85" ty="8.65"/>
                  </matrix>
                  <transformationPoint>
                    <Point/>
                  </transformationPoint>
                </DOMSymbolInstance>
              </elements>
            </DOMFrame>
            <DOMFrame index="38" duration="3" tweenType="motion" motionTweenSnap="true" hasCustomEase="true" keyMode="22017" acceleration="99">
              <tweens>
                <CustomEase target="all">
                  <Point/>
                  <Point x="0.333333333333333" y="0.00333333333333334"/>
                  <Point x="0.666666666666667" y="0.336666666666667"/>
                  <Point x="1" y="1"/>
                </CustomEase>
              </tweens>
              <elements>
                <DOMSymbolInstance libraryItemName="MovieClips/Weapons/Parts/WPN.M9.Slide" name="mc_slide" centerPoint3DX="-0.3" centerPoint3DY="3.6">
                  <matrix>
                    <Matrix a="0.67333984375" b="0.739273071289063" c="-0.739273071289063" d="0.67333984375" tx="-2.45" ty="3.15"/>
                  </matrix>
                  <transformationPoint>
                    <Point/>
                  </transformationPoint>
                </DOMSymbolInstance>
              </elements>
            </DOMFrame>
            <DOMFrame index="41" tweenType="motion" motionTweenSnap="true" keyMode="22017">
              <elements>
                <DOMSymbolInstance libraryItemName="MovieClips/Weapons/Parts/WPN.M9.Slide" name="mc_slide" centerPoint3DX="1" centerPoint3DY="4.25">
                  <matrix>
                    <Matrix a="0.571640014648438" b="0.820449829101563" c="-0.820449829101563" d="0.571640014648438" tx="-1" ty="3.7"/>
                  </matrix>
                  <transformationPoint>
                    <Point/>
                  </transformationPoint>
                </DOMSymbolInstance>
              </elements>
            </DOMFrame>
            <DOMFrame index="42" duration="4" tweenType="motion" motionTweenSnap="true" hasCustomEase="true" keyMode="22017" acceleration="-100">
              <tweens>
                <CustomEase target="all">
                  <Point/>
                  <Point x="0.333333333333333" y="0.666666666666667"/>
                  <Point x="0.666666666666667" y="1"/>
                  <Point x="1" y="1"/>
                </CustomEase>
              </tweens>
              <elements>
                <DOMSymbolInstance libraryItemName="MovieClips/Weapons/Parts/WPN.M9.Slide" name="mc_slide" centerPoint3DX="3.65" centerPoint3DY="3.25">
                  <matrix>
                    <Matrix a="0.52301025390625" b="0.852310180664063" c="-0.852310180664063" d="0.52301025390625" tx="3.75" ty="3.15"/>
                  </matrix>
                  <transformationPoint>
                    <Point/>
                  </transformationPoint>
                </DOMSymbolInstance>
              </elements>
            </DOMFrame>
            <DOMFrame index="46" duration="4" tweenType="motion" motionTweenSnap="true" hasCustomEase="true" keyMode="22017" acceleration="100">
              <tweens>
                <CustomEase target="all">
                  <Point/>
                  <Point x="0.333333333333333"/>
                  <Point x="0.666666666666667" y="0.333333333333333"/>
                  <Point x="1" y="1"/>
                </CustomEase>
              </tweens>
              <elements>
                <DOMSymbolInstance libraryItemName="MovieClips/Weapons/Parts/WPN.M9.Slide" name="mc_slide" centerPoint3DX="6.9" centerPoint3DY="1.8">
                  <matrix>
                    <Matrix a="0.642776489257813" b="0.766036987304688" c="-0.766036987304688" d="0.642776489257813" tx="6.9" ty="1.45"/>
                  </matrix>
                  <transformationPoint>
                    <Point/>
                  </transformationPoint>
                </DOMSymbolInstance>
              </elements>
            </DOMFrame>
            <DOMFrame index="50" tweenType="motion" motionTweenSnap="true" keyMode="22017">
              <elements>
                <DOMSymbolInstance libraryItemName="MovieClips/Weapons/Parts/WPN.M9.Slide" name="mc_slide" centerPoint3DX="5.4" centerPoint3DY="-3.7">
                  <matrix>
                    <Matrix a="0.768234252929688" b="0.640151977539063" c="-0.640151977539063" d="0.768234252929688" tx="5.3" ty="-3.2"/>
                  </matrix>
                  <transformationPoint>
                    <Point/>
                  </transformationPoint>
                </DOMSymbolInstance>
              </elements>
            </DOMFrame>
            <DOMFrame index="51" duration="4" tweenType="motion" motionTweenSnap="true" hasCustomEase="true" keyMode="22017" acceleration="-100">
              <tweens>
                <CustomEase target="all">
                  <Point/>
                  <Point x="0.333333333333333" y="0.666666666666667"/>
                  <Point x="0.666666666666667" y="1"/>
                  <Point x="1" y="1"/>
                </CustomEase>
              </tweens>
              <elements>
                <DOMSymbolInstance libraryItemName="MovieClips/Weapons/Parts/WPN.M9.Slide" name="mc_slide" centerPoint3DX="13.9" centerPoint3DY="2.4">
                  <matrix>
                    <Matrix a="0.704986572265625" b="0.709213256835938" c="-0.709213256835938" d="0.704986572265625" tx="14.3" ty="2.3"/>
                  </matrix>
                  <transformationPoint>
                    <Point/>
                  </transformationPoint>
                </DOMSymbolInstance>
              </elements>
            </DOMFrame>
            <DOMFrame index="55" duration="4" tweenType="motion" motionTweenSnap="true" hasCustomEase="true" keyMode="22017" acceleration="100">
              <tweens>
                <CustomEase target="all">
                  <Point/>
                  <Point x="0.333333333333333"/>
                  <Point x="0.666666666666667" y="0.333333333333333"/>
                  <Point x="1" y="1"/>
                </CustomEase>
              </tweens>
              <elements>
                <DOMSymbolInstance libraryItemName="MovieClips/Weapons/Parts/WPN.M9.Slide" name="mc_slide" centerPoint3DX="16.35" centerPoint3DY="3.4">
                  <matrix>
                    <Matrix a="0.726303100585938" b="0.687347412109375" c="-0.687347412109375" d="0.726303100585938" tx="16.5" ty="3.2"/>
                  </matrix>
                  <transformationPoint>
                    <Point/>
                  </transformationPoint>
                </DOMSymbolInstance>
              </elements>
            </DOMFrame>
            <DOMFrame index="59" duration="4" tweenType="motion" motionTweenSnap="true" hasCustomEase="true" keyMode="22017" acceleration="-100">
              <tweens>
                <CustomEase target="all">
                  <Point/>
                  <Point x="0.333333333333333" y="0.666666666666667"/>
                  <Point x="0.666666666666667" y="1"/>
                  <Point x="1" y="1"/>
                </CustomEase>
              </tweens>
              <elements>
                <DOMSymbolInstance libraryItemName="MovieClips/Weapons/Parts/WPN.M9.Slide" name="mc_slide" centerPoint3DX="9.15" centerPoint3DY="-6.4">
                  <matrix>
                    <Matrix a="0.954925537109375" b="0.296737670898438" c="-0.296737670898438" d="0.954925537109375" tx="9.4" ty="-5.85"/>
                  </matrix>
                  <transformationPoint>
                    <Point/>
                  </transformationPoint>
                </DOMSymbolInstance>
              </elements>
            </DOMFrame>
            <DOMFrame index="63" keyMode="9728">
              <elements>
                <DOMSymbolInstance libraryItemName="MovieClips/Weapons/Parts/WPN.M9.Slide" name="mc_slide" centerPoint3DX="0.25" centerPoint3DY="-8.55">
                  <matrix>
                    <Matrix tx="0.25" ty="-8.55"/>
                  </matrix>
                  <transformationPoint>
                    <Point/>
                  </transformationPoint>
                </DOMSymbolInstance>
              </elements>
            </DOMFrame>
          </frames>
        </DOMLayer>
        <DOMLayer name="mc_gun" color="#808080" autoNamed="false">
          <frames>
            <DOMFrame index="0" keyMode="9728">
              <elements>
                <DOMSymbolInstance libraryItemName="MovieClips/Weapons/Parts/WPN.M9.Gun" name="mc_gun" centerPoint3DY="0.7">
                  <matrix>
                    <Matrix ty="0.75"/>
                  </matrix>
                  <transformationPoint>
                    <Point y="-0.05"/>
                  </transformationPoint>
                </DOMSymbolInstance>
              </elements>
            </DOMFrame>
            <DOMFrame index="1" duration="3" tweenType="motion" motionTweenSnap="true" hasCustomEase="true" keyMode="22017" acceleration="100">
              <tweens>
                <CustomEase target="all">
                  <Point/>
                  <Point x="0.333333333333333"/>
                  <Point x="0.666666666666667" y="0.333333333333333"/>
                  <Point x="1" y="1"/>
                </CustomEase>
              </tweens>
              <elements>
                <DOMSymbolInstance libraryItemName="MovieClips/Weapons/Parts/WPN.M9.Gun" name="mc_gun" centerPoint3DX="-6.65" centerPoint3DY="-3.5">
                  <matrix>
                    <Matrix a="0.9984130859375" b="-0.0563201904296875" c="0.0563201904296875" d="0.9984130859375" tx="-5.55" ty="-3.1"/>
                  </matrix>
                  <transformationPoint>
                    <Point x="0.05" y="-0.05"/>
                  </transformationPoint>
                </DOMSymbolInstance>
              </elements>
            </DOMFrame>
            <DOMFrame index="4" duration="4" tweenType="motion" motionTweenSnap="true" hasCustomEase="true" keyMode="22017" acceleration="-100">
              <tweens>
                <CustomEase target="all">
                  <Point/>
                  <Point x="0.333333333333333" y="0.666666666666667"/>
                  <Point x="0.666666666666667" y="1"/>
                  <Point x="1" y="1"/>
                </CustomEase>
              </tweens>
              <elements>
                <DOMSymbolInstance libraryItemName="MovieClips/Weapons/Parts/WPN.M9.Gun" name="mc_gun" centerPoint3DX="-2" centerPoint3DY="-2.6">
                  <matrix>
                    <Matrix a="0.991455078125" b="0.130340576171875" c="-0.130340576171875" d="0.991455078125" tx="-2.95" ty="0.95"/>
                  </matrix>
                  <transformationPoint>
                    <Point x="0.05" y="-0.05"/>
                  </transformationPoint>
                </DOMSymbolInstance>
              </elements>
            </DOMFrame>
            <DOMFrame index="8" keyMode="9728">
              <elements>
                <DOMSymbolInstance libraryItemName="MovieClips/Weapons/Parts/WPN.M9.Gun" name="mc_gun" centerPoint3DY="0.7">
                  <matrix>
                    <Matrix ty="0.75"/>
                  </matrix>
                  <transformationPoint>
                    <Point y="-0.05"/>
                  </transformationPoint>
                </DOMSymbolInstance>
              </elements>
            </DOMFrame>
            <DOMFrame index="9" duration="5" keyMode="9728">
              <elements>
                <DOMSymbolInstance libraryItemName="MovieClips/Weapons/Parts/WPN.M9.Gun" name="mc_gun" centerPoint3DY="0.7">
                  <matrix>
                    <Matrix ty="0.75"/>
                  </matrix>
                  <transformationPoint>
                    <Point y="-0.05"/>
                  </transformationPoint>
                </DOMSymbolInstance>
              </elements>
            </DOMFrame>
            <DOMFrame index="14" duration="4" tweenType="motion" motionTweenSnap="true" hasCustomEase="true" keyMode="22017" acceleration="100">
              <tweens>
                <CustomEase target="all">
                  <Point/>
                  <Point x="0.333333333333333"/>
                  <Point x="0.666666666666667" y="0.333333333333333"/>
                  <Point x="1" y="1"/>
                </CustomEase>
              </tweens>
              <elements>
                <DOMSymbolInstance libraryItemName="MovieClips/Weapons/Parts/WPN.M9.Gun" name="mc_gun" centerPoint3DY="0.7">
                  <matrix>
                    <Matrix ty="0.75"/>
                  </matrix>
                  <transformationPoint>
                    <Point y="-0.05"/>
                  </transformationPoint>
                </DOMSymbolInstance>
              </elements>
            </DOMFrame>
            <DOMFrame index="18" duration="3" tweenType="motion" motionTweenSnap="true" hasCustomEase="true" keyMode="22017" acceleration="-100">
              <tweens>
                <CustomEase target="all">
                  <Point/>
                  <Point x="0.333333333333333" y="0.666666666666667"/>
                  <Point x="0.666666666666667" y="1"/>
                  <Point x="1" y="1"/>
                </CustomEase>
              </tweens>
              <elements>
                <DOMSymbolInstance libraryItemName="MovieClips/Weapons/Parts/WPN.M9.Gun" name="mc_gun" centerPoint3DX="-0.9" centerPoint3DY="-2.95">
                  <matrix>
                    <Matrix a="0.9891357421875" b="-0.146942138671875" c="0.146942138671875" d="0.9891357421875" tx="-0.95" ty="-2.95"/>
                  </matrix>
                  <transformationPoint>
                    <Point x="-0.05" y="-0.05"/>
                  </transformationPoint>
                </DOMSymbolInstance>
              </elements>
            </DOMFrame>
            <DOMFrame index="21" duration="5" tweenType="motion" motionTweenSnap="true" hasCustomEase="true" keyMode="22017" acceleration="100">
              <tweens>
                <CustomEase target="all">
                  <Point/>
                  <Point x="0.333333333333333"/>
                  <Point x="0.666666666666667" y="0.333333333333333"/>
                  <Point x="1" y="1"/>
                </CustomEase>
              </tweens>
              <elements>
                <DOMSymbolInstance libraryItemName="MovieClips/Weapons/Parts/WPN.M9.Gun" name="mc_gun" centerPoint3DX="-2.65" centerPoint3DY="-8.7">
                  <matrix>
                    <Matrix a="0.994552612304688" b="0.104141235351563" c="-0.104141235351563" d="0.994552612304688" tx="-2.6" ty="-8.75"/>
                  </matrix>
                  <transformationPoint>
                    <Point x="-0.05" y="-0.05"/>
                  </transformationPoint>
                </DOMSymbolInstance>
              </elements>
            </DOMFrame>
            <DOMFrame index="26" duration="4" tweenType="motion" motionTweenSnap="true" hasCustomEase="true" keyMode="22017" acceleration="-100">
              <tweens>
                <CustomEase target="all">
                  <Point/>
                  <Point x="0.333333333333333" y="0.666666666666667"/>
                  <Point x="0.666666666666667" y="1"/>
                  <Point x="1" y="1"/>
                </CustomEase>
              </tweens>
              <elements>
                <DOMSymbolInstance libraryItemName="MovieClips/Weapons/Parts/WPN.M9.Gun" name="mc_gun" centerPoint3DX="-4.95" centerPoint3DY="3.6">
                  <matrix>
                    <Matrix a="0.99993896484375" b="0.0081634521484375" c="-0.0081634521484375" d="0.99993896484375" tx="-5" ty="3.6"/>
                  </matrix>
                  <transformationPoint>
                    <Point x="-0.1"/>
                  </transformationPoint>
                </DOMSymbolInstance>
              </elements>
            </DOMFrame>
            <DOMFrame index="30" duration="4" tweenType="motion" motionTweenSnap="true" hasCustomEase="true" keyMode="22017" acceleration="100">
              <tweens>
                <CustomEase target="all">
                  <Point/>
                  <Point x="0.333333333333333"/>
                  <Point x="0.666666666666667" y="0.333333333333333"/>
                  <Point x="1" y="1"/>
                </CustomEase>
              </tweens>
              <elements>
                <DOMSymbolInstance libraryItemName="MovieClips/Weapons/Parts/WPN.M9.Gun" name="mc_gun" centerPoint3DX="-8.05" centerPoint3DY="19.95">
                  <matrix>
                    <Matrix a="0.85076904296875" b="0.525482177734375" c="-0.525482177734375" d="0.85076904296875" tx="-8.5" ty="20.45"/>
                  </matrix>
                  <transformationPoint>
                    <Point x="-0.15" y="-0.05"/>
                  </transformationPoint>
                </DOMSymbolInstance>
              </elements>
            </DOMFrame>
            <DOMFrame index="34" duration="4" tweenType="motion" motionTweenSnap="true" hasCustomEase="true" keyMode="22017" acceleration="-100">
              <tweens>
                <CustomEase target="all">
                  <Point/>
                  <Point x="0.333333333333333" y="0.666666666666667"/>
                  <Point x="0.666666666666667" y="1"/>
                  <Point x="1" y="1"/>
                </CustomEase>
              </tweens>
              <elements>
                <DOMSymbolInstance libraryItemName="MovieClips/Weapons/Parts/WPN.M9.Gun" name="mc_gun" centerPoint3DX="-5.8" centerPoint3DY="19.2">
                  <matrix>
                    <Matrix a="0.545944213867188" b="0.8377685546875" c="-0.8377685546875" d="0.545944213867188" tx="-6.95" ty="19.5"/>
                  </matrix>
                  <transformationPoint>
                    <Point x="-0.15" y="-0.05"/>
                  </transformationPoint>
                </DOMSymbolInstance>
              </elements>
            </DOMFrame>
            <DOMFrame index="38" duration="3" tweenType="motion" motionTweenSnap="true" hasCustomEase="true" keyMode="22017" acceleration="99">
              <tweens>
                <CustomEase target="all">
                  <Point/>
                  <Point x="0.333333333333333" y="0.00333333333333334"/>
                  <Point x="0.666666666666667" y="0.336666666666667"/>
                  <Point x="1" y="1"/>
                </CustomEase>
              </tweens>
              <elements>
                <DOMSymbolInstance libraryItemName="MovieClips/Weapons/Parts/WPN.M9.Gun" name="mc_gun" centerPoint3DX="-3.5" centerPoint3DY="14.1">
                  <matrix>
                    <Matrix a="0.67333984375" b="0.739273071289063" c="-0.739273071289063" d="0.67333984375" tx="-4.8" ty="14.55"/>
                  </matrix>
                  <transformationPoint>
                    <Point x="-0.15" y="-0.05"/>
                  </transformationPoint>
                </DOMSymbolInstance>
              </elements>
            </DOMFrame>
            <DOMFrame index="41" tweenType="motion" motionTweenSnap="true" keyMode="22017">
              <elements>
                <DOMSymbolInstance libraryItemName="MovieClips/Weapons/Parts/WPN.M9.Gun" name="mc_gun" centerPoint3DX="-3.6" centerPoint3DY="14.3">
                  <matrix>
                    <Matrix a="0.571640014648438" b="0.820449829101563" c="-0.820449829101563" d="0.571640014648438" tx="-4.8" ty="14.75"/>
                  </matrix>
                  <transformationPoint>
                    <Point x="-0.15" y="-0.1"/>
                  </transformationPoint>
                </DOMSymbolInstance>
              </elements>
            </DOMFrame>
            <DOMFrame index="42" duration="4" tweenType="motion" motionTweenSnap="true" hasCustomEase="true" keyMode="22017" acceleration="-100">
              <tweens>
                <CustomEase target="all">
                  <Point/>
                  <Point x="0.333333333333333" y="0.666666666666667"/>
                  <Point x="0.666666666666667" y="1"/>
                  <Point x="1" y="1"/>
                </CustomEase>
              </tweens>
              <elements>
                <DOMSymbolInstance libraryItemName="MovieClips/Weapons/Parts/WPN.M9.Gun" name="mc_gun" centerPoint3DX="-0.55" centerPoint3DY="13.8">
                  <matrix>
                    <Matrix a="0.52301025390625" b="0.852310180664063" c="-0.852310180664063" d="0.52301025390625" tx="-0.65" ty="13.7"/>
                  </matrix>
                  <transformationPoint>
                    <Point x="0.05"/>
                  </transformationPoint>
                </DOMSymbolInstance>
              </elements>
            </DOMFrame>
            <DOMFrame index="46" duration="4" tweenType="motion" motionTweenSnap="true" hasCustomEase="true" keyMode="22017" acceleration="100">
              <tweens>
                <CustomEase target="all">
                  <Point/>
                  <Point x="0.333333333333333"/>
                  <Point x="0.666666666666667" y="0.333333333333333"/>
                  <Point x="1" y="1"/>
                </CustomEase>
              </tweens>
              <elements>
                <DOMSymbolInstance libraryItemName="MovieClips/Weapons/Parts/WPN.M9.Gun" name="mc_gun" centerPoint3DX="4.25" centerPoint3DY="12.55">
                  <matrix>
                    <Matrix a="0.642776489257813" b="0.766036987304688" c="-0.766036987304688" d="0.642776489257813" tx="4.1" ty="12.5"/>
                  </matrix>
                  <transformationPoint>
                    <Point x="0.05"/>
                  </transformationPoint>
                </DOMSymbolInstance>
              </elements>
            </DOMFrame>
            <DOMFrame index="50" tweenType="motion" motionTweenSnap="true" keyMode="22017">
              <elements>
                <DOMSymbolInstance libraryItemName="MovieClips/Weapons/Parts/WPN.M9.Gun" name="mc_gun" centerPoint3DX="4.6" centerPoint3DY="7.75">
                  <matrix>
                    <Matrix a="0.768234252929688" b="0.640151977539063" c="-0.640151977539063" d="0.768234252929688" tx="4.5" ty="8.2"/>
                  </matrix>
                  <transformationPoint>
                    <Point x="0.1" y="-0.05"/>
                  </transformationPoint>
                </DOMSymbolInstance>
              </elements>
            </DOMFrame>
            <DOMFrame index="51" duration="4" tweenType="motion" motionTweenSnap="true" hasCustomEase="true" keyMode="22017" acceleration="-100">
              <tweens>
                <CustomEase target="all">
                  <Point/>
                  <Point x="0.333333333333333" y="0.666666666666667"/>
                  <Point x="0.666666666666667" y="1"/>
                  <Point x="1" y="1"/>
                </CustomEase>
              </tweens>
              <elements>
                <DOMSymbolInstance libraryItemName="MovieClips/Weapons/Parts/WPN.M9.Gun" name="mc_gun" centerPoint3DX="7.4" centerPoint3DY="8.2">
                  <matrix>
                    <Matrix a="0.704986572265625" b="0.709213256835938" c="-0.709213256835938" d="0.704986572265625" tx="7.45" ty="8.65"/>
                  </matrix>
                  <transformationPoint>
                    <Point x="0.05" y="-0.05"/>
                  </transformationPoint>
                </DOMSymbolInstance>
              </elements>
            </DOMFrame>
            <DOMFrame index="55" duration="4" tweenType="motion" motionTweenSnap="true" hasCustomEase="true" keyMode="22017" acceleration="100">
              <tweens>
                <CustomEase target="all">
                  <Point/>
                  <Point x="0.333333333333333"/>
                  <Point x="0.666666666666667" y="0.333333333333333"/>
                  <Point x="1" y="1"/>
                </CustomEase>
              </tweens>
              <elements>
                <DOMSymbolInstance libraryItemName="MovieClips/Weapons/Parts/WPN.M9.Gun" name="mc_gun" centerPoint3DX="9.85" centerPoint3DY="8.9">
                  <matrix>
                    <Matrix a="0.726303100585938" b="0.687347412109375" c="-0.687347412109375" d="0.726303100585938" tx="9.8" ty="9.7"/>
                  </matrix>
                  <transformationPoint>
                    <Point x="0.05" y="-0.05"/>
                  </transformationPoint>
                </DOMSymbolInstance>
              </elements>
            </DOMFrame>
            <DOMFrame index="59" duration="4" tweenType="motion" motionTweenSnap="true" hasCustomEase="true" keyMode="22017" acceleration="-100">
              <tweens>
                <CustomEase target="all">
                  <Point/>
                  <Point x="0.333333333333333" y="0.666666666666667"/>
                  <Point x="0.666666666666667" y="1"/>
                  <Point x="1" y="1"/>
                </CustomEase>
              </tweens>
              <elements>
                <DOMSymbolInstance libraryItemName="MovieClips/Weapons/Parts/WPN.M9.Gun" name="mc_gun" centerPoint3DX="5.7" centerPoint3DY="2.15">
                  <matrix>
                    <Matrix a="0.954925537109375" b="0.296737670898438" c="-0.296737670898438" d="0.954925537109375" tx="6.3" ty="3"/>
                  </matrix>
                  <transformationPoint>
                    <Point x="0.05" y="-0.05"/>
                  </transformationPoint>
                </DOMSymbolInstance>
              </elements>
            </DOMFrame>
            <DOMFrame index="63" keyMode="9728">
              <elements>
                <DOMSymbolInstance libraryItemName="MovieClips/Weapons/Parts/WPN.M9.Gun" name="mc_gun" centerPoint3DY="0.7">
                  <matrix>
                    <Matrix ty="0.75"/>
                  </matrix>
                  <transformationPoint>
                    <Point y="-0.05"/>
                  </transformationPoint>
                </DOMSymbolInstance>
              </elements>
            </DOMFrame>
          </frames>
        </DOMLayer>
        <DOMLayer name="mc_mag" color="#4F80FF" autoNamed="false">
          <frames>
            <DOMFrame index="0" keyMode="9728">
              <elements>
                <DOMSymbolInstance libraryItemName="MovieClips/Weapons/Parts/WPN.M9.Mag" name="mc_mag" centerPoint3DX="-10.95" centerPoint3DY="2.1">
                  <matrix>
                    <Matrix tx="-10.95" ty="2.1"/>
                  </matrix>
                  <transformationPoint>
                    <Point x="-0.15"/>
                  </transformationPoint>
                </DOMSymbolInstance>
              </elements>
            </DOMFrame>
            <DOMFrame index="1" duration="3" tweenType="motion" motionTweenSnap="true" hasCustomEase="true" keyMode="22017" acceleration="100">
              <tweens>
                <CustomEase target="all">
                  <Point/>
                  <Point x="0.333333333333333"/>
                  <Point x="0.666666666666667" y="0.333333333333333"/>
                  <Point x="1" y="1"/>
                </CustomEase>
              </tweens>
              <elements>
                <DOMSymbolInstance libraryItemName="MovieClips/Weapons/Parts/WPN.M9.Mag" name="mc_mag" centerPoint3DX="-17.35" centerPoint3DY="-0.8">
                  <matrix>
                    <Matrix a="0.9984130859375" b="-0.0563201904296875" c="0.0563201904296875" d="0.9984130859375" tx="-16.45" ty="-1.2"/>
                  </matrix>
                  <transformationPoint>
                    <Point x="-0.1"/>
                  </transformationPoint>
                </DOMSymbolInstance>
              </elements>
            </DOMFrame>
            <DOMFrame index="4" duration="4" tweenType="motion" motionTweenSnap="true" hasCustomEase="true" keyMode="22017" acceleration="-100">
              <tweens>
                <CustomEase target="all">
                  <Point/>
                  <Point x="0.333333333333333" y="0.666666666666667"/>
                  <Point x="0.666666666666667" y="1"/>
                  <Point x="1" y="1"/>
                </CustomEase>
              </tweens>
              <elements>
                <DOMSymbolInstance libraryItemName="MovieClips/Weapons/Parts/WPN.M9.Mag" name="mc_mag" centerPoint3DX="-12.2" centerPoint3DY="-3.6">
                  <matrix>
                    <Matrix a="0.991455078125" b="0.130340576171875" c="-0.130340576171875" d="0.991455078125" tx="-13.9" ty="0.75"/>
                  </matrix>
                  <transformationPoint>
                    <Point x="-0.15" y="0.05"/>
                  </transformationPoint>
                </DOMSymbolInstance>
              </elements>
            </DOMFrame>
            <DOMFrame index="8" keyMode="9728">
              <elements>
                <DOMSymbolInstance libraryItemName="MovieClips/Weapons/Parts/WPN.M9.Mag" name="mc_mag" centerPoint3DX="-10.95" centerPoint3DY="2.1">
                  <matrix>
                    <Matrix tx="-10.95" ty="2.1"/>
                  </matrix>
                  <transformationPoint>
                    <Point x="-0.15"/>
                  </transformationPoint>
                </DOMSymbolInstance>
              </elements>
            </DOMFrame>
            <DOMFrame index="9" duration="5" keyMode="9728">
              <elements>
                <DOMSymbolInstance libraryItemName="MovieClips/Weapons/Parts/WPN.M9.Mag" name="mc_mag" centerPoint3DX="-10.95" centerPoint3DY="2.1">
                  <matrix>
                    <Matrix tx="-10.95" ty="2.1"/>
                  </matrix>
                  <transformationPoint>
                    <Point x="-0.15"/>
                  </transformationPoint>
                </DOMSymbolInstance>
              </elements>
            </DOMFrame>
            <DOMFrame index="14" duration="4" tweenType="motion" motionTweenSnap="true" hasCustomEase="true" keyMode="22017" acceleration="100">
              <tweens>
                <CustomEase target="all">
                  <Point/>
                  <Point x="0.333333333333333"/>
                  <Point x="0.666666666666667" y="0.333333333333333"/>
                  <Point x="1" y="1"/>
                </CustomEase>
              </tweens>
              <elements>
                <DOMSymbolInstance libraryItemName="MovieClips/Weapons/Parts/WPN.M9.Mag" name="mc_mag" centerPoint3DX="-10.95" centerPoint3DY="2.1">
                  <matrix>
                    <Matrix tx="-10.95" ty="2.1"/>
                  </matrix>
                  <transformationPoint>
                    <Point x="-0.15"/>
                  </transformationPoint>
                </DOMSymbolInstance>
              </elements>
            </DOMFrame>
            <DOMFrame index="18" keyMode="9728">
              <elements>
                <DOMSymbolInstance libraryItemName="MovieClips/Weapons/Parts/WPN.M9.Mag" name="mc_mag" centerPoint3DX="-11.7" centerPoint3DY="0.1">
                  <matrix>
                    <Matrix a="0.9891357421875" b="-0.146942138671875" c="0.146942138671875" d="0.9891357421875" tx="-11.6"/>
                  </matrix>
                  <transformationPoint>
                    <Point x="-0.15" y="0.05"/>
                  </transformationPoint>
                </DOMSymbolInstance>
              </elements>
            </DOMFrame>
            <DOMFrame index="19" duration="11" keyMode="9728">
              <elements/>
            </DOMFrame>
            <DOMFrame index="30" duration="4" tweenType="motion" motionTweenSnap="true" hasCustomEase="true" keyMode="22017" acceleration="100">
              <tweens>
                <CustomEase target="all">
                  <Point/>
                  <Point x="0.333333333333333"/>
                  <Point x="0.666666666666667" y="0.333333333333333"/>
                  <Point x="1" y="1"/>
                </CustomEase>
              </tweens>
              <elements>
                <DOMSymbolInstance libraryItemName="MovieClips/Weapons/Parts/WPN.M9.Mag" name="mc_mag" centerPoint3DX="-53.8" centerPoint3DY="24.45">
                  <matrix>
                    <Matrix a="0.548110961914063" b="0.836395263671875" c="-0.836395263671875" d="0.548110961914063" tx="-53.75" ty="23.8"/>
                  </matrix>
                  <transformationPoint>
                    <Point x="-0.1"/>
                  </transformationPoint>
                </DOMSymbolInstance>
              </elements>
            </DOMFrame>
            <DOMFrame index="34" duration="4" tweenType="motion" motionTweenSnap="true" hasCustomEase="true" keyMode="22017" acceleration="-100">
              <tweens>
                <CustomEase target="all">
                  <Point/>
                  <Point x="0.333333333333333" y="0.666666666666667"/>
                  <Point x="0.666666666666667" y="1"/>
                  <Point x="1" y="1"/>
                </CustomEase>
              </tweens>
              <elements>
                <DOMSymbolInstance libraryItemName="MovieClips/Weapons/Parts/WPN.M9.Mag" name="mc_mag" centerPoint3DX="-38.65" centerPoint3DY="21.75">
                  <matrix>
                    <Matrix a="0.548110961914063" b="0.836395263671875" c="-0.836395263671875" d="0.548110961914063" tx="-38.6" ty="21.1"/>
                  </matrix>
                  <transformationPoint>
                    <Point x="-0.1"/>
                  </transformationPoint>
                </DOMSymbolInstance>
              </elements>
            </DOMFrame>
            <DOMFrame index="38" duration="3" tweenType="motion" motionTweenSnap="true" hasCustomEase="true" keyMode="22017" acceleration="99">
              <tweens>
                <CustomEase target="all">
                  <Point/>
                  <Point x="0.333333333333333" y="0.00333333333333334"/>
                  <Point x="0.666666666666667" y="0.336666666666667"/>
                  <Point x="1" y="1"/>
                </CustomEase>
              </tweens>
              <elements>
                <DOMSymbolInstance libraryItemName="MovieClips/Weapons/Parts/WPN.M9.Mag" name="mc_mag" centerPoint3DX="-26.55" centerPoint3DY="13.8">
                  <matrix>
                    <Matrix a="0.46136474609375" b="0.88720703125" c="-0.88720703125" d="0.46136474609375" tx="-26.6" ty="13.4"/>
                  </matrix>
                  <transformationPoint>
                    <Point x="-0.15" y="0.05"/>
                  </transformationPoint>
                </DOMSymbolInstance>
              </elements>
            </DOMFrame>
            <DOMFrame index="41" tweenType="motion" motionTweenSnap="true" keyMode="22017">
              <elements>
                <DOMSymbolInstance libraryItemName="MovieClips/Weapons/Parts/WPN.M9.Mag" name="mc_mag" centerPoint3DX="-17.7" centerPoint3DY="8.7">
                  <matrix>
                    <Matrix a="0.342254638671875" b="0.939605712890625" c="-0.939605712890625" d="0.342254638671875" tx="-17.65" ty="8.5"/>
                  </matrix>
                  <transformationPoint>
                    <Point x="-0.15" y="0.05"/>
                  </transformationPoint>
                </DOMSymbolInstance>
              </elements>
            </DOMFrame>
            <DOMFrame index="42" duration="4" tweenType="motion" motionTweenSnap="true" hasCustomEase="true" keyMode="22017" acceleration="-100">
              <tweens>
                <CustomEase target="all">
                  <Point/>
                  <Point x="0.333333333333333" y="0.666666666666667"/>
                  <Point x="0.666666666666667" y="1"/>
                  <Point x="1" y="1"/>
                </CustomEase>
              </tweens>
              <elements>
                <DOMSymbolInstance libraryItemName="MovieClips/Weapons/Parts/WPN.M9.Mag" name="mc_mag" centerPoint3DX="-7.9" centerPoint3DY="5.15">
                  <matrix>
                    <Matrix a="0.52301025390625" b="0.852310180664063" c="-0.852310180664063" d="0.52301025390625" tx="-7.5" ty="5.1"/>
                  </matrix>
                  <transformationPoint>
                    <Point x="-0.1"/>
                  </transformationPoint>
                </DOMSymbolInstance>
              </elements>
            </DOMFrame>
            <DOMFrame index="46" duration="4" tweenType="motion" motionTweenSnap="true" hasCustomEase="true" keyMode="22017" acceleration="100">
              <tweens>
                <CustomEase target="all">
                  <Point/>
                  <Point x="0.333333333333333"/>
                  <Point x="0.666666666666667" y="0.333333333333333"/>
                  <Point x="1" y="1"/>
                </CustomEase>
              </tweens>
              <elements>
                <DOMSymbolInstance libraryItemName="MovieClips/Weapons/Parts/WPN.M9.Mag" name="mc_mag" centerPoint3DX="-4.15" centerPoint3DY="5.1">
                  <matrix>
                    <Matrix a="0.642776489257813" b="0.766036987304688" c="-0.766036987304688" d="0.642776489257813" tx="-3.9" ty="5"/>
                  </matrix>
                  <transformationPoint>
                    <Point x="-0.15"/>
                  </transformationPoint>
                </DOMSymbolInstance>
              </elements>
            </DOMFrame>
            <DOMFrame index="50" tweenType="motion" motionTweenSnap="true" keyMode="22017">
              <elements>
                <DOMSymbolInstance libraryItemName="MovieClips/Weapons/Parts/WPN.M9.Mag" name="mc_mag" centerPoint3DX="-4.1" centerPoint3DY="2.85">
                  <matrix>
                    <Matrix a="0.768234252929688" b="0.640151977539063" c="-0.640151977539063" d="0.768234252929688" tx="-4.65" ty="2.2"/>
                  </matrix>
                  <transformationPoint>
                    <Point x="-0.2"/>
                  </transformationPoint>
                </DOMSymbolInstance>
              </elements>
            </DOMFrame>
            <DOMFrame index="51" duration="4" tweenType="motion" motionTweenSnap="true" hasCustomEase="true" keyMode="22017" acceleration="-100">
              <tweens>
                <CustomEase target="all">
                  <Point/>
                  <Point x="0.333333333333333" y="0.666666666666667"/>
                  <Point x="0.666666666666667" y="1"/>
                  <Point x="1" y="1"/>
                </CustomEase>
              </tweens>
              <elements>
                <DOMSymbolInstance libraryItemName="MovieClips/Weapons/Parts/WPN.M9.Mag" name="mc_mag" centerPoint3DX="-1.25" centerPoint3DY="1.95">
                  <matrix>
                    <Matrix a="0.704986572265625" b="0.709213256835938" c="-0.709213256835938" d="0.704986572265625" tx="-1.2" ty="1.9"/>
                  </matrix>
                  <transformationPoint>
                    <Point x="-0.15"/>
                  </transformationPoint>
                </DOMSymbolInstance>
              </elements>
            </DOMFrame>
            <DOMFrame index="55" duration="4" tweenType="motion" motionTweenSnap="true" hasCustomEase="true" keyMode="22017" acceleration="100">
              <tweens>
                <CustomEase target="all">
                  <Point/>
                  <Point x="0.333333333333333"/>
                  <Point x="0.666666666666667" y="0.333333333333333"/>
                  <Point x="1" y="1"/>
                </CustomEase>
              </tweens>
              <elements>
                <DOMSymbolInstance libraryItemName="MovieClips/Weapons/Parts/WPN.M9.Mag" name="mc_mag" centerPoint3DX="1.2" centerPoint3DY="3.4">
                  <matrix>
                    <Matrix a="0.726303100585938" b="0.687347412109375" c="-0.687347412109375" d="0.726303100585938" tx="0.9" ty="3.25"/>
                  </matrix>
                  <transformationPoint>
                    <Point x="-0.2" y="-0.05"/>
                  </transformationPoint>
                </DOMSymbolInstance>
              </elements>
            </DOMFrame>
            <DOMFrame index="59" duration="4" tweenType="motion" motionTweenSnap="true" hasCustomEase="true" keyMode="22017" acceleration="-100">
              <tweens>
                <CustomEase target="all">
                  <Point/>
                  <Point x="0.333333333333333" y="0.666666666666667"/>
                  <Point x="0.666666666666667" y="1"/>
                  <Point x="1" y="1"/>
                </CustomEase>
              </tweens>
              <elements>
                <DOMSymbolInstance libraryItemName="MovieClips/Weapons/Parts/WPN.M9.Mag" name="mc_mag" centerPoint3DX="-4.45" centerPoint3DY="0.1">
                  <matrix>
                    <Matrix a="0.954925537109375" b="0.296737670898438" c="-0.296737670898438" d="0.954925537109375" tx="-4.45" ty="1.05"/>
                  </matrix>
                  <transformationPoint>
                    <Point x="-0.2"/>
                  </transformationPoint>
                </DOMSymbolInstance>
              </elements>
            </DOMFrame>
            <DOMFrame index="63" keyMode="9728">
              <elements>
                <DOMSymbolInstance libraryItemName="MovieClips/Weapons/Parts/WPN.M9.Mag" name="mc_mag" centerPoint3DX="-10.95" centerPoint3DY="2.1">
                  <matrix>
                    <Matrix tx="-10.95" ty="2.1"/>
                  </matrix>
                  <transformationPoint>
                    <Point x="-0.15"/>
                  </transformationPoint>
                </DOMSymbolInstance>
              </elements>
            </DOMFrame>
          </frames>
        </DOMLayer>
      </layers>
    </DOMTimeline>
  </timeline>
</DOMSymbolItem>