<DOMSymbolItem xmlns:xsi="http://www.w3.org/2001/XMLSchema-instance" xmlns="http://ns.adobe.com/xfl/2008/" name="MovieClips/Equipment/Parts/WPN.CONCUSSION.Grenade" itemID="52ba2af5-000018c4" lastModified="1409523732">
  <timeline>
    <DOMTimeline name="WPN.CONCUSSION.Grenade">
      <layers>
        <DOMLayer name="Layer 1" color="#4FFF4F" current="true" isSelected="true">
          <frames>
            <DOMFrame index="0" keyMode="9728">
              <elements>
                <DOMShape>
                  <fills>
                    <FillStyle index="1">
                      <SolidColor color="#272727"/>
                    </FillStyle>
                    <FillStyle index="2">
                      <SolidColor color="#191919"/>
                    </FillStyle>
                    <FillStyle index="3">
                      <SolidColor color="#7F4242"/>
                    </FillStyle>
                    <FillStyle index="4">
                      <SolidColor color="#743C3C"/>
                    </FillStyle>
                  </fills>
                  <strokes>
                    <StrokeStyle index="1">
                      <SolidStroke scaleMode="normal" caps="none" weight="0.05" pixelHinting="true" joints="miter" solidStyle="hairline">
                        <fill>
                          <SolidColor alpha="0.247058823529412"/>
                        </fill>
                      </SolidStroke>
                    </StrokeStyle>
                  </strokes>
                  <edges>
                    <Edge fillStyle0="1" strokeStyle="1" edges="!53 -179|48 -190!48 -190|51 -197!51 -197|76 -197!76 -197|80 -188!80 -188|80 -171!80 -171|72 -152"/>
                    <Edge fillStyle1="1" strokeStyle="1" edges="!43 -201|48 -204!48 -204|80 -204!80 -204|89 -186!89 -186|89 -173!89 -173|79 -148"/>
                    <Edge fillStyle1="2" strokeStyle="1" edges="!-20 -216|32 -216!32 -216|39 -210!39 -210|43 -201"/>
                    <Edge fillStyle0="2" fillStyle1="1" strokeStyle="1" edges="!46 -150|44 -166!44 -166|30 -178!30 -178|30 -185"/>
                    <Edge fillStyle1="1" strokeStyle="1" edges="!20 -150|20 -138"/>
                    <Edge fillStyle0="1" fillStyle1="2" strokeStyle="1" edges="!20 -150|5 -150"/>
                    <Edge fillStyle1="2" strokeStyle="1" edges="!46 -150|20 -150!20 -138|47 -138!47 -138|51 -135"/>
                    <Edge fillStyle0="2" fillStyle1="2" strokeStyle="1" edges="!30 -185|3 -185!3 -185|-20 -198!-20 -198|-20 -216!-37 -129|3 -135!3 -135|39 -129"/>
                    <Edge fillStyle0="2" strokeStyle="1" edges="!72 -152|62 -160!62 -160|53 -179"/>
                    <Edge fillStyle0="1" fillStyle1="2" strokeStyle="1" edges="!54 -148|51 -166!51 -166|53 -179"/>
                    <Edge fillStyle1="2" strokeStyle="1" edges="!68 -141[62 -146 54 -148"/>
                    <Edge fillStyle0="1" strokeStyle="1" edges="!68 -141|66 -134!66 -134|54 -148"/>
                    <Edge fillStyle1="1" strokeStyle="1" edges="!73 -134|72 -128!72 -128|64 -125!64 -125|46 -150"/>
                    <Edge fillStyle1="2" strokeStyle="1" edges="!51 -135|59 -125!59 -125|59 -78!59 -78|51 -69"/>
                    <Edge fillStyle0="1" fillStyle1="2" strokeStyle="1" edges="!72 -152|68 -141"/>
                    <Edge fillStyle1="2" strokeStyle="1" edges="!79 -148|85 -144!85 -144|92 -132!92 -132|92 69!92 69|89 73!89 73|48 73!48 73|48 66!48 66|71 66!71 66|76 59!76 59|76 -128!76 -128[76 -131 73 -134"/>
                    <Edge fillStyle0="2" fillStyle1="1" strokeStyle="1" edges="!79 -148|73 -134!30 -185|43 -201"/>
                    <Edge fillStyle0="2" fillStyle1="2" strokeStyle="1" edges="!39 -129|51 -135"/>
                    <Edge fillStyle0="2" fillStyle1="3" strokeStyle="1" edges="!-73 -60|1 -60"/>
                    <Edge fillStyle0="2" fillStyle1="4" strokeStyle="1" edges="!1 -60|44 -60"/>
                    <Edge fillStyle0="2" fillStyle1="2" strokeStyle="1" edges="!39 -78|2 -72!2 -72|-37 -78!51 -69|39 -78"/>
                    <Edge fillStyle1="2" strokeStyle="1" edges="!51 -69|44 -60"/>
                    <Edge fillStyle0="2" fillStyle1="2" strokeStyle="1" edges="!39 -129|39 -78"/>
                    <Edge fillStyle1="2" strokeStyle="1" edges="!52 147|60 154!60 154|60 203!60 203|48 212"/>
                    <Edge fillStyle0="3" fillStyle1="2" strokeStyle="1" edges="!-73 140|2 140"/>
                    <Edge fillStyle0="4" fillStyle1="2" strokeStyle="1" edges="!2 140|44 140"/>
                    <Edge fillStyle0="2" fillStyle1="2" strokeStyle="1" edges="!-37 159|1 151!1 151|39 158!39 207|2 212!2 212|-31 208!-31 208|-37 208"/>
                    <Edge fillStyle1="2" strokeStyle="1" edges="!48 212|42 217!42 217|-76 217!-76 217|-91 206"/>
                    <Edge fillStyle0="2" fillStyle1="2" strokeStyle="1" edges="!48 212|39 207!39 158|39 207"/>
                    <Edge fillStyle1="2" strokeStyle="1" edges="!44 140|52 147"/>
                    <Edge fillStyle0="2" fillStyle1="2" strokeStyle="1" edges="!39 158|52 147"/>
                    <Edge fillStyle0="4" fillStyle1="3" edges="!1 -60|2 140"/>
                    <Edge fillStyle1="4" strokeStyle="1" edges="!44 -60|44 140"/>
                    <Edge fillStyle1="2" strokeStyle="1" edges="!-33 -216|-20 -216"/>
                    <Edge fillStyle1="1" strokeStyle="1" edges="!-44 -150|-44 -180!-44 -180|-53 -184!-53 -184[-59 -193 -53 -204!-53 -204|-40 -216!-40 -216|-33 -216"/>
                    <Edge fillStyle0="2" fillStyle1="2" strokeStyle="1" edges="!-92 -128|-63 -134!-63 -134|-37 -129"/>
                    <Edge fillStyle1="2" strokeStyle="1" edges="!-92 -128|-75 -138!-75 -138|-48 -138"/>
                    <Edge fillStyle0="2" fillStyle1="2" strokeStyle="1" edges="!5 -150|-10 -181!-10 -181|-29 -150"/>
                    <Edge fillStyle0="1" fillStyle1="1" strokeStyle="1" edges="!-33 -150|-44 -150"/>
                    <Edge fillStyle0="1" fillStyle1="2" strokeStyle="1" edges="!-29 -150|-33 -150"/>
                    <Edge fillStyle1="1" strokeStyle="1" edges="!-48 -138|-48 -150!-48 -150|-44 -150"/>
                    <Edge fillStyle0="1" fillStyle1="2" strokeStyle="1" edges="!-33 -150|-33 -216"/>
                    <Edge fillStyle0="2" fillStyle1="2" strokeStyle="1" edges="!-37 -78|-64 -72!-64 -72|-92 -77"/>
                    <Edge fillStyle1="2" strokeStyle="1" edges="!-73 -60|-92 -77"/>
                    <Edge fillStyle0="2" fillStyle1="2" strokeStyle="1" edges="!-37 -78|-37 -129"/>
                    <Edge fillStyle1="2" strokeStyle="1" edges="!-92 -77|-92 -128"/>
                    <Edge fillStyle0="2" fillStyle1="2" strokeStyle="1" edges="!-37 208|-37 159!-37 208|-64 212!-64 212|-91 206!-91 155|-37 159"/>
                    <Edge fillStyle1="2" strokeStyle="1" edges="!-91 155|-73 140!-91 206|-91 155"/>
                    <Edge fillStyle1="3" strokeStyle="1" edges="!-73 140|-73 -60"/>
                    <Edge fillStyle0="2" fillStyle1="1" strokeStyle="1" edges="!20 -138|-48 -138"/>
                    <Edge fillStyle0="1" fillStyle1="2" strokeStyle="1" edges="!5 -150|-29 -150"/>
                    <Edge cubics="!51 -197(51,-197;51,-197 76,-197 76,-197q51 -197 76 -197);"/>
                    <Edge cubics="!76 -197(76,-197;76,-197 80,-188 80,-188q76 -197 80 -188);"/>
                    <Edge cubics="!80 -204(;80,-204 89,-186 89,-186q80 -204 89 -186);"/>
                    <Edge cubics="!43 -201(;43,-201 48,-204 48,-204p43 -201q48 -204);"/>
                    <Edge cubics="!32 -216(;32,-216 39,-210 39,-210q32 -216 39 -210);"/>
                    <Edge cubics="!39 -210(;39,-210 43,-201 43,-201q39 -210p43 -201);"/>
                    <Edge cubics="!30 -185(;30,-185 30,-178 30,-178p30 -185q30 -178);"/>
                    <Edge cubics="!30 -178(;30,-178 44,-166 44,-166q30 -178 44 -166);"/>
                    <Edge cubics="!20 -150(;20,-150 20,-138 20,-138p20 -150 20 -138);"/>
                    <Edge cubics="!20 -150(;20,-150 5,-150 5,-150p20 -150 5 -150);"/>
                    <Edge cubics="!46 -150(;46,-150 20,-150 20,-150p46 -150 20 -150);"/>
                    <Edge cubics="!20 -138(;20,-138 47,-138 47,-138p20 -138q47 -138);"/>
                    <Edge cubics="!44 -166(;44,-166 46,-150 46,-150q44 -166p46 -150);"/>
                    <Edge cubics="!3 -135(;3,-135 39,-129 39,-129q3 -135p39 -129);"/>
                    <Edge cubics="!3 -185(;3,-185 30,-185 30,-185q3 -185p30 -185);"/>
                    <Edge cubics="!53 -179(;53,-179 62,-160 62,-160p53 -179q62 -160);"/>
                    <Edge cubics="!51 -166(;51,-166 53,-179 53,-179q51 -166p53 -179);"/>
                    <Edge cubics="!68 -141(;64,-144 59,-147 54,-148p68 -141Q62 -146p54 -148);"/>
                    <Edge cubics="!51 -135(;51,-135 59,-125 59,-125p51 -135q59 -125);"/>
                    <Edge cubics="!72 -128(;72,-128 64,-125 64,-125q72 -128 64 -125);"/>
                    <Edge cubics="!73 -134(;73,-134 72,-128 72,-128p73 -134q72 -128);"/>
                    <Edge cubics="!72 -152(;72,-152 68,-141 68,-141p72 -152 68 -141);"/>
                    <Edge cubics="!68 -141(;68,-141 66,-134 66,-134p68 -141q66 -134);"/>
                    <Edge cubics="!66 -134(;66,-134 54,-148 54,-148q66 -134p54 -148);"/>
                    <Edge cubics="!85 -144(;85,-144 92,-132 92,-132q85 -144 92 -132);"/>
                    <Edge cubics="!79 -148(;79,-148 85,-144 85,-144p79 -148q85 -144);"/>
                    <Edge cubics="!89 -173(;89,-173 79,-148 79,-148q89 -173p79 -148);"/>
                    <Edge cubics="!54 -148(;54,-148 51,-166 51,-166p54 -148q51 -166);"/>
                    <Edge cubics="!80 -171(80,-171;80,-171 72,-152 72,-152q80 -171p72 -152);"/>
                    <Edge cubics="!76 -128(76,-128;76,-130 75,-132 73,-134q76 -128Q76 -131p73 -134);"/>
                    <Edge cubics="!62 -160(;62,-160 72,-152 72,-152q62 -160p72 -152);"/>
                    <Edge cubics="!79 -148(;79,-148 73,-134 73,-134p79 -148 73 -134);"/>
                    <Edge cubics="!53 -179(;53,-179 48,-190 48,-190p53 -179q48 -190);"/>
                    <Edge cubics="!48 -190(;48,-190 51,-197 51,-197q48 -190 51 -197);"/>
                    <Edge cubics="!80 -188(;80,-188 80,-171 80,-171q80 -188 80 -171);"/>
                    <Edge cubics="!48 -204(;48,-204 80,-204 80,-204q48 -204 80 -204);"/>
                    <Edge cubics="!89 -186(;89,-186 89,-173 89,-173q89 -186 89 -173);"/>
                    <Edge cubics="!64 -125(;64,-125 46,-150 46,-150q64 -125p46 -150);"/>
                    <Edge cubics="!47 -138(;47,-138 51,-135 51,-135q47 -138p51 -135);"/>
                    <Edge cubics="!43 -201(;43,-201 30,-185 30,-185p43 -201 30 -185);"/>
                    <Edge cubics="!39 -129(;39,-129 51,-135 51,-135p39 -129 51 -135);"/>
                    <Edge cubics="!59 -78(;59,-78 51,-69 51,-69q59 -78p51 -69);"/>
                    <Edge cubics="!39 -78(;39,-78 2,-72 2,-72p39 -78q2 -72);"/>
                    <Edge cubics="!36 -20(;36,-15 35,-10 33,-7q36 -20Q36 -12q33 -7);"/>
                    <Edge cubics="!16 -7(;13,-10 11,-15 11,-20q16 -7Q11 -12q11 -20);"/>
                    <Edge cubics="!11 -20(;11,-25 13,-30 16,-33q11 -20Q11 -28q16 -33);"/>
                    <Edge cubics="!16 -33(;19,-38 21,-40 24,-40q16 -33Q20 -40q24 -40);"/>
                    <Edge cubics="!24 -40(;28,-40 31,-38 33,-33q24 -40Q30 -40q33 -33);"/>
                    <Edge cubics="!33 -33(;35,-30 36,-25 36,-20q33 -33Q36 -28q36 -20);"/>
                    <Edge cubics="!51 -69(;51,-69 39,-78 39,-78p51 -69 39 -78);"/>
                    <Edge cubics="!51 -69(51,-69;51,-69 44,-60 44,-60p51 -69 44 -60);"/>
                    <Edge cubics="!59 -125(;59,-125 59,-78 59,-78q59 -125 59 -78);"/>
                    <Edge cubics="!39 -78(;39,-78 39,-129 39,-129p39 -78 39 -129);"/>
                    <Edge cubics="!36 38(;36,43 35,48 33,52q36 38Q36 46q33 52);"/>
                    <Edge cubics="!33 24(;35,29 36,33 36,38q33 24Q36 31q36 38);"/>
                    <Edge cubics="!24 19(;28,19 31,21 33,24q24 19Q30 19q33 24);"/>
                    <Edge cubics="!16 24(;19,21 21,19 24,19q16 24Q20 19q24 19);"/>
                    <Edge cubics="!33 52(;31,56 28,58 24,58q33 52Q30 58q24 58);"/>
                    <Edge cubics="!24 58(;21,58 19,56 16,52q24 58Q20 58q16 52);"/>
                    <Edge cubics="!16 52(16,52;13,48 11,43 11,38q16 52Q11 46q11 38);"/>
                    <Edge cubics="!11 38(11,38;11,33 13,29 16,24q11 38Q11 31q16 24);"/>
                    <Edge cubics="!48 73(;48,73 48,66 48,66q48 73 48 66);"/>
                    <Edge cubics="!16 85(16,85;19,81 21,79 24,79q16 85Q20 79q24 79);"/>
                    <Edge cubics="!24 119(;21,119 19,117 16,112q24 119Q20 119q16 112);"/>
                    <Edge cubics="!16 112(;13,109 11,104 11,99q16 112Q11 107q11 99);"/>
                    <Edge cubics="!36 99(;36,104 35,109 33,112q36 99Q36 107q33 112);"/>
                    <Edge cubics="!24 79(24,79;28,79 31,81 33,85q24 79Q30 79q33 85);"/>
                    <Edge cubics="!33 85(;35,89 36,94 36,99q33 85Q36 91q36 99);"/>
                    <Edge cubics="!33 112(;31,117 28,119 24,119q33 112Q30 119q24 119);"/>
                    <Edge cubics="!11 99(;11,94 13,89 16,85q11 99Q11 91q16 85);"/>
                    <Edge cubics="!92 69(;92,69 89,73 89,73q92 69 89 73);"/>
                    <Edge cubics="!89 73(;89,73 48,73 48,73q89 73 48 73);"/>
                    <Edge cubics="!48 66(;48,66 71,66 71,66q48 66 71 66);"/>
                    <Edge cubics="!71 66(;71,66 76,59 76,59q71 66 76 59);"/>
                    <Edge cubics="!52 147(;52,147 60,154 60,154p52 147q60 154);"/>
                    <Edge cubics="!1 151(1,151;1,151 39,158 39,158q1 151p39 158)39,158;"/>
                    <Edge cubics="!39 207(39,207;39,207 2,212 2,212p39 207q2 212);"/>
                    <Edge cubics="!48 212(48,212;48,212 39,207 39,207p48 212 39 207);"/>
                    <Edge cubics="!48 212(48,212;48,212 42,217 42,217p48 212q42 217);"/>
                    <Edge cubics="!39 158(;39,158 39,207 39,207p39 158 39 207);"/>
                    <Edge cubics="!60 154(60,154;60,154 60,203 60,203q60 154 60 203);"/>
                    <Edge cubics="!60 203(;60,203 48,212 48,212q60 203p48 212);"/>
                    <Edge cubics="!39 158(;39,158 52,147 52,147p39 158 52 147);"/>
                    <Edge cubics="!44 140(;44,140 52,147 52,147p44 140 52 147);"/>
                    <Edge cubics="!92 -132(92,-132;92,-132 92,69 92,69q92 -132 92 69)92,69;"/>
                    <Edge cubics="!76 59(;76,59 76,-128 76,-128q76 59 76 -128);"/>
                    <Edge cubics="!44 -60(44,-60;44,-60 44,140 44,140p44 -60 44 140);"/>
                    <Edge cubics="!33 -7(;31,-2 28,0 24,0q33 -7Q30 0q24 0);"/>
                    <Edge cubics="!24 0(24,0;21,0 19,-2 16,-7q24 0Q20 0q16 -7);"/>
                    <Edge cubics="!-40 -216(-40,-216;-40,-216 -33,-216 -33,-216q-40 -216p-33 -216);"/>
                    <Edge cubics="!-33 -216(;-33,-216 -20,-216 -20,-216p-33 -216 -20 -216);"/>
                    <Edge cubics="!-20 -216(-20,-216;-20,-216 -20,-198 -20,-198p-20 -216q-20 -198);"/>
                    <Edge cubics="!-92 -128(;-92,-128 -75,-138 -75,-138p-92 -128q-75 -138);"/>
                    <Edge cubics="!-92 -128(;-92,-128 -63,-134 -63,-134p-92 -128q-63 -134);"/>
                    <Edge cubics="!-48 -138(;-48,-138 -48,-150 -48,-150p-48 -138q-48 -150);"/>
                    <Edge cubics="!-48 -150(;-48,-150 -44,-150 -44,-150q-48 -150p-44 -150);"/>
                    <Edge cubics="!-44 -150(;-44,-150 -44,-180 -44,-180p-44 -150q-44 -180);"/>
                    <Edge cubics="!-29 -150(;-29,-150 -33,-150 -33,-150p-29 -150 -33 -150);"/>
                    <Edge cubics="!-33 -150(;-33,-150 -44,-150 -44,-150p-33 -150 -44 -150);"/>
                    <Edge cubics="!-29 -150(;-29,-150 -10,-181 -10,-181p-29 -150q-10 -181);"/>
                    <Edge cubics="!-53 -204(;-53,-204 -40,-216 -40,-216q-53 -204 -40 -216);"/>
                    <Edge cubics="!-53 -184(;-57,-190 -57,-197 -53,-204q-53 -184Q-59 -193q-53 -204);"/>
                    <Edge cubics="!-44 -180(;-44,-180 -53,-184 -53,-184q-44 -180 -53 -184);"/>
                    <Edge cubics="!-75 -138(;-75,-138 -48,-138 -48,-138q-75 -138p-48 -138);"/>
                    <Edge cubics="!-63 -134(-63,-134;-63,-134 -37,-129 -37,-129q-63 -134p-37 -129);"/>
                    <Edge cubics="!-33 -216(-33,-216;-33,-216 -33,-150 -33,-150p-33 -216 -33 -150);"/>
                    <Edge cubics="!-64 -72(-64,-72;-64,-72 -92,-77 -92,-77q-64 -72p-92 -77);"/>
                    <Edge cubics="!-73 -38(;-73,-38 -73,-60 -73,-60p-73 -38 -73 -60);"/>
                    <Edge cubics="!-73 -2(-73,-2;-73,-2 -73,-38 -73,-38p-73 -2 -73 -38)-73,-38;"/>
                    <Edge cubics="!-73 -2(;-72,-3 -71,-5 -69,-7p-73 -2Q-72 -4q-69 -7);"/>
                    <Edge cubics="!-69 -7(;-66,-10 -65,-15 -65,-20q-69 -7Q-65 -12q-65 -20);"/>
                    <Edge cubics="!-65 -20(;-65,-25 -66,-30 -69,-33q-65 -20Q-65 -28q-69 -33);"/>
                    <Edge cubics="!-69 -33(;-71,-36 -72,-37 -73,-38q-69 -33Q-72 -37p-73 -38);"/>
                    <Edge cubics="!-48 -33(-48,-33;-45,-38 -40,-40 -34,-40q-48 -33Q-43 -40q-34 -40)-34,-40;"/>
                    <Edge cubics="!-34 -40(;-29,-40 -24,-38 -20,-33q-34 -40Q-26 -40q-20 -33);"/>
                    <Edge cubics="!-15 -20(;-15,-15 -17,-10 -20,-7q-15 -20Q-15 -12q-20 -7);"/>
                    <Edge cubics="!-20 -33(-20,-33;-17,-30 -15,-25 -15,-20q-20 -33Q-15 -28q-15 -20);"/>
                    <Edge cubics="!-37 -78(;-37,-78 -64,-72 -64,-72p-37 -78q-64 -72);"/>
                    <Edge cubics="!-73 -60(-73,-60;-73,-60 -92,-77 -92,-77p-73 -60 -92 -77)-92,-77;"/>
                    <Edge cubics="!-48 -7(;-51,-10 -53,-15 -53,-20q-48 -7Q-53 -12q-53 -20);"/>
                    <Edge cubics="!-53 -20(;-53,-25 -51,-30 -48,-33q-53 -20Q-53 -28q-48 -33);"/>
                    <Edge cubics="!-92 -77(;-92,-77 -92,-128 -92,-128p-92 -77 -92 -128);"/>
                    <Edge cubics="!-37 -129(;-37,-129 -37,-78 -37,-78p-37 -129 -37 -78);"/>
                    <Edge cubics="!-15 38(;-15,43 -17,48 -20,52q-15 38Q-15 46q-20 52);"/>
                    <Edge cubics="!-20 24(;-17,29 -15,33 -15,38q-20 24Q-15 31q-15 38);"/>
                    <Edge cubics="!-34 19(-34,19;-29,19 -24,21 -20,24q-34 19Q-26 19q-20 24);"/>
                    <Edge cubics="!-48 24(;-45,21 -40,19 -34,19q-48 24Q-43 19q-34 19);"/>
                    <Edge cubics="!-20 52(;-24,56 -29,58 -34,58q-20 52Q-26 58q-34 58);"/>
                    <Edge cubics="!-34 58(;-40,58 -45,56 -48,52q-34 58Q-43 58q-48 52);"/>
                    <Edge cubics="!-73 57(;-73,57 -73,20 -73,20p-73 57 -73 20);"/>
                    <Edge cubics="!-73 20(-73,20;-72,21 -71,22 -69,24p-73 20Q-72 21q-69 24);"/>
                    <Edge cubics="!-69 24(;-66,29 -65,33 -65,38q-69 24Q-65 31q-65 38);"/>
                    <Edge cubics="!-65 38(-65,38;-65,43 -66,48 -69,52q-65 38Q-65 46q-69 52);"/>
                    <Edge cubics="!-69 52(-69,52;-71,54 -72,56 -73,57q-69 52Q-72 55p-73 57)-73,57;"/>
                    <Edge cubics="!-73 117(;-73,117 -73,81 -73,81p-73 117 -73 81);"/>
                    <Edge cubics="!-73 81(-73,81;-72,82 -71,84 -69,85p-73 81Q-72 83q-69 85);"/>
                    <Edge cubics="!-69 85(-69,85;-66,89 -65,94 -65,99q-69 85Q-65 91q-65 99);"/>
                    <Edge cubics="!-65 99(;-65,104 -66,109 -69,112q-65 99Q-65 107q-69 112);"/>
                    <Edge cubics="!-69 112(-69,112;-71,114 -72,116 -73,117q-69 112Q-72 115p-73 117);"/>
                    <Edge cubics="!-34 119(-34,119;-40,119 -45,117 -48,112q-34 119Q-43 119q-48 112);"/>
                    <Edge cubics="!-48 85(-48,85;-45,81 -40,79 -34,79q-48 85Q-43 79q-34 79);"/>
                    <Edge cubics="!-34 79(-34,79;-29,79 -24,81 -20,85q-34 79Q-26 79q-20 85);"/>
                    <Edge cubics="!-20 85(-20,85;-17,89 -15,94 -15,99q-20 85Q-15 91q-15 99);"/>
                    <Edge cubics="!-15 99(;-15,104 -17,109 -20,112q-15 99Q-15 107q-20 112);"/>
                    <Edge cubics="!-20 112(-20,112;-24,117 -29,119 -34,119q-20 112Q-26 119q-34 119);"/>
                    <Edge cubics="!-53 38(;-53,33 -51,29 -48,24q-53 38Q-53 31q-48 24);"/>
                    <Edge cubics="!-48 52(;-51,48 -53,43 -53,38q-48 52Q-53 46q-53 38);"/>
                    <Edge cubics="!-73 81(;-73,81 -73,57 -73,57p-73 81 -73 57);"/>
                    <Edge cubics="!-48 112(;-51,109 -53,104 -53,99q-48 112Q-53 107q-53 99);"/>
                    <Edge cubics="!-53 99(-53,99;-53,94 -51,89 -48,85q-53 99Q-53 91q-48 85);"/>
                    <Edge cubics="!-91 155(-91,155;-91,155 -73,140 -73,140p-91 155 -73 140);"/>
                    <Edge cubics="!-64 212(;-64,212 -91,206 -91,206q-64 212p-91 206);"/>
                    <Edge cubics="!-76 217(;-76,217 -91,206 -91,206q-76 217p-91 206);"/>
                    <Edge cubics="!-31 208(;-31,208 -37,208 -37,208q-31 208p-37 208);"/>
                    <Edge cubics="!-37 159(;-37,159 -37,208 -37,208p-37 159 -37 208);"/>
                    <Edge cubics="!-37 208(;-37,208 -64,212 -64,212p-37 208q-64 212);"/>
                    <Edge cubics="!-91 206(;-91,206 -91,155 -91,155p-91 206 -91 155);"/>
                    <Edge cubics="!-91 155(;-91,155 -37,159 -37,159p-91 155 -37 159);"/>
                    <Edge cubics="!-73 140(;-73,140 -73,117 -73,117p-73 140 -73 117);"/>
                    <Edge cubics="!-73 20(;-73,20 -73,-2 -73,-2p-73 20 -73 -2);"/>
                    <Edge cubics="!-20 -7(-20,-7;-24,-2 -29,0 -34,0q-20 -7Q-26 0q-34 0);"/>
                    <Edge cubics="!-34 0(-34,0;-40,0 -45,-2 -48,-7q-34 0Q-43 0q-48 -7);"/>
                    <Edge cubics="!2 212(;2,212 -31,208 -31,208q2 212 -31 208);"/>
                    <Edge cubics="!-37 159(;-37,159 1,151 1,151p-37 159q1 151);"/>
                    <Edge cubics="!42 217(;42,217 -76,217 -76,217q42 217 -76 217);"/>
                    <Edge cubics="!-20 -216(;-20,-216 32,-216 32,-216p-20 -216q32 -216);"/>
                    <Edge cubics="!5 -150(;5,-150 -29,-150 -29,-150p5 -150 -29 -150);"/>
                    <Edge cubics="!-37 -129(;-37,-129 3,-135 3,-135p-37 -129q3 -135);"/>
                    <Edge cubics="!-20 -198(;-20,-198 3,-185 3,-185q-20 -198 3 -185);"/>
                    <Edge cubics="!2 -72(;2,-72 -37,-78 -37,-78q2 -72p-37 -78);"/>
                    <Edge cubics="!-10 -181(;-10,-181 5,-150 5,-150q-10 -181p5 -150);"/>
                    <Edge cubics="!-73 140(;-73,140 2,140 2,140p-73 140q2 140);"/>
                    <Edge cubics="!2 140(;2,140 44,140 44,140q2 140p44 140);"/>
                    <Edge cubics="!-73 -60(;-73,-60 1,-60 1,-60p-73 -60q1 -60);"/>
                    <Edge cubics="!1 -60(1,-60;1,-60 44,-60 44,-60q1 -60p44 -60)44,-60;"/>
                    <Edge cubics="!20 -138(;20,-138 -48,-138 -48,-138p20 -138 -48 -138);"/>
                    <Edge cubics="!1 -60(1,-60;1,-60 2,140 2,140q1 -60 2 140);"/>
                  </edges>
                </DOMShape>
                <DOMGroup>
                  <members>
                    <DOMShape>
                      <fills>
                        <FillStyle index="1">
                          <SolidColor color="#191919" alpha="0.501960784313725"/>
                        </FillStyle>
                      </fills>
                      <edges>
                        <Edge fillStyle1="1" edges="!28 -28[33 -23 33 -15!33 -15[33 -7 28 -2!28 -2[22 5 14 5!14 5[5 5 0 -2!0 -2[-5 -7 -5 -15!-5 -15[-5 -23 0 -28!0 -28[5 -35 14 -35!14 -35[22 -35 28 -28!28 29[33 34 33 42!33 42[33 50 28 55!28 55[22 62 14 62!14 62[5 62 0 55!0 55[-5 50 -5 42
!-5 42[-5 34 0 29!0 29[5 22 14 22!14 22[22 22 28 29!28 111[22 118 14 118!14 118[5 118 0 111!0 111[-5 106 -5 98!-5 98[-5 90 0 85!0 85[5 78 14 78!14 78[22 78 28 85!28 85[33 90 33 98!33 98[33 106 28 111!-26 -2[-32 5 -40 5!-40 5[-49 5 -54
 -2!-54 -2[-59 -7 -59 -15!-59 -15[-59 -23 -54 -28!-54 -28[-49 -35 -40 -35!-40 -35[-32 -35 -26 -28!-26 -28[-21 -23 -21 -15!-21 -15[-21 -7 -26 -2!-26 55[-32 62 -40 62!-40 62[-49 62 -54 55!-54 55[-59 50 -59 42!-59 42[-59 34 -54 29!-54 29
[-49 22 -40 22!-40 22[-32 22 -26 29!-26 29[-21 34 -21 42!-21 42[-21 50 -26 55!-54 85[-49 78 -40 78!-40 78[-32 78 -26 85!-26 85[-21 90 -21 98!-21 98[-21 106 -26 111!-26 111[-32 118 -40 118!-40 118[-49 118 -54 111!-54 111[-59 106 -59 98
!-59 98[-59 90 -54 85"/>
                      </edges>
                    </DOMShape>
                  </members>
                </DOMGroup>
              </elements>
            </DOMFrame>
          </frames>
        </DOMLayer>
      </layers>
    </DOMTimeline>
  </timeline>
</DOMSymbolItem>