<DOMSymbolItem xmlns:xsi="http://www.w3.org/2001/XMLSchema-instance" xmlns="http://ns.adobe.com/xfl/2008/" name="MovieClips/MC.Weapon.RPK.Base" itemID="5ca6243e-00001ac1" lastModified="1552936905">
  <timeline>
    <DOMTimeline name="MC.Weapon.RPK.Base">
      <layers>
        <DOMLayer name="gfx" color="#4F80FF" current="true" isSelected="true" autoNamed="false">
          <frames>
            <DOMFrame index="0" keyMode="9728">
              <elements>
                <DOMGroup>
                  <members>
                    <DOMShape>
                      <fills>
                        <FillStyle index="1">
                          <SolidColor color="#141414"/>
                        </FillStyle>
                        <FillStyle index="2">
                          <SolidColor color="#5D5A56"/>
                        </FillStyle>
                        <FillStyle index="3">
                          <SolidColor color="#191919"/>
                        </FillStyle>
                      </fills>
                      <strokes>
                        <StrokeStyle index="1">
                          <SolidStroke scaleMode="normal" weight="0.05" solidStyle="hairline">
                            <fill>
                              <SolidColor alpha="0.498039215686275"/>
                            </fill>
                          </SolidStroke>
                        </StrokeStyle>
                      </strokes>
                      <edges>
                        <Edge fillStyle1="2" strokeStyle="1" edges="!941 -1238|1063 -1300!1063 -1300|2309 -1238!2309 -1238|2385 -1192!2385 -1192|2445 -1192"/>
                        <Edge fillStyle0="1" strokeStyle="1" edges="!941 -1238|865 -1238!865 -1238|865 -1192!865 -1192|789 -1192!759 -1192[789 -1238 759 -1300!759 -1300[727 -1330 683 -1330!683 -1330|671 -1330"/>
                        <Edge fillStyle0="1" fillStyle1="1" strokeStyle="1" edges="!531 -1268|531 -1284!531 -1284[545 -1300 561 -1314"/>
                        <Edge fillStyle0="3" fillStyle1="1" strokeStyle="1" edges="!561 -1314[615 -1328 671 -1330"/>
                        <Edge fillStyle0="1" strokeStyle="1" edges="!789 -1192|759 -1192"/>
                        <Edge fillStyle0="1" fillStyle1="1" strokeStyle="1" edges="!759 -1192|393 -950!393 -950[303 -934 317 -1040!317 -1040[423 -1116 531 -1268"/>
                        <Edge fillStyle1="2" strokeStyle="1" edges="!2445 -312|789 -280!789 -280|545 -160!545 -160|409 -160!409 -160|241 -190"/>
                        <Edge fillStyle0="1" fillStyle1="2" strokeStyle="1" edges="!241 -190|241 -858!241 -858|789 -858"/>
                        <Edge fillStyle0="1" fillStyle1="1" strokeStyle="1" edges="!-1127 -554|-17 -554!-17 -554[29 -554 29 -508!29 -508|29 -372!29 -372[29 -326 -17 -326!-17 -326|-1127 -326!-1127 -326[-1173 -326 -1173 -372!-1173 -372|-1173 -508!-1173 -508[-1173 -554 -1127 -554"/>
                        <Edge fillStyle0="1" strokeStyle="1" edges="!-609 -266|-63 -266!-63 -266|105 -312!105 -312|241 -190"/>
                        <Edge fillStyle0="2" fillStyle1="1" strokeStyle="1" edges="!1153 -904|1487 -904!1487 -904[1503 -904 1517 -888!1517 -888[1533 -858 1533 -844!1533 -844[1533 -828 1517 -812!1517 -812[1503 -752 1487 -752!1487 -752|1153 -752!1153 -752[1139 -752 1123 -812!1123 -812[1123 -828 1123 -844!1123 -844[1123
 -858 1123 -888!1123 -888[1139 -904 1153 -904"/>
                        <Edge fillStyle0="1" fillStyle1="1" strokeStyle="1" edges="
!789 -1192|789 -858"/>
                        <Edge fillStyle0="1" fillStyle1="2" strokeStyle="1" edges="
!789 -858|941 -858!941 -858|941 -1238"/>
                        <Edge fillStyle0="1" strokeStyle="1" edges="
!2821 -1090|2897 -1090!2897 -1090|2897 -1014!2897 -1014|2821 -1014!2821 -1014|2821 -1090"/>
                        <Edge fillStyle1="1" strokeStyle="1" edges="
!2445 -1192|2445 -1224!2445 -1224|2521 -1224!2521 -1224|2613 -1132!2613 -1132|3767 -1132!3767 -1132[3889 -888 4177 -706"/>
                        <Edge fillStyle0="1" strokeStyle="1" edges="
!2935 -1090|3011 -1090!3011 -1090|3011 -1014!3011 -1014|2935 -1014!2935 -1014|2935 -1090!3049 -1090|3125 -1090!3125 -1090|3125 -1014!3125 -1014|3049 -1014!3049 -1014|3049 -1090!3163 -1090|3239 -1090!3239 -1090|3239 -1014!3239 -1014|3163
 -1014!3163 -1014|3163 -1090"/>
                        <Edge fillStyle0="2" fillStyle1="1" strokeStyle="1" edges="
!1867 -904|2141 -904!2141 -904[2201 -904 2233 -888!2233 -888[2247 -858 2247 -844!2247 -844[2247 -828 2233 -812!2233 -812[2201 -752 2141 -752!2141 -752|1867 -752!1867 -752[1853 -752 1821 -812!1821 -812[1807 -828 1807 -844!1807 -844[1807
 -858 1821 -888!1821 -888[1853 -904 1867 -904"/>
                        <Edge fillStyle0="1" strokeStyle="1" edges="
!2795 -844|2795 -858!2795 -858[2809 -888 2825 -888!2825 -888|3615 -888!3615 -888|3615 -722!2795 -736|2765 -752!2765 -752|2765 -812!2765 -812[2765 -828 2795 -844!3615 -722|2825 -722!2825 -722[2809 -722 2795 -736"/>
                        <Edge fillStyle1="1" strokeStyle="1" edges="
!3645 -448|3645 -524!3645 -524|2809 -524!2809 -524|2765 -508!2765 -508|2567 -508!2567 -508|2567 -448"/>
                        <Edge fillStyle0="1" fillStyle1="1" strokeStyle="1" edges="
!2795 -844|2581 -844!2581 -844|2581 -736!2581 -736|2795 -736"/>
                        <Edge fillStyle0="1" strokeStyle="1" edges="
!2445 -312|2505 -312!2505 -312|2567 -326!2567 -326|2567 -356"/>
                        <Edge fillStyle0="1" fillStyle1="1" strokeStyle="1" edges="
!2567 -448|2567 -356"/>
                        <Edge fillStyle0="1" fillStyle1="2" strokeStyle="1" edges="
!2445 -1192|2445 -312"/>
                        <Edge fillStyle0="1" strokeStyle="1" edges="
!3277 -1090|3353 -1090!3353 -1090|3353 -1014!3353 -1014|3277 -1014!3277 -1014|3277 -1090!3391 -1090|3467 -1090!3467 -1090|3467 -1014!3467 -1014|3391 -1014!3391 -1014|3391 -1090"/>
                        <Edge fillStyle0="1" fillStyle1="1" strokeStyle="1" edges="
!3753 -356|3645 -432!3645 -432|3645 -448!3935 -448|3859 -356"/>
                        <Edge fillStyle1="1" strokeStyle="1" edges="
!3859 -356|3813 -326!3813 -326|3783 -326!3783 -326|3753 -356"/>
                        <Edge fillStyle0="1" fillStyle1="1" strokeStyle="1" edges="
!3645 -736[3631 -722 3615 -722"/>
                        <Edge fillStyle1="1" strokeStyle="1" edges="
!4193 -508|3935 -508!3935 -508|3935 -448"/>
                        <Edge fillStyle0="1" fillStyle1="1" strokeStyle="1" edges="
!4177 -706|4177 -646!4177 -646|4253 -570!4253 -570|4193 -508!5377 -706|5377 -508!5247 -706|5247 -508!5247 -448|5247 -356!5377 -448|5377 -356"/>
                        <Edge fillStyle0="1" strokeStyle="1" edges="
!5377 -706|5247 -706"/>
                        <Edge fillStyle0="1" fillStyle1="1" strokeStyle="1" edges="
!5247 -508|5377 -508!5247 -448|5377 -448"/>
                        <Edge fillStyle1="1" strokeStyle="1" edges="
!5377 -356[5312 -302 5247 -356"/>
                        <Edge fillStyle0="1" strokeStyle="1" edges="
!5247 -508|5247 -448"/>
                        <Edge fillStyle1="1" strokeStyle="1" edges="
!5377 -508|5377 -448"/>
                        <Edge fillStyle0="1" strokeStyle="1" edges="
!5247 -706|4177 -706!4193 -508|5247 -508"/>
                        <Edge fillStyle1="1" strokeStyle="1" edges="
!3935 -448|5247 -448!5247 -356|3859 -356"/>
                        <Edge fillStyle0="1" strokeStyle="1" edges="
!3645 -448|2567 -448"/>
                        <Edge fillStyle1="1" strokeStyle="1" edges="
!3753 -356|2567 -356!7119 -758|7119 -1048!7119 -1048|7023 -1048!7023 -1048|6969 -758!6969 -758|7119 -758"/>
                        <Edge fillStyle0="1" strokeStyle="1" edges="
!7283 -722|7283 -812!7283 -812|7207 -812!7207 -812|7207 -1314!7207 -1314|7145 -1406!7145 -1406|7023 -1406!7023 -1406|6963 -1330!6963 -1330|6963 -1132!6963 -1132|6781 -706!7115 -356|7115 -312!7115 -312|7221 -312!7221 -312|7221 -464!7221
 -464|7267 -524!7267 -524|7283 -524"/>
                        <Edge fillStyle0="1" fillStyle1="1" strokeStyle="1" edges="
!7119 -742|7119 -758!7283 -722|7283 -524!6947 -448|7115 -448!7115 -448|7115 -356!6947 -508[6781 -540 6781 -706"/>
                        <Edge fillStyle0="1" strokeStyle="1" edges="
!6947 -508|6947 -448!7283 -524|7435 -524!7435 -524|7435 -722!7435 -722|7283 -722!5377 -508|6947 -508!6781 -706|5377 -706"/>
                        <Edge fillStyle1="1" strokeStyle="1" edges="
!5377 -448|6947 -448!7115 -356|5377 -356!-3421 -1040|-3285 -1224!-3285 -1224|-215 -1224"/>
                        <Edge fillStyle0="2" strokeStyle="1" edges="
!-4114 -672|-4611 -648!-4611 -648|-7435 -303!-7435 -303|-7334 1200!-7334 1200[-7239 1358 -7054 1304!-7054 1304|-5710 1158!-5710 1158[-5580 1134 -5576 982!-5576 982[-5685 511 -5206 201!-5206 201|-4005 -77"/>
                        <Edge fillStyle0="1" fillStyle1="1" strokeStyle="1" edges="
!-3619 -828|-3559 -904!-3695 -540[-3695 -554 -3679 -570!-3679 -570[-3665 -570 -3619 -570!-3619 -570[-3603 -570 -3589 -570!-3589 -570[-3573 -554 -3573 -540"/>
                        <Edge fillStyle1="1" strokeStyle="1" edges="
!-3619 -828|-3665 -920!-3665 -920|-3589 -950!-3589 -950|-3483 -950"/>
                        <Edge fillStyle0="1" fillStyle1="1" strokeStyle="1" edges="
!-3559 -904|-3483 -950!-3619 -144|-3755 -448!-3755 -448[-3771 -570 -3695 -722!-3695 -722|-3695 -736!-3573 -540[-3573 -508 -3589 -478!-3589 -478[-3603 -464 -3619 -464!-3619 -464[-3665 -464 -3679 -478!-3679 -478[-3695 -508 -3695 -540"/>
                        <Edge fillStyle1="1" strokeStyle="1" edges="
!-3513 -144|-3619 -144!-3513 -52|-3513 -144"/>
                        <Edge fillStyle0="1" fillStyle1="1" strokeStyle="1" edges="
!-3695 -540|-3573 -540"/>
                        <Edge fillStyle1="1" strokeStyle="1" edges="
!-3695 -736|-3619 -828!-3619 -144|-4005 -77"/>
                        <Edge fillStyle0="2" fillStyle1="1" strokeStyle="1" edges="
!-4005 -77|-4114 -672"/>
                        <Edge fillStyle1="1" strokeStyle="1" edges="
!-4114 -672|-3695 -736!-3483 -950|-3421 -1040"/>
                        <Edge fillStyle0="1" fillStyle1="1" strokeStyle="1" edges="
!-2715 -524[-2715 -480 -2747 -448!-2747 -448[-2779 -416 -2823 -416!-2823 -416[-2867 -416 -2899 -448!-2899 -448[-2931 -480 -2931 -524!-2931 -524[-2931 -568 -2899 -600!-2899 -600[-2867 -632 -2823 -632!-2823 -632[-2779 -632 -2747 -600!-2747
 -600[-2715 -568 -2715 -524!-2541 -266|-2433 -266!-2541 -266[-2541 -280 -2541 -296!-2541 -296[-2525 -312 -2479 -312!-2479 -312[-2465 -312 -2449 -296!-2449 -296[-2433 -280 -2433 -266!-2433 -266[-2433 -190 -2449 -190!-2449 -190[-2465 -174
 -2479 -174!-2479 -174[-2525 -174 -2541 -190!-2541 -190|-2541 -266"/>
                        <Edge fillStyle0="1" strokeStyle="1" edges="
!-2601 -144|-2601 -98!-2601 -98|-2479 8!-2479 8[-2465 190 -2297 220!-2297 220|-2267 190!-2267 190[-2479 38 -2343 -144"/>
                        <Edge fillStyle1="1" strokeStyle="1" edges="
!-2601 -144|-2661 -144"/>
                        <Edge fillStyle0="1" fillStyle1="1" strokeStyle="1" edges="
!-2677 -372|-1583 -676!-1583 -676|-1583 -844!-1583 -844|-2297 -844!-2297 -844|-2631 -676!-2631 -676|-2859 -676!-2859 -676[-3087 -646 -2995 -464!-2995 -464[-2935 -326 -2677 -372!-2267 -296[-2267 -312 -2251 -326!-2251 -326[-2237 -342 -2221
 -342!-2221 -342[-2161 -342 -2161 -326!-2161 -326[-2161 -312 -2129 -296!-2129 -296|-2129 -280!-2129 -280[-2129 -266 -2161 -250!-2161 -250[-2161 -190 -2221 -190!-2221 -190[-2237 -190 -2251 -250!-2251 -250[-2267 -266 -2267 -280!-2267 -280
|-2267 -296!-2267 -296|-2129 -296!-1583 -312|-1583 -296!-1583 -296[-1583 -280 -1613 -266!-1613 -266[-1659 -250 -1689 -250!-1689 -250[-1705 -250 -1719 -266!-1719 -266[-1735 -280 -1735 -296!-1735 -296|-1735 -312!-1735 -312[-1735 -326 -1719
 -342!-1719 -342[-1705 -356 -1689 -356!-1689 -356[-1659 -356 -1613 -342!-1613 -342[-1613 -326 -1583 -312!-1963 -356[-1963 -372 -1933 -372!-1933 -372[-1917 -432 -1887 -432!-1887 -432[-1871 -432 -1857 -372!-1857 -372[-1841 -372 -1841 -356
!-1841 -356[-1841 -326 -1857 -312!-1857 -312[-1871 -296 -1887 -296!-1887 -296[-1917 -296 -1933 -312!-1933 -312[-1963 -326 -1963 -356!-1963 -356|-1841 -356"/>
                        <Edge fillStyle1="1" strokeStyle="1" edges="
!-1917 -128|-1917 -144!-1917 -144|-2343 -144"/>
                        <Edge fillStyle0="1" fillStyle1="1" strokeStyle="1" edges="
!-2343 -144|-2601 -144"/>
                        <Edge fillStyle1="1" strokeStyle="1" edges="
!-77 -1390|-33 -1390!-33 -1390|-17 -1330"/>
                        <Edge fillStyle0="3" fillStyle1="1" strokeStyle="1" edges="
!-17 -1330|-1 -1314"/>
                        <Edge fillStyle0="1" fillStyle1="1" strokeStyle="1" edges="
!-1 -1314|-33 -1268"/>
                        <Edge fillStyle1="1" strokeStyle="1" edges="
!-153 -1268|-153 -1314"/>
                        <Edge fillStyle0="1" fillStyle1="1" strokeStyle="1" edges="
!-153 -1268|-33 -1268!-153 -1314|-77 -1390"/>
                        <Edge fillStyle0="1" strokeStyle="1" edges="
!-77 -1390|-215 -1436!-215 -1436|-229 -1390!-229 -1390|-153 -1314"/>
                        <Edge fillStyle0="1" fillStyle1="1" strokeStyle="1" edges="
!-215 -1224|-215 -1102!-215 -1102|-123 -1072!-123 -1072|-123 -1040"/>
                        <Edge fillStyle1="1" strokeStyle="1" edges="
!-215 -1224|-215 -1268!-215 -1268|-153 -1268"/>
                        <Edge fillStyle0="1" fillStyle1="1" strokeStyle="1" edges="
!-1369 -904|-1293 -844!-1293 -844|-1293 -736!-1293 -736|-199 -736!-199 -736|-123 -828!-123 -828|-123 -1040"/>
                        <Edge fillStyle0="1" strokeStyle="1" edges="
!-1537 -160|-1537 -144!-1537 -144|-609 -144!-609 -144|-609 -266"/>
                        <Edge fillStyle1="1" strokeStyle="1" edges="
!-1537 -160|-1583 -128"/>
                        <Edge fillStyle0="1" fillStyle1="1" strokeStyle="1" edges="
!-1309 -1040|-1369 -904!-123 -1040|-1309 -1040!-609 -266|-1537 -160!-1735 -312|-1583 -312!-1583 -128|-1917 -128!-3513 -144|-2661 -144!-1309 -1040|-3421 -1040!-3559 -904|-1369 -904"/>
                        <Edge fillStyle1="1" strokeStyle="1" edges="
!-1583 -128|-1583 114!-1583 114|-1659 220!-1659 220|-1673 220"/>
                        <Edge fillStyle0="1" fillStyle1="1" strokeStyle="1" edges="
!-1841 100[-1841 68 -1811 54!-1811 54[-1781 38 -1749 38!-1749 38[-1735 38 -1719 54!-1719 54[-1705 68 -1705 100!-1705 100[-1705 114 -1719 130!-1719 130[-1735 190 -1749 190!-1749 190[-1781 190 -1811 130!-1811 130[-1841 114 -1841 100!-1673
 220|-1749 220"/>
                        <Edge fillStyle1="1" strokeStyle="1" edges="
!-1901 220|-1917 220!-1917 220|-1917 -128"/>
                        <Edge strokeStyle="1" edges="
!-2661 220[-2648 292 -2553 324!-2553 324[-2547 326 -2541 328!-2541 328|-1963 328!-1963 328|-1901 296!-1901 296|-1901 220"/>
                        <Edge fillStyle0="1" strokeStyle="1" edges="
!-1749 220|-1719 252!-1719 252|-1719 418!-1719 418|-1673 418!-1673 418|-1673 220"/>
                        <Edge fillStyle1="1" strokeStyle="1" edges="
!-1749 220|-1901 220"/>
                        <Edge fillStyle0="1" fillStyle1="1" strokeStyle="1" edges="
!-1841 100|-1705 100"/>
                        <Edge fillStyle0="1" strokeStyle="1" edges="
!-3513 -52|-3559 8!-3559 8|-3559 84!-3559 84[-3467 114 -3467 236!-3467 236|-3467 404!-3467 404|-3741 1178!-3741 1178|-3741 1254!-3741 1254|-3361 1436!-3361 1436|-3223 1436!-3223 1436[-3133 1392 -3103 1270!-3103 1270[-3163 1164 -3103 1012
!-3103 1012|-2859 328!-2859 328[-2813 236 -2661 220!-2661 220|-2617 206!-2617 206|-2617 68!-2617 68|-2661 38"/>
                        <Edge fillStyle1="1" strokeStyle="1" edges="
!-2661 -144|-2661 38"/>
                        <Edge fillStyle0="1" fillStyle1="1" strokeStyle="1" edges="
!-2661 38|-3513 -52!-33 -1268|531 -1268"/>
                        <Edge fillStyle0="3" strokeStyle="1" edges="
!671 -1330|-17 -1330"/>
                        <Edge fillStyle0="3" fillStyle1="1" edges="
!-1 -1314|561 -1314"/>
                        <Edge cubics="!531 -1284(;545,-1300 561,-1300 561,-1314q531 -1284Q545 -1300q561 -1314);"/>
                        <Edge cubics="!531 -1268(;531,-1268 531,-1284 531,-1284q531 -1268Q531 -1284q531 -1284);"/>
                        <Edge cubics="!317 -1040(;393,-1086 485,-1132 531,-1268q317 -1040Q423 -1116q531 -1268);"/>
                        <Edge cubics="!789 -1192(;789,-1192 759,-1192 759,-1192q789 -1192 759 -1192);"/>
                        <Edge cubics="!865 -1192(;865,-1192 789,-1192 789,-1192q865 -1192 789 -1192);"/>
                        <Edge cubics="!941 -1238(;941,-1238 1063,-1300 1063,-1300q941 -1238 1063 -1300);"/>
                        <Edge cubics="!941 -1238(;941,-1238 865,-1238 865,-1238q941 -1238 865 -1238);"/>
                        <Edge cubics="!865 -1238(;865,-1238 865,-1192 865,-1192q865 -1238 865 -1192);"/>
                        <Edge cubics="!759 -1192(;773,-1224 773,-1268 759,-1300q759 -1192Q789 -1238q759 -1300);"/>
                        <Edge cubics="!683 -1330(;727,-1330 743,-1330 759,-1300q683 -1330Q727 -1330q759 -1300);"/>
                        <Edge cubics="!2521 -1224(;2521,-1224 2613,-1132 2613,-1132q2521 -1224 2613 -1132);"/>
                        <Edge cubics="!2445 -1224(;2445,-1224 2521,-1224 2521,-1224q2445 -1224 2521 -1224);"/>
                        <Edge cubics="!2445 -1192(;2445,-1192 2445,-1224 2445,-1224q2445 -1192 2445 -1224);"/>
                        <Edge cubics="!2385 -1192(;2385,-1192 2309,-1238 2309,-1238q2385 -1192 2309 -1238);"/>
                        <Edge cubics="!2445 -1192(;2445,-1192 2385,-1192 2385,-1192q2445 -1192 2385 -1192);"/>
                        <Edge cubics="!1063 -1300(;1063,-1300 2309,-1238 2309,-1238q1063 -1300 2309 -1238);"/>
                        <Edge cubics="!2613 -1132(;2613,-1132 3767,-1132 3767,-1132q2613 -1132 3767 -1132);"/>
                        <Edge cubics="!-3421 -1040(;-3421,-1040 -3285,-1224 -3285,-1224q-3421 -1040 -3285 -1224);"/>
                        <Edge cubics="!-17 -1330(;-17,-1330 -1,-1314 -1,-1314q-17 -1330 -1 -1314);"/>
                        <Edge cubics="!-33 -1390(;-33,-1390 -17,-1330 -17,-1330q-33 -1390 -17 -1330);"/>
                        <Edge cubics="!-1 -1314(;-1,-1314 -33,-1268 -33,-1268q-1 -1314 -33 -1268);"/>
                        <Edge cubics="!-215 -1268(;-215,-1268 -153,-1268 -153,-1268q-215 -1268 -153 -1268);"/>
                        <Edge cubics="!-153 -1268(;-153,-1268 -153,-1314 -153,-1314q-153 -1268 -153 -1314);"/>
                        <Edge cubics="!-215 -1224(;-215,-1224 -215,-1102 -215,-1102q-215 -1224 -215 -1102);"/>
                        <Edge cubics="!-215 -1102(;-215,-1102 -123,-1072 -123,-1072q-215 -1102 -123 -1072);"/>
                        <Edge cubics="!-123 -1040(;-123,-1040 -123,-1072 -123,-1072q-123 -1040 -123 -1072);"/>
                        <Edge cubics="!-153 -1268(;-153,-1268 -33,-1268 -33,-1268q-153 -1268 -33 -1268);"/>
                        <Edge cubics="!-77 -1390(;-77,-1390 -33,-1390 -33,-1390q-77 -1390 -33 -1390);"/>
                        <Edge cubics="!-215 -1224(;-215,-1224 -215,-1268 -215,-1268q-215 -1224 -215 -1268);"/>
                        <Edge cubics="!-123 -1040(;-123,-1040 -1309,-1040 -1309,-1040q-123 -1040 -1309 -1040);"/>
                        <Edge cubics="!-1309 -1040(;-1309,-1040 -3421,-1040 -3421,-1040q-1309 -1040 -3421 -1040);"/>
                        <Edge cubics="!-3285 -1224(;-3285,-1224 -215,-1224 -215,-1224q-3285 -1224 -215 -1224);"/>
                        <Edge cubics="!-17 -554(;13,-554 29,-540 29,-508q-17 -554Q29 -554q29 -508);"/>
                        <Edge cubics="!29 -508(;29,-508 29,-372 29,-372q29 -508 29 -372);"/>
                        <Edge cubics="!29 -372(;29,-342 13,-326 -17,-326q29 -372Q29 -326q-17 -326);"/>
                        <Edge cubics="!-63 -266(;-63,-266 105,-312 105,-312q-63 -266 105 -312);"/>
                        <Edge cubics="!-199 -736(;-199,-736 -123,-828 -123,-828q-199 -736 -123 -828);"/>
                        <Edge cubics="!-1127 -326(;-1157,-326 -1173,-342 -1173,-372q-1127 -326Q-1173 -326q-1173 -372);"/>
                        <Edge cubics="!-1173 -372(;-1173,-372 -1173,-508 -1173,-508q-1173 -372 -1173 -508);"/>
                        <Edge cubics="!-1173 -508(;-1173,-540 -1157,-554 -1127,-554q-1173 -508Q-1173 -554q-1127 -554);"/>
                        <Edge cubics="!-1127 -554(;-1127,-554 -17,-554 -17,-554q-1127 -554 -17 -554);"/>
                        <Edge cubics="!-17 -326(;-17,-326 -1127,-326 -1127,-326q-17 -326 -1127 -326);"/>
                        <Edge cubics="!-609 -144(;-609,-144 -609,-266 -609,-266q-609 -144 -609 -266);"/>
                        <Edge cubics="!-609 -266(;-609,-266 -63,-266 -63,-266q-609 -266 -63 -266);"/>
                        <Edge cubics="!-1293 -844(;-1293,-844 -1293,-736 -1293,-736q-1293 -844 -1293 -736);"/>
                        <Edge cubics="!-1369 -904(;-1369,-904 -1293,-844 -1293,-844q-1369 -904 -1293 -844);"/>
                        <Edge cubics="!-1583 -676(;-1583,-676 -1583,-844 -1583,-844q-1583 -676 -1583 -844);"/>
                        <Edge cubics="!-1735 -296(;-1735,-312 -1735,-312 -1735,-312q-1735 -296Q-1735 -312q-1735 -312);"/>
                        <Edge cubics="!-1857 -372(;-1841,-372 -1841,-372 -1841,-356q-1857 -372Q-1841 -372q-1841 -356);"/>
                        <Edge cubics="!-1841 -356(;-1841,-342 -1841,-326 -1857,-312q-1841 -356Q-1841 -326q-1857 -312);"/>
                        <Edge cubics="!-1857 -312(;-1857,-312 -1871,-296 -1887,-296q-1857 -312Q-1871 -296q-1887 -296);"/>
                        <Edge cubics="!-1719 -342(;-1719,-356 -1705,-356 -1689,-356q-1719 -342Q-1705 -356q-1689 -356);"/>
                        <Edge cubics="!-1689 -250(;-1705,-250 -1719,-250 -1719,-266q-1689 -250Q-1705 -250q-1719 -266);"/>
                        <Edge cubics="!-1689 -356(;-1673,-356 -1659,-356 -1613,-342q-1689 -356Q-1659 -356q-1613 -342);"/>
                        <Edge cubics="!-1613 -266(;-1659,-250 -1673,-250 -1689,-250q-1613 -266Q-1659 -250q-1689 -250);"/>
                        <Edge cubics="!-1613 -342(;-1613,-326 -1613,-326 -1583,-312q-1613 -342Q-1613 -326q-1583 -312);"/>
                        <Edge cubics="!-1583 -312(;-1583,-312 -1583,-312 -1583,-296q-1583 -312Q-1583 -312q-1583 -296);"/>
                        <Edge cubics="!-1583 -296(;-1583,-280 -1613,-280 -1613,-266q-1583 -296Q-1583 -280q-1613 -266);"/>
                        <Edge cubics="!-1719 -266(;-1735,-280 -1735,-280 -1735,-296q-1719 -266Q-1735 -280q-1735 -296);"/>
                        <Edge cubics="!-1735 -312(;-1735,-326 -1735,-326 -1719,-342q-1735 -312Q-1735 -326q-1719 -342);"/>
                        <Edge cubics="!-1735 -312(;-1735,-312 -1583,-312 -1583,-312q-1735 -312 -1583 -312);"/>
                        <Edge cubics="!-1887 -432(;-1871,-432 -1857,-432 -1857,-372q-1887 -432Q-1871 -432q-1857 -372);"/>
                        <Edge cubics="!-2541 -296(;-2525,-312 -2495,-312 -2479,-312q-2541 -296Q-2525 -312q-2479 -312);"/>
                        <Edge cubics="!-2479 -312(;-2465,-312 -2449,-312 -2449,-296q-2479 -312Q-2465 -312q-2449 -296);"/>
                        <Edge cubics="!-2449 -296(;-2433,-280 -2433,-280 -2433,-266q-2449 -296Q-2433 -280q-2433 -266);"/>
                        <Edge cubics="!-2541 -266(;-2541,-280 -2541,-280 -2541,-296q-2541 -266Q-2541 -280q-2541 -296);"/>
                        <Edge cubics="!-2541 -266(;-2541,-266 -2433,-266 -2433,-266q-2541 -266 -2433 -266);"/>
                        <Edge cubics="!-2251 -250(;-2267,-266 -2267,-266 -2267,-280q-2251 -250Q-2267 -266q-2267 -280);"/>
                        <Edge cubics="!-2267 -296(;-2267,-312 -2267,-312 -2251,-326q-2267 -296Q-2267 -312q-2251 -326);"/>
                        <Edge cubics="!-2267 -280(;-2267,-280 -2267,-280 -2267,-296q-2267 -280Q-2267 -280q-2267 -296);"/>
                        <Edge cubics="!-2221 -342(;-2191,-342 -2161,-326 -2161,-326q-2221 -342Q-2161 -342q-2161 -326);"/>
                        <Edge cubics="!-2161 -326(;-2161,-312 -2161,-312 -2129,-296q-2161 -326Q-2161 -312q-2129 -296);"/>
                        <Edge cubics="!-1933 -312(;-1933,-326 -1963,-342 -1963,-356q-1933 -312Q-1963 -326q-1963 -356);"/>
                        <Edge cubics="!-1963 -356(;-1963,-372 -1933,-372 -1933,-372q-1963 -356Q-1963 -372q-1933 -372);"/>
                        <Edge cubics="!-2129 -296(;-2129,-280 -2129,-280 -2129,-280q-2129 -296Q-2129 -280q-2129 -280);"/>
                        <Edge cubics="!-2129 -280(;-2129,-266 -2161,-266 -2161,-250q-2129 -280Q-2129 -266q-2161 -250);"/>
                        <Edge cubics="!-2161 -250(;-2161,-190 -2191,-190 -2221,-190q-2161 -250Q-2161 -190q-2221 -190);"/>
                        <Edge cubics="!-2221 -190(;-2237,-190 -2251,-190 -2251,-250q-2221 -190Q-2237 -190q-2251 -250);"/>
                        <Edge cubics="!-2251 -326(;-2251,-326 -2237,-342 -2221,-342q-2251 -326Q-2237 -342q-2221 -342);"/>
                        <Edge cubics="!-2267 -296(;-2267,-296 -2129,-296 -2129,-296q-2267 -296 -2129 -296);"/>
                        <Edge cubics="!-1917 -128(;-1917,-128 -1917,-144 -1917,-144q-1917 -128 -1917 -144);"/>
                        <Edge cubics="!-2449 -190(;-2449,-174 -2465,-174 -2479,-174q-2449 -190Q-2465 -174q-2479 -174);"/>
                        <Edge cubics="!-2479 -174(;-2495,-174 -2525,-174 -2541,-190q-2479 -174Q-2525 -174q-2541 -190);"/>
                        <Edge cubics="!-1963 328(;-1963,328 -1901,296 -1901,296q-1963 328 -1901 296);"/>
                        <Edge cubics="!-1901 220(;-1901,220 -1917,220 -1917,220q-1901 220 -1917 220);"/>
                        <Edge cubics="!-1901 296(;-1901,296 -1901,220 -1901,220q-1901 296 -1901 220);"/>
                        <Edge cubics="!-1917 220(;-1917,220 -1917,-128 -1917,-128q-1917 220 -1917 -128);"/>
                        <Edge cubics="!-2541 328(;-2541,328 -1963,328 -1963,328q-2541 328 -1963 328);"/>
                        <Edge cubics="!-1537 -160(;-1537,-160 -1537,-144 -1537,-144q-1537 -160Q-1537 -144q-1537 -144);"/>
                        <Edge cubics="!-1537 -160(;-1537,-160 -1583,-128 -1583,-128q-1537 -160 -1583 -128);"/>
                        <Edge cubics="!-1583 -128(;-1583,-128 -1583,114 -1583,114q-1583 -128 -1583 114);"/>
                        <Edge cubics="!-1583 114(;-1583,114 -1659,220 -1659,220q-1583 114 -1659 220);"/>
                        <Edge cubics="!-1583 -128(;-1583,-128 -1917,-128 -1917,-128q-1583 -128 -1917 -128);"/>
                        <Edge cubics="!-1583 -844(;-1583,-844 -2297,-844 -2297,-844q-1583 -844 -2297 -844);"/>
                        <Edge cubics="!-2433 -266(;-2433,-250 -2433,-190 -2449,-190q-2433 -266Q-2433 -190q-2449 -190);"/>
                        <Edge cubics="!-2541 -190(;-2541,-190 -2541,-250 -2541,-266q-2541 -190Q-2541 -190q-2541 -266);"/>
                        <Edge cubics="!-1963 -356(;-1963,-356 -1841,-356 -1841,-356q-1963 -356 -1841 -356);"/>
                        <Edge cubics="!-1887 -296(;-1901,-296 -1917,-312 -1933,-312q-1887 -296Q-1917 -296q-1933 -312);"/>
                        <Edge cubics="!-1933 -372(;-1917,-432 -1901,-432 -1887,-432q-1933 -372Q-1917 -432q-1887 -432);"/>
                        <Edge cubics="!-1293 -736(;-1293,-736 -199,-736 -199,-736q-1293 -736 -199 -736);"/>
                        <Edge cubics="!-2631 -676(;-2631,-676 -2859,-676 -2859,-676q-2631 -676 -2859 -676);"/>
                        <Edge cubics="!-2995 -464(;-2965,-356 -2859,-342 -2677,-372q-2995 -464Q-2935 -326q-2677 -372);"/>
                        <Edge cubics="!-2859 -676(;-3011,-660 -3041,-570 -2995,-464q-2859 -676Q-3087 -646q-2995 -464);"/>
                        <Edge cubics="!-3559 -904(;-3559,-904 -3483,-950 -3483,-950q-3559 -904 -3483 -950);"/>
                        <Edge cubics="!-3695 -722(;-3695,-722 -3695,-736 -3695,-736q-3695 -722 -3695 -736);"/>
                        <Edge cubics="!-3695 -736(;-3695,-736 -3619,-828 -3619,-828q-3695 -736 -3619 -828);"/>
                        <Edge cubics="!-3619 -828(;-3619,-828 -3665,-920 -3665,-920q-3619 -828 -3665 -920);"/>
                        <Edge cubics="!-3665 -920(;-3665,-920 -3589,-950 -3589,-950q-3665 -920 -3589 -950);"/>
                        <Edge cubics="!-3589 -570(;-3573,-570 -3573,-554 -3573,-540q-3589 -570Q-3573 -554q-3573 -540);"/>
                        <Edge cubics="!-3619 -570(;-3619,-570 -3603,-570 -3589,-570q-3619 -570Q-3603 -570q-3589 -570);"/>
                        <Edge cubics="!-3695 -540(;-3695,-554 -3695,-570 -3679,-570q-3695 -540Q-3695 -554q-3679 -570);"/>
                        <Edge cubics="!-3589 -478(;-3603,-478 -3619,-464 -3619,-464q-3589 -478Q-3603 -464q-3619 -464);"/>
                        <Edge cubics="!-3679 -478(;-3695,-508 -3695,-524 -3695,-540q-3679 -478Q-3695 -508q-3695 -540);"/>
                        <Edge cubics="!-3573 -540(;-3573,-524 -3573,-508 -3589,-478q-3573 -540Q-3573 -508q-3589 -478);"/>
                        <Edge cubics="!-3695 -540(;-3695,-540 -3573,-540 -3573,-540q-3695 -540 -3573 -540);"/>
                        <Edge cubics="!-3679 -570(;-3665,-570 -3635,-570 -3619,-570q-3679 -570Q-3665 -570q-3619 -570);"/>
                        <Edge cubics="!-3619 -464(;-3635,-464 -3665,-478 -3679,-478q-3619 -464Q-3665 -464q-3679 -478);"/>
                        <Edge cubics="!-3619 -828(;-3619,-828 -3559,-904 -3559,-904q-3619 -828 -3559 -904);"/>
                        <Edge cubics="!-3589 -950(;-3589,-950 -3483,-950 -3483,-950q-3589 -950 -3483 -950);"/>
                        <Edge cubics="!-3755 -448(;-3755,-540 -3755,-646 -3695,-722q-3755 -448Q-3771 -570q-3695 -722);"/>
                        <Edge cubics="!-3467 236(;-3467,236 -3467,404 -3467,404q-3467 236 -3467 404);"/>
                        <Edge cubics="!-3513 -52(;-3513,-52 -3559,8 -3559,8q-3513 -52 -3559 8);"/>
                        <Edge cubics="!-3513 -52(;-3513,-52 -3513,-144 -3513,-144q-3513 -52 -3513 -144);"/>
                        <Edge cubics="!-3513 -144(;-3513,-144 -3619,-144 -3619,-144q-3513 -144 -3619 -144);"/>
                        <Edge cubics="!-2661 220(;-2661,220 -2617,206 -2617,206q-2661 220 -2617 206);"/>
                        <Edge cubics="!-2617 68(;-2617,68 -2661,38 -2661,38q-2617 68 -2661 38);"/>
                        <Edge cubics="!-2617 206(;-2617,206 -2617,68 -2617,68q-2617 206 -2617 68);"/>
                        <Edge cubics="!-2661 -144(;-2661,-144 -2661,38 -2661,38q-2661 -144 -2661 38);"/>
                        <Edge cubics="!-3513 -144(;-3513,-144 -2661,-144 -2661,-144q-3513 -144 -2661 -144);"/>
                        <Edge cubics="!-2661 38(;-2661,38 -3513,-52 -3513,-52q-2661 38 -3513 -52);"/>
                        <Edge cubics="!-3619 -144(;-3619,-144 -3755,-448 -3755,-448q-3619 -144 -3755 -448);"/>
                        <Edge cubics="!-3361 1436(;-3361,1436 -3223,1436 -3223,1436q-3361 1436 -3223 1436);"/>
                        <Edge cubics="!-3741 1254(;-3741,1254 -3361,1436 -3361,1436q-3741 1254 -3361 1436);"/>
                        <Edge cubics="!-3741 1178(;-3741,1178 -3741,1254 -3741,1254q-3741 1178 -3741 1254);"/>
                        <Edge cubics="!-3103 1012(;-3103,1012 -2859,328 -2859,328q-3103 1012 -2859 328);"/>
                        <Edge cubics="!-3467 404(;-3467,404 -3741,1178 -3741,1178q-3467 404 -3741 1178);"/>
                        <Edge cubics="!-2297 -844(;-2297,-844 -2631,-676 -2631,-676q-2297 -844 -2631 -676);"/>
                        <Edge cubics="!-2677 -372(;-2677,-372 -1583,-676 -1583,-676q-2677 -372 -1583 -676);"/>
                        <Edge cubics="!-3559 -904(;-3559,-904 -1369,-904 -1369,-904q-3559 -904 -1369 -904);"/>
                        <Edge cubics="!4177 -706(;4177,-706 4177,-646 4177,-646q4177 -706 4177 -646);"/>
                        <Edge cubics="!4177 -646(;4177,-646 4253,-570 4253,-570q4177 -646 4253 -570);"/>
                        <Edge cubics="!4253 -570(;4253,-570 4193,-508 4193,-508q4253 -570 4193 -508);"/>
                        <Edge cubics="!3645 -736(;3645,-722 3631,-722 3615,-722q3645 -736Q3631 -722q3615 -722);"/>
                        <Edge cubics="!3813 -326(;3813,-326 3783,-326 3783,-326q3813 -326 3783 -326);"/>
                        <Edge cubics="!3935 -508(;3935,-508 3935,-448 3935,-448q3935 -508 3935 -448);"/>
                        <Edge cubics="!2825 -722(;2825,-722 2809,-722 2795,-736q2825 -722Q2809 -722q2795 -736);"/>
                        <Edge cubics="!2765 -752(;2765,-752 2765,-812 2765,-812q2765 -752 2765 -812);"/>
                        <Edge cubics="!2795 -858(;2809,-888 2825,-888 2825,-888q2795 -858Q2809 -888q2825 -888);"/>
                        <Edge cubics="!2809 -524(;2809,-524 2765,-508 2765,-508q2809 -524 2765 -508);"/>
                        <Edge cubics="!2825 -888(;2825,-888 3615,-888 3615,-888q2825 -888 3615 -888);"/>
                        <Edge cubics="!3615 -722(;3615,-722 2825,-722 2825,-722q3615 -722 2825 -722);"/>
                        <Edge cubics="!3645 -524(;3645,-524 2809,-524 2809,-524q3645 -524 2809 -524);"/>
                        <Edge cubics="!4193 -508(;4193,-508 3935,-508 3935,-508q4193 -508 3935 -508);"/>
                        <Edge cubics="!2247 -844(;2247,-828 2247,-812 2233,-812q2247 -844Q2247 -828q2233 -812);"/>
                        <Edge cubics="!2233 -888(;2247,-888 2247,-858 2247,-844q2233 -888Q2247 -858q2247 -844);"/>
                        <Edge cubics="!2141 -904(;2187,-904 2201,-904 2233,-888q2141 -904Q2201 -904q2233 -888);"/>
                        <Edge cubics="!2233 -812(;2201,-752 2187,-752 2141,-752q2233 -812Q2201 -752q2141 -752);"/>
                        <Edge cubics="!2505 -312(;2505,-312 2567,-326 2567,-326q2505 -312 2567 -326);"/>
                        <Edge cubics="!2445 -312(;2445,-312 2505,-312 2505,-312q2445 -312 2505 -312);"/>
                        <Edge cubics="!1821 -888(;1821,-904 1853,-904 1867,-904q1821 -888Q1853 -904q1867 -904);"/>
                        <Edge cubics="!1807 -844(;1807,-858 1807,-888 1821,-888q1807 -844Q1807 -858q1821 -888);"/>
                        <Edge cubics="!1821 -812(;1807,-812 1807,-828 1807,-844q1821 -812Q1807 -828q1807 -844);"/>
                        <Edge cubics="!1517 -812(;1503,-752 1503,-752 1487,-752q1517 -812Q1503 -752q1487 -752);"/>
                        <Edge cubics="!1533 -844(;1533,-828 1517,-812 1517,-812q1533 -844Q1533 -828q1517 -812);"/>
                        <Edge cubics="!1517 -888(;1517,-888 1533,-858 1533,-844q1517 -888Q1533 -858q1533 -844);"/>
                        <Edge cubics="!1487 -904(;1503,-904 1503,-904 1517,-888q1487 -904Q1503 -904q1517 -888);"/>
                        <Edge cubics="!1867 -752(;1853,-752 1821,-752 1821,-812q1867 -752Q1853 -752q1821 -812);"/>
                        <Edge cubics="!2141 -752(;2141,-752 1867,-752 1867,-752q2141 -752 1867 -752);"/>
                        <Edge cubics="!1867 -904(;1867,-904 2141,-904 2141,-904q1867 -904 2141 -904);"/>
                        <Edge cubics="!789 -858(;789,-858 941,-858 941,-858q789 -858 941 -858);"/>
                        <Edge cubics="!1153 -752(;1139,-752 1123,-752 1123,-812q1153 -752Q1139 -752q1123 -812);"/>
                        <Edge cubics="!1123 -812(;1123,-812 1123,-828 1123,-844q1123 -812Q1123 -828q1123 -844);"/>
                        <Edge cubics="!1123 -844(;1123,-858 1123,-888 1123,-888q1123 -844Q1123 -858q1123 -888);"/>
                        <Edge cubics="!1123 -888(;1123,-904 1139,-904 1153,-904q1123 -888Q1139 -904q1153 -904);"/>
                        <Edge cubics="!241 -190(;241,-190 241,-858 241,-858q241 -190 241 -858);"/>
                        <Edge cubics="!545 -160(;545,-160 409,-160 409,-160q545 -160 409 -160);"/>
                        <Edge cubics="!241 -858(;241,-858 789,-858 789,-858q241 -858 789 -858);"/>
                        <Edge cubics="!789 -280(;789,-280 545,-160 545,-160q789 -280 545 -160);"/>
                        <Edge cubics="!409 -160(;409,-160 241,-190 241,-190q409 -160 241 -190);"/>
                        <Edge cubics="!2445 -312(;2445,-312 789,-280 789,-280q2445 -312 789 -280);"/>
                        <Edge cubics="!1153 -904(;1153,-904 1487,-904 1487,-904q1153 -904 1487 -904);"/>
                        <Edge cubics="!1487 -752(;1487,-752 1153,-752 1153,-752q1487 -752 1153 -752);"/>
                        <Edge cubics="!2765 -508(;2765,-508 2567,-508 2567,-508q2765 -508 2567 -508);"/>
                        <Edge cubics="!3767 -1132(;3829,-950 3995,-828 4177,-706q3767 -1132Q3889 -888q4177 -706);"/>
                        <Edge cubics="!2445 -1192(;2445,-1192 2445,-312 2445,-312q2445 -1192 2445 -312);"/>
                        <Edge cubics="!-3483 -950(;-3483,-950 -3421,-1040 -3421,-1040q-3483 -950 -3421 -1040);"/>
                        <Edge cubics="!789 -1192(;789,-1192 789,-858 789,-858q789 -1192 789 -858);"/>
                        <Edge cubics="!-1 -1314(;-1,-1314 561,-1314 561,-1314q-1 -1314 561 -1314);"/>
                        <Edge cubics="!-33 -1268(;-33,-1268 531,-1268 531,-1268q-33 -1268 531 -1268);"/>
                        <Edge cubics="!393 -950(;347,-934 303,-950 317,-1040q393 -950Q303 -934q317 -1040);"/>
                        <Edge cubics="!759 -1192(;759,-1192 393,-950 393,-950q759 -1192 393 -950);"/>
                        <Edge cubics="!-1309 -1040(;-1309,-1040 -1369,-904 -1369,-904q-1309 -1040 -1369 -904);"/>
                        <Edge cubics="!-123 -828(;-123,-828 -123,-1040 -123,-1040q-123 -828 -123 -1040);"/>
                        <Edge cubics="!941 -858(;941,-858 941,-1238 941,-1238q941 -858 941 -1238);"/>
                        <Edge cubics="!105 -312(;105,-312 241,-190 241,-190q105 -312 241 -190);"/>
                        <Edge cubics="!3645 -448(;3645,-448 3645,-524 3645,-524q3645 -448 3645 -524);"/>
                        <Edge cubics="!3645 -432(;3645,-432 3645,-448 3645,-448q3645 -432 3645 -448);"/>
                        <Edge cubics="!2567 -508(;2567,-508 2567,-448 2567,-448q2567 -508 2567 -448);"/>
                        <Edge cubics="!3645 -448(;3645,-448 2567,-448 2567,-448q3645 -448 2567 -448);"/>
                        <Edge cubics="!3753 -356(;3753,-356 3645,-432 3645,-432q3753 -356 3645 -432);"/>
                        <Edge cubics="!3859 -356(;3859,-356 3813,-326 3813,-326q3859 -356 3813 -326);"/>
                        <Edge cubics="!3935 -448(;3935,-448 3859,-356 3859,-356q3935 -448 3859 -356);"/>
                        <Edge cubics="!3783 -326(;3783,-326 3753,-356 3753,-356q3783 -326 3753 -356);"/>
                        <Edge cubics="!2567 -356(;2567,-356 2567,-326 2567,-326q2567 -356 2567 -326);"/>
                        <Edge cubics="!2567 -448(;2567,-448 2567,-356 2567,-356q2567 -448 2567 -356);"/>
                        <Edge cubics="!3753 -356(;3753,-356 2567,-356 2567,-356q3753 -356 2567 -356);"/>
                        <Edge cubics="!2795 -844(;2795,-844 2795,-858 2795,-858q2795 -844Q2795 -858q2795 -858);"/>
                        <Edge cubics="!2765 -812(;2765,-828 2765,-844 2795,-844q2765 -812Q2765 -828q2795 -844);"/>
                        <Edge cubics="!2795 -844(;2795,-844 2581,-844 2581,-844q2795 -844 2581 -844);"/>
                        <Edge cubics="!2581 -844(;2581,-844 2581,-736 2581,-736q2581 -844 2581 -736);"/>
                        <Edge cubics="!2795 -736(;2765,-752 2765,-752 2765,-752q2795 -736Q2765 -752q2765 -752);"/>
                        <Edge cubics="!2581 -736(;2581,-736 2795,-736 2795,-736q2581 -736 2795 -736);"/>
                        <Edge cubics="!-1811 54(;-1781,54 -1781,38 -1749,38q-1811 54Q-1781 38q-1749 38);"/>
                        <Edge cubics="!-1749 190(;-1781,190 -1781,190 -1811,130q-1749 190Q-1781 190q-1811 130);"/>
                        <Edge cubics="!-1749 38(;-1735,38 -1735,54 -1719,54q-1749 38Q-1735 38q-1719 54);"/>
                        <Edge cubics="!-1719 130(;-1735,190 -1735,190 -1749,190q-1719 130Q-1735 190q-1749 190);"/>
                        <Edge cubics="!-1719 54(;-1705,68 -1705,84 -1705,100q-1719 54Q-1705 68q-1705 100);"/>
                        <Edge cubics="!-1705 100(;-1705,114 -1705,130 -1719,130q-1705 100Q-1705 114q-1719 130);"/>
                        <Edge cubics="!-1811 130(;-1811,130 -1841,114 -1841,100q-1811 130Q-1841 114q-1841 100);"/>
                        <Edge cubics="!-1841 100(;-1841,84 -1811,68 -1811,54q-1841 100Q-1841 68q-1811 54);"/>
                        <Edge cubics="!-1841 100(;-1841,100 -1705,100 -1705,100q-1841 100 -1705 100);"/>
                        <Edge cubics="!-609 -266(;-609,-266 -1537,-160 -1537,-160q-609 -266 -1537 -160);"/>
                        <Edge cubics="!-2601 -144(;-2601,-144 -2601,-98 -2601,-98q-2601 -144 -2601 -98);"/>
                        <Edge cubics="!-2601 -144(;-2601,-144 -2661,-144 -2661,-144q-2601 -144 -2661 -144);"/>
                        <Edge cubics="!-2601 -98(;-2601,-98 -2479,8 -2479,8q-2601 -98 -2479 8);"/>
                        <Edge cubics="!-2479 8(;-2479,100 -2433,190 -2297,220q-2479 8Q-2465 190q-2297 220);"/>
                        <Edge cubics="!-2297 220(;-2297,220 -2267,190 -2267,190q-2297 220 -2267 190);"/>
                        <Edge cubics="!-2267 190(;-2433,84 -2449,8 -2343,-144q-2267 190Q-2479 38q-2343 -144);"/>
                        <Edge cubics="!-1917 -144(;-1917,-144 -2343,-144 -2343,-144q-1917 -144 -2343 -144);"/>
                        <Edge cubics="!-2343 -144(;-2343,-144 -2601,-144 -2601,-144q-2343 -144 -2601 -144);"/>
                        <Edge cubics="!-1749 220(;-1749,220 -1719,252 -1719,252q-1749 220 -1719 252);"/>
                        <Edge cubics="!-1749 220(;-1749,220 -1901,220 -1901,220q-1749 220 -1901 220);"/>
                        <Edge cubics="!-1719 252(;-1719,252 -1719,418 -1719,418q-1719 252 -1719 418);"/>
                        <Edge cubics="!-1719 418(;-1719,418 -1673,418 -1673,418q-1719 418 -1673 418);"/>
                        <Edge cubics="!-1673 418(;-1673,418 -1673,220 -1673,220q-1673 418 -1673 220);"/>
                        <Edge cubics="!-1673 220(;-1673,220 -1749,220 -1749,220q-1673 220 -1749 220);"/>
                        <Edge cubics="!-1659 220(;-1659,220 -1673,220 -1673,220q-1659 220 -1673 220);"/>
                        <Edge cubics="!-3559 84(;-3513,114 -3467,190 -3467,236q-3559 84Q-3467 114q-3467 236);"/>
                        <Edge cubics="!-3559 8(;-3559,8 -3559,84 -3559,84q-3559 8 -3559 84);"/>
                        <Edge cubics="!-2859 328(;-2829,282 -2723,236 -2661,220q-2859 328Q-2813 236q-2661 220);"/>
                        <Edge cubics="!-3103 1270(;-3133,1208 -3133,1148 -3103,1012q-3103 1270Q-3163 1164q-3103 1012);"/>
                        <Edge cubics="!-3223 1436(;-3179,1406 -3133,1360 -3103,1270q-3223 1436Q-3133 1392q-3103 1270);"/>
                        <Edge cubics="!-77 -1390(;-77,-1390 -215,-1436 -215,-1436q-77 -1390 -215 -1436);"/>
                        <Edge cubics="!-215 -1436(;-215,-1436 -229,-1390 -229,-1390q-215 -1436 -229 -1390);"/>
                        <Edge cubics="!-229 -1390(;-229,-1390 -153,-1314 -153,-1314q-229 -1390 -153 -1314);"/>
                        <Edge cubics="!-153 -1314(;-153,-1314 -77,-1390 -77,-1390q-153 -1314 -77 -1390);"/>
                        <Edge cubics="!-1537 -144(;-1537,-144 -609,-144 -609,-144q-1537 -144 -609 -144);"/>
                        <Edge cubics="!561 -1314(;597,-1324 633,-1328 671,-1330q561 -1314Q615 -1328q671 -1330);"/>
                        <Edge cubics="!683 -1330(;683,-1330 671,-1330 671,-1330q683 -1330 671 -1330);"/>
                        <Edge cubics="!671 -1330(;671,-1330 -17,-1330 -17,-1330q671 -1330 -17 -1330);"/>
                        <Edge cubics="!2821 -1090(;2821,-1090 2897,-1090 2897,-1090q2821 -1090 2897 -1090);"/>
                        <Edge cubics="!2897 -1014(;2897,-1014 2821,-1014 2821,-1014q2897 -1014 2821 -1014);"/>
                        <Edge cubics="!2897 -1090(;2897,-1090 2897,-1014 2897,-1014q2897 -1090 2897 -1014);"/>
                        <Edge cubics="!2821 -1014(;2821,-1014 2821,-1090 2821,-1090q2821 -1014 2821 -1090);"/>
                        <Edge cubics="!3391 -1090(;3391,-1090 3467,-1090 3467,-1090q3391 -1090 3467 -1090);"/>
                        <Edge cubics="!3277 -1090(;3277,-1090 3353,-1090 3353,-1090q3277 -1090 3353 -1090);"/>
                        <Edge cubics="!2935 -1090(;2935,-1090 3011,-1090 3011,-1090q2935 -1090 3011 -1090);"/>
                        <Edge cubics="!3049 -1090(;3049,-1090 3125,-1090 3125,-1090q3049 -1090 3125 -1090);"/>
                        <Edge cubics="!3011 -1014(;3011,-1014 2935,-1014 2935,-1014q3011 -1014 2935 -1014);"/>
                        <Edge cubics="!3125 -1014(;3125,-1014 3049,-1014 3049,-1014q3125 -1014 3049 -1014);"/>
                        <Edge cubics="!3467 -1014(;3467,-1014 3391,-1014 3391,-1014q3467 -1014 3391 -1014);"/>
                        <Edge cubics="!3353 -1014(;3353,-1014 3277,-1014 3277,-1014q3353 -1014 3277 -1014);"/>
                        <Edge cubics="!3391 -1014(;3391,-1014 3391,-1090 3391,-1090q3391 -1014 3391 -1090);"/>
                        <Edge cubics="!3467 -1090(;3467,-1090 3467,-1014 3467,-1014q3467 -1090 3467 -1014);"/>
                        <Edge cubics="!3277 -1014(;3277,-1014 3277,-1090 3277,-1090q3277 -1014 3277 -1090);"/>
                        <Edge cubics="!3353 -1090(;3353,-1090 3353,-1014 3353,-1014q3353 -1090 3353 -1014);"/>
                        <Edge cubics="!2935 -1014(;2935,-1014 2935,-1090 2935,-1090q2935 -1014 2935 -1090);"/>
                        <Edge cubics="!3011 -1090(;3011,-1090 3011,-1014 3011,-1014q3011 -1090 3011 -1014);"/>
                        <Edge cubics="!3049 -1014(;3049,-1014 3049,-1090 3049,-1090q3049 -1014 3049 -1090);"/>
                        <Edge cubics="!3125 -1090(;3125,-1090 3125,-1014 3125,-1014q3125 -1090 3125 -1014);"/>
                        <Edge cubics="!3163 -1014(;3163,-1014 3163,-1090 3163,-1090q3163 -1014 3163 -1090);"/>
                        <Edge cubics="!3239 -1014(;3239,-1014 3163,-1014 3163,-1014q3239 -1014 3163 -1014);"/>
                        <Edge cubics="!3239 -1090(;3239,-1090 3239,-1014 3239,-1014q3239 -1090 3239 -1014);"/>
                        <Edge cubics="!3163 -1090(;3163,-1090 3239,-1090 3239,-1090q3163 -1090 3239 -1090);"/>
                        <Edge cubics="!3615 -888(;3615,-888 3615,-722 3615,-722q3615 -888 3615 -722);"/>
                        <Edge cubics="!-2823 -632(;-2793,-632 -2769,-622 -2747,-600q-2823 -632Q-2779 -632q-2747 -600);"/>
                        <Edge cubics="!-2899 -448(;-2921,-470 -2931,-494 -2931,-524q-2899 -448Q-2931 -480q-2931 -524);"/>
                        <Edge cubics="!-2715 -524(;-2715,-494 -2725,-470 -2747,-448q-2715 -524Q-2715 -480q-2747 -448);"/>
                        <Edge cubics="!-2747 -448(;-2769,-426 -2793,-416 -2823,-416q-2747 -448Q-2779 -416q-2823 -416);"/>
                        <Edge cubics="!-2823 -416(;-2853,-416 -2877,-426 -2899,-448q-2823 -416Q-2867 -416q-2899 -448);"/>
                        <Edge cubics="!-2931 -524(;-2931,-554 -2921,-578 -2899,-600q-2931 -524Q-2931 -568q-2899 -600);"/>
                        <Edge cubics="!-2899 -600(;-2877,-622 -2853,-632 -2823,-632q-2899 -600Q-2867 -632q-2823 -632);"/>
                        <Edge cubics="!-2747 -600(;-2725,-578 -2715,-554 -2715,-524q-2747 -600Q-2715 -568q-2715 -524);"/>
                        <Edge cubics="!-2553 324(;-2549,325 -2545,327 -2541,328q-2553 324Q-2547 326q-2541 328);"/>
                        <Edge cubics="!-2661 220(;-2652,268 -2616,303 -2553,324q-2661 220Q-2648 292q-2553 324);"/>
                        <Edge cubics="!5247 -448(;5247,-448 5247,-356 5247,-356q5247 -448 5247 -356);"/>
                        <Edge cubics="!5247 -508(;5247,-508 5247,-448 5247,-448q5247 -508 5247 -448);"/>
                        <Edge cubics="!5247 -706(;5247,-706 5247,-508 5247,-508q5247 -706 5247 -508);"/>
                        <Edge cubics="!5247 -706(;5247,-706 4177,-706 4177,-706q5247 -706 4177 -706);"/>
                        <Edge cubics="!4193 -508(;4193,-508 5247,-508 5247,-508q4193 -508 5247 -508);"/>
                        <Edge cubics="!3935 -448(;3935,-448 5247,-448 5247,-448q3935 -448 5247 -448);"/>
                        <Edge cubics="!5247 -356(;5247,-356 3859,-356 3859,-356q5247 -356 3859 -356);"/>
                        <Edge cubics="!7145 -1406(;7145,-1406 7023,-1406 7023,-1406q7145 -1406 7023 -1406);"/>
                        <Edge cubics="!7207 -1314(;7207,-1314 7145,-1406 7145,-1406q7207 -1314 7145 -1406);"/>
                        <Edge cubics="!7283 -812(;7283,-812 7207,-812 7207,-812q7283 -812 7207 -812);"/>
                        <Edge cubics="!7283 -722(;7283,-722 7283,-812 7283,-812q7283 -722 7283 -812);"/>
                        <Edge cubics="!7221 -464(;7221,-464 7267,-524 7267,-524q7221 -464 7267 -524);"/>
                        <Edge cubics="!7221 -312(;7221,-312 7221,-464 7221,-464q7221 -312 7221 -464);"/>
                        <Edge cubics="!7115 -312(;7115,-312 7221,-312 7221,-312q7115 -312 7221 -312);"/>
                        <Edge cubics="!7435 -722(;7435,-722 7283,-722 7283,-722q7435 -722 7283 -722);"/>
                        <Edge cubics="!7435 -524(;7435,-524 7435,-722 7435,-722q7435 -524 7435 -722);"/>
                        <Edge cubics="!7207 -812(;7207,-812 7207,-1314 7207,-1314q7207 -812 7207 -1314);"/>
                        <Edge cubics="!6963 -1330(;6963,-1330 6963,-1132 6963,-1132q6963 -1330 6963 -1132);"/>
                        <Edge cubics="!6947 -508(;6857,-540 6781,-570 6781,-706q6947 -508Q6781 -540q6781 -706);"/>
                        <Edge cubics="!6947 -508(;6947,-508 6947,-448 6947,-448q6947 -508 6947 -448);"/>
                        <Edge cubics="!6963 -1132(;6963,-1132 6781,-706 6781,-706q6963 -1132 6781 -706);"/>
                        <Edge cubics="!7023 -1406(;7023,-1406 6963,-1330 6963,-1330q7023 -1406 6963 -1330);"/>
                        <Edge cubics="!6947 -448(;6947,-448 7115,-448 7115,-448q6947 -448 7115 -448);"/>
                        <Edge cubics="!7115 -356(;7115,-356 7115,-312 7115,-312q7115 -356 7115 -312);"/>
                        <Edge cubics="!7115 -448(;7115,-448 7115,-356 7115,-356q7115 -448 7115 -356);"/>
                        <Edge cubics="!7267 -524(;7267,-524 7283,-524 7283,-524q7267 -524 7283 -524);"/>
                        <Edge cubics="!7283 -722(;7283,-722 7283,-524 7283,-524q7283 -722 7283 -524);"/>
                        <Edge cubics="!7283 -524(;7283,-524 7435,-524 7435,-524q7283 -524 7435 -524);"/>
                        <Edge cubics="!7023 -1048(;7023,-1048 6969,-758 6969,-758q7023 -1048 6969 -758);"/>
                        <Edge cubics="!6969 -758(;6969,-758 7119,-758 7119,-758q6969 -758 7119 -758);"/>
                        <Edge cubics="!7119 -742(;7119,-742 7119,-758 7119,-758q7119 -742 7119 -758);"/>
                        <Edge cubics="!7023 -1048(;7023,-1048 7119,-1048 7119,-1048q7023 -1048 7119 -1048);"/>
                        <Edge cubics="!7119 -758(;7119,-758 7119,-1048 7119,-1048q7119 -758 7119 -1048);"/>
                        <Edge cubics="!5377 -706(;5377,-706 5377,-508 5377,-508q5377 -706 5377 -508);"/>
                        <Edge cubics="!5377 -448(;5377,-448 5377,-356 5377,-356q5377 -448 5377 -356);"/>
                        <Edge cubics="!5377 -356(;5334,-320 5290,-320 5247,-356q5377 -356Q5312 -302q5247 -356);"/>
                        <Edge cubics="!5247 -508(;5247,-508 5377,-508 5377,-508q5247 -508 5377 -508);"/>
                        <Edge cubics="!5377 -706(;5377,-706 5247,-706 5247,-706q5377 -706 5247 -706);"/>
                        <Edge cubics="!5247 -448(;5247,-448 5377,-448 5377,-448q5247 -448 5377 -448);"/>
                        <Edge cubics="!5377 -508(;5377,-508 5377,-448 5377,-448q5377 -508 5377 -448);"/>
                        <Edge cubics="!5377 -508(;5377,-508 6947,-508 6947,-508q5377 -508 6947 -508);"/>
                        <Edge cubics="!6781 -706(;6781,-706 5377,-706 5377,-706q6781 -706 5377 -706);"/>
                        <Edge cubics="!5377 -448(;5377,-448 6947,-448 6947,-448q5377 -448 6947 -448);"/>
                        <Edge cubics="!7115 -356(;7115,-356 5377,-356 5377,-356q7115 -356 5377 -356);"/>
                        <Edge cubics="!-7334 1200(;-7270,1305 -7177,1340 -7054,1304q-7334 1200Q-7239 1358q-7054 1304);"/>
                        <Edge cubics="!-7435 -303(;-7435,-303 -7334,1200 -7334,1200q-7435 -303 -7334 1200);"/>
                        <Edge cubics="!-4005 -77(;-4005,-77 -4114,-672 -4114,-672q-4005 -77 -4114 -672);"/>
                        <Edge cubics="!-4114 -672(;-4114,-672 -4611,-648 -4611,-648q-4114 -672 -4611 -648);"/>
                        <Edge cubics="!-5710 1158(;-5623,1142 -5579,1083 -5576,982q-5710 1158Q-5580 1134q-5576 982);"/>
                        <Edge cubics="!-5206 201(;-5206,201 -4005,-77 -4005,-77q-5206 201 -4005 -77);"/>
                        <Edge cubics="!-5576 982(;-5649,668 -5525,408 -5206,201q-5576 982Q-5685 511q-5206 201);"/>
                        <Edge cubics="!-4611 -648(;-4611,-648 -7435,-303 -7435,-303q-4611 -648 -7435 -303);"/>
                        <Edge cubics="!-7054 1304(;-7054,1304 -5710,1158 -5710,1158q-7054 1304 -5710 1158);"/>
                        <Edge cubics="!-3619 -144(;-3619,-144 -4005,-77 -4005,-77q-3619 -144 -4005 -77);"/>
                        <Edge cubics="!-4114 -672(;-4114,-672 -3695,-736 -3695,-736q-4114 -672 -3695 -736);"/>
                      </edges>
                    </DOMShape>
                    <DOMGroup>
                      <transformationPoint>
                        <Point x="-89.35" y="-62.2"/>
                      </transformationPoint>
                      <members>
                        <DOMShape>
                          <transformationPoint>
                            <Point x="-89.35" y="-62.2"/>
                          </transformationPoint>
                          <fills>
                            <FillStyle index="1">
                              <SolidColor color="#141414"/>
                            </FillStyle>
                          </fills>
                          <strokes>
                            <StrokeStyle index="1">
                              <SolidStroke scaleMode="normal" weight="0.05" solidStyle="hairline">
                                <fill>
                                  <SolidColor alpha="0.498039215686275"/>
                                </fill>
                              </SolidStroke>
                            </StrokeStyle>
                          </strokes>
                          <edges>
                            <Edge fillStyle1="1" strokeStyle="1" edges="
!-2115 -1224|-2195 -1224!-2195 -1224|-2195 -1264!-2195 -1264|-2115 -1264!-2115 -1264|-2115 -1224!-2341 -1264|-2261 -1264!-2261 -1264|-2261 -1224!-2261 -1224|-2341 -1224!-2341 -1224|-2341 -1264!-2489 -1224|-2489 -1264!-2489 -1264|-2409
 -1264!-2409 -1264|-2409 -1224!-2409 -1224|-2489 -1224!-2047 -1264|-1967 -1264!-1967 -1264|-1967 -1224!-1967 -1224|-2047 -1224!-2047 -1224|-2047 -1264!-1673 -1224|-1753 -1224!-1753 -1224|-1753 -1264!-1753 -1264|-1673 -1264!-1673 -1264
|-1673 -1224!-1901 -1224|-1901 -1264!-1901 -1264|-1821 -1264!-1821 -1264|-1821 -1224!-1821 -1224|-1901 -1224!-2929 -1224|-2929 -1264!-2929 -1264|-2849 -1264!-2849 -1264|-2849 -1224!-2849 -1224|-2929 -1224!-2703 -1224|-2783 -1224!-2783
 -1224|-2783 -1264!-2783 -1264|-2703 -1264!-2703 -1264|-2703 -1224!-2555 -1264|-2555 -1224!-2555 -1224|-2635 -1224!-2635 -1224|-2635 -1264!-2635 -1264|-2555 -1264!-791 -1224|-871 -1224!-871 -1224|-871 -1264!-871 -1264|-791 -1264!-791
 -1264|-791 -1224!-725 -1264|-645 -1264!-645 -1264|-645 -1224!-645 -1224|-725 -1224!-725 -1224|-725 -1264!-1233 -1224|-1313 -1224!-1313 -1224|-1313 -1264!-1313 -1264|-1233 -1264!-1233 -1264|-1233 -1224!-1527 -1264|-1527 -1224!-1527 -1224
|-1607 -1224!-1607 -1224|-1607 -1264!-1607 -1264|-1527 -1264!-1379 -1224|-1459 -1224!-1459 -1224|-1459 -1264!-1459 -1264|-1379 -1264!-1379 -1264|-1379 -1224!-1085 -1224|-1165 -1224!-1165 -1224|-1165 -1264!-1165 -1264|-1085 -1264!-1085
 -1264|-1085 -1224!-939 -1264|-939 -1224!-939 -1224|-1019 -1224!-1019 -1224|-1019 -1264!-1019 -1264|-939 -1264"/>
                            <Edge cubics="!-725 -1224(;-725,-1224 -725,-1264 -725,-1264q-725 -1224 -725 -1264);"/>
                            <Edge cubics="!-645 -1224(;-645,-1224 -725,-1224 -725,-1224q-645 -1224 -725 -1224);"/>
                            <Edge cubics="!-645 -1264(;-645,-1264 -645,-1224 -645,-1224q-645 -1264 -645 -1224);"/>
                            <Edge cubics="!-725 -1264(;-725,-1264 -645,-1264 -645,-1264q-725 -1264 -645 -1264)-645,-1264;"/>
                            <Edge cubics="!-2703 -1264(;-2703,-1264 -2703,-1224 -2703,-1224q-2703 -1264 -2703 -1224);"/>
                            <Edge cubics="!-2635 -1224(;-2635,-1224 -2635,-1264 -2635,-1264q-2635 -1224 -2635 -1264);"/>
                            <Edge cubics="!-2849 -1224(;-2849,-1224 -2929,-1224 -2929,-1224q-2849 -1224 -2929 -1224);"/>
                            <Edge cubics="!-2929 -1224(;-2929,-1224 -2929,-1264 -2929,-1264q-2929 -1224 -2929 -1264);"/>
                            <Edge cubics="!-2929 -1264(;-2929,-1264 -2849,-1264 -2849,-1264q-2929 -1264 -2849 -1264);"/>
                            <Edge cubics="!-2783 -1224(;-2783,-1224 -2783,-1264 -2783,-1264q-2783 -1224 -2783 -1264);"/>
                            <Edge cubics="!-2849 -1264(;-2849,-1264 -2849,-1224 -2849,-1224q-2849 -1264 -2849 -1224);"/>
                            <Edge cubics="!-2703 -1224(;-2703,-1224 -2783,-1224 -2783,-1224q-2703 -1224 -2783 -1224);"/>
                            <Edge cubics="!-2783 -1264(;-2783,-1264 -2703,-1264 -2703,-1264q-2783 -1264 -2703 -1264);"/>
                            <Edge cubics="!-2195 -1224(;-2195,-1224 -2195,-1264 -2195,-1264q-2195 -1224 -2195 -1264);"/>
                            <Edge cubics="!-2341 -1224(;-2341,-1224 -2341,-1264 -2341,-1264q-2341 -1224 -2341 -1264);"/>
                            <Edge cubics="!-2261 -1224(;-2261,-1224 -2341,-1224 -2341,-1224q-2261 -1224 -2341 -1224);"/>
                            <Edge cubics="!-2261 -1264(;-2261,-1264 -2261,-1224 -2261,-1224q-2261 -1264 -2261 -1224);"/>
                            <Edge cubics="!-2341 -1264(;-2341,-1264 -2261,-1264 -2261,-1264q-2341 -1264 -2261 -1264);"/>
                            <Edge cubics="!-2409 -1224(;-2409,-1224 -2489,-1224 -2489,-1224q-2409 -1224 -2489 -1224);"/>
                            <Edge cubics="!-2555 -1264(;-2555,-1264 -2555,-1224 -2555,-1224q-2555 -1264 -2555 -1224);"/>
                            <Edge cubics="!-2409 -1264(;-2409,-1264 -2409,-1224 -2409,-1224q-2409 -1264 -2409 -1224);"/>
                            <Edge cubics="!-2489 -1264(;-2489,-1264 -2409,-1264 -2409,-1264q-2489 -1264 -2409 -1264);"/>
                            <Edge cubics="!-2489 -1224(;-2489,-1224 -2489,-1264 -2489,-1264q-2489 -1224 -2489 -1264);"/>
                            <Edge cubics="!-2635 -1264(;-2635,-1264 -2555,-1264 -2555,-1264q-2635 -1264 -2555 -1264);"/>
                            <Edge cubics="!-2555 -1224(;-2555,-1224 -2635,-1224 -2635,-1224q-2555 -1224 -2635 -1224);"/>
                            <Edge cubics="!-1085 -1264(;-1085,-1264 -1085,-1224 -1085,-1224q-1085 -1264 -1085 -1224);"/>
                            <Edge cubics="!-1019 -1224(;-1019,-1224 -1019,-1264 -1019,-1264q-1019 -1224 -1019 -1264);"/>
                            <Edge cubics="!-1233 -1264(;-1233,-1264 -1233,-1224 -1233,-1224q-1233 -1264 -1233 -1224);"/>
                            <Edge cubics="!-1233 -1224(;-1233,-1224 -1313,-1224 -1313,-1224q-1233 -1224 -1313 -1224);"/>
                            <Edge cubics="!-1313 -1224(;-1313,-1224 -1313,-1264 -1313,-1264q-1313 -1224 -1313 -1264);"/>
                            <Edge cubics="!-1165 -1224(;-1165,-1224 -1165,-1264 -1165,-1264q-1165 -1224 -1165 -1264);"/>
                            <Edge cubics="!-1313 -1264(;-1313,-1264 -1233,-1264 -1233,-1264q-1313 -1264 -1233 -1264);"/>
                            <Edge cubics="!-1085 -1224(;-1085,-1224 -1165,-1224 -1165,-1224q-1085 -1224 -1165 -1224);"/>
                            <Edge cubics="!-1165 -1264(;-1165,-1264 -1085,-1264 -1085,-1264q-1165 -1264 -1085 -1264);"/>
                            <Edge cubics="!-939 -1264(;-939,-1264 -939,-1224 -939,-1224q-939 -1264 -939 -1224);"/>
                            <Edge cubics="!-791 -1264(;-791,-1264 -791,-1224 -791,-1224q-791 -1264 -791 -1224);"/>
                            <Edge cubics="!-871 -1264(;-871,-1264 -791,-1264 -791,-1264q-871 -1264 -791 -1264);"/>
                            <Edge cubics="!-871 -1224(;-871,-1224 -871,-1264 -871,-1264q-871 -1224 -871 -1264);"/>
                            <Edge cubics="!-791 -1224(-791,-1224;-791,-1224 -871,-1224 -871,-1224q-791 -1224 -871 -1224);"/>
                            <Edge cubics="!-1019 -1264(;-1019,-1264 -939,-1264 -939,-1264q-1019 -1264 -939 -1264);"/>
                            <Edge cubics="!-939 -1224(;-939,-1224 -1019,-1224 -1019,-1224q-939 -1224 -1019 -1224);"/>
                            <Edge cubics="!-1901 -1224(;-1901,-1224 -1901,-1264 -1901,-1264q-1901 -1224 -1901 -1264);"/>
                            <Edge cubics="!-1821 -1224(;-1821,-1224 -1901,-1224 -1901,-1224q-1821 -1224 -1901 -1224);"/>
                            <Edge cubics="!-1821 -1264(;-1821,-1264 -1821,-1224 -1821,-1224q-1821 -1264 -1821 -1224);"/>
                            <Edge cubics="!-1901 -1264(;-1901,-1264 -1821,-1264 -1821,-1264q-1901 -1264 -1821 -1264);"/>
                            <Edge cubics="!-2115 -1264(;-2115,-1264 -2115,-1224 -2115,-1224q-2115 -1264 -2115 -1224);"/>
                            <Edge cubics="!-1967 -1264(;-1967,-1264 -1967,-1224 -1967,-1224q-1967 -1264 -1967 -1224);"/>
                            <Edge cubics="!-1967 -1224(;-1967,-1224 -2047,-1224 -2047,-1224q-1967 -1224 -2047 -1224);"/>
                            <Edge cubics="!-2047 -1224(;-2047,-1224 -2047,-1264 -2047,-1264q-2047 -1224 -2047 -1264);"/>
                            <Edge cubics="!-2047 -1264(;-2047,-1264 -1967,-1264 -1967,-1264q-2047 -1264 -1967 -1264);"/>
                            <Edge cubics="!-1379 -1224(;-1379,-1224 -1459,-1224 -1459,-1224q-1379 -1224 -1459 -1224);"/>
                            <Edge cubics="!-1459 -1264(;-1459,-1264 -1379,-1264 -1379,-1264q-1459 -1264 -1379 -1264);"/>
                            <Edge cubics="!-1459 -1224(;-1459,-1224 -1459,-1264 -1459,-1264q-1459 -1224 -1459 -1264);"/>
                            <Edge cubics="!-1379 -1264(;-1379,-1264 -1379,-1224 -1379,-1224q-1379 -1264 -1379 -1224);"/>
                            <Edge cubics="!-1527 -1264(;-1527,-1264 -1527,-1224 -1527,-1224q-1527 -1264 -1527 -1224);"/>
                            <Edge cubics="!-1673 -1264(;-1673,-1264 -1673,-1224 -1673,-1224q-1673 -1264 -1673 -1224);"/>
                            <Edge cubics="!-1673 -1224(;-1673,-1224 -1753,-1224 -1753,-1224q-1673 -1224 -1753 -1224);"/>
                            <Edge cubics="!-1753 -1224(;-1753,-1224 -1753,-1264 -1753,-1264q-1753 -1224 -1753 -1264);"/>
                            <Edge cubics="!-1753 -1264(;-1753,-1264 -1673,-1264 -1673,-1264q-1753 -1264 -1673 -1264);"/>
                            <Edge cubics="!-1607 -1224(;-1607,-1224 -1607,-1264 -1607,-1264q-1607 -1224 -1607 -1264);"/>
                            <Edge cubics="!-1527 -1224(;-1527,-1224 -1607,-1224 -1607,-1224q-1527 -1224 -1607 -1224);"/>
                            <Edge cubics="!-1607 -1264(;-1607,-1264 -1527,-1264 -1527,-1264q-1607 -1264 -1527 -1264);"/>
                            <Edge cubics="!-2195 -1264(;-2195,-1264 -2115,-1264 -2115,-1264q-2195 -1264 -2115 -1264);"/>
                            <Edge cubics="!-2115 -1224(;-2115,-1224 -2195,-1224 -2195,-1224q-2115 -1224 -2195 -1224);"/>
                          </edges>
                        </DOMShape>
                      </members>
                    </DOMGroup>
                    <DOMGroup>
                      <members>
                        <DOMShape>
                          <fills>
                            <FillStyle index="1">
                              <SolidColor color="#141414"/>
                            </FillStyle>
                          </fills>
                          <strokes>
                            <StrokeStyle index="1">
                              <SolidStroke scaleMode="normal" weight="0.05" solidStyle="hairline">
                                <fill>
                                  <SolidColor alpha="0.498039215686275"/>
                                </fill>
                              </SolidStroke>
                            </StrokeStyle>
                          </strokes>
                          <edges>
                            <Edge fillStyle0="1" fillStyle1="1" strokeStyle="1" edges="
!2859 -141|2739 -141"/>
                            <Edge fillStyle0="1" strokeStyle="1" edges="
!6659 -380|2740 -380!2740 -380|2657 -300"/>
                            <Edge fillStyle0="1" fillStyle1="1" strokeStyle="1" edges="
!2739 -300|2739 -141!2739 -300|2657 -300"/>
                            <Edge fillStyle1="1" strokeStyle="1" edges="
!6659 -380|6659 -508!6659 -508|6839 -508"/>
                            <Edge fillStyle0="1" fillStyle1="1" strokeStyle="1" edges="
!6659 -300|6659 -380"/>
                            <Edge fillStyle0="1" strokeStyle="1" edges="
!6659 -141[6759 -56 6839 -141"/>
                            <Edge fillStyle0="1" fillStyle1="1" strokeStyle="1" edges="
!6659 -300|6659 -141"/>
                            <Edge fillStyle0="1" strokeStyle="1" edges="
!6839 -141|6947 -141!6947 -141|6947 -508!6947 -508|6839 -508"/>
                            <Edge fillStyle0="1" fillStyle1="1" strokeStyle="1" edges="
!6839 -508|6839 -141"/>
                            <Edge fillStyle1="1" strokeStyle="1" edges="
!6659 -141|2859 -141"/>
                            <Edge fillStyle0="1" fillStyle1="1" strokeStyle="1" edges="
!2739 -300|6659 -300"/>
                            <Edge fillStyle1="1" strokeStyle="1" edges="
!2859 127|2657 127!2657 127|2657 -300"/>
                            <Edge fillStyle0="1" strokeStyle="1" edges="
!2859 127|2859 -141"/>
                            <Edge fillStyle0="1" fillStyle1="1" strokeStyle="1" edges="
!2739 -141|2859 127"/>
                            <Edge cubics="!6659 -300(;6659,-300 6659,-380 6659,-380q6659 -300 6659 -380);"/>
                            <Edge cubics="!6659 -380(;6659,-380 6659,-508 6659,-508q6659 -380 6659 -508);"/>
                            <Edge cubics="!6659 -508(;6659,-508 6839,-508 6839,-508q6659 -508 6839 -508);"/>
                            <Edge cubics="!6659 -141(;6726,-84 6786,-84 6839,-141q6659 -141Q6759 -56q6839 -141);"/>
                            <Edge cubics="!6659 -300(;6659,-300 6659,-141 6659,-141q6659 -300 6659 -141);"/>
                            <Edge cubics="!6839 -141(;6839,-141 6947,-141 6947,-141q6839 -141 6947 -141);"/>
                            <Edge cubics="!6839 -508(;6839,-508 6947,-508 6947,-508q6839 -508 6947 -508);"/>
                            <Edge cubics="!6947 -141(;6947,-141 6947,-508 6947,-508q6947 -141 6947 -508);"/>
                            <Edge cubics="!2739 -300(;2739,-300 2739,-141 2739,-141q2739 -300 2739 -141);"/>
                            <Edge cubics="!2739 -300(;2739,-300 2657,-300 2657,-300q2739 -300 2657 -300);"/>
                            <Edge cubics="!6839 -508(;6839,-508 6839,-141 6839,-141q6839 -508 6839 -141);"/>
                            <Edge cubics="!2859 -141(;2859,-141 2739,-141 2739,-141q2859 -141 2739 -141);"/>
                            <Edge cubics="!2740 -380(;2740,-380 2657,-300 2657,-300q2740 -380 2657 -300);"/>
                            <Edge cubics="!6659 -380(;6659,-380 2740,-380 2740,-380q6659 -380 2740 -380);"/>
                            <Edge cubics="!6659 -141(;6659,-141 2859,-141 2859,-141q6659 -141 2859 -141);"/>
                            <Edge cubics="!2739 -300(;2739,-300 6659,-300 6659,-300q2739 -300 6659 -300);"/>
                            <Edge cubics="!2859 127(;2859,127 2657,127 2657,127q2859 127 2657 127);"/>
                            <Edge cubics="!2657 127(;2657,127 2657,-300 2657,-300q2657 127 2657 -300);"/>
                            <Edge cubics="!2859 127(;2859,127 2859,-141 2859,-141q2859 127 2859 -141);"/>
                            <Edge cubics="!2739 -141(;2739,-141 2859,127 2859,127q2739 -141 2859 127);"/>
                          </edges>
                        </DOMShape>
                      </members>
                    </DOMGroup>
                    <DOMGroup>
                      <transformationPoint>
                        <Point x="41.25" y="-22.75"/>
                      </transformationPoint>
                      <members>
                        <DOMShape>
                          <transformationPoint>
                            <Point x="41.25" y="-22.75"/>
                          </transformationPoint>
                          <fills>
                            <FillStyle index="1">
                              <SolidColor alpha="0.0980392156862745"/>
                            </FillStyle>
                            <FillStyle index="2">
                              <SolidColor color="#FFFFFF" alpha="0.0274509803921569"/>
                            </FillStyle>
                          </fills>
                          <edges>
                            <Edge fillStyle1="1" edges="
!1239 -590|1311 -590!1401 -590|1473 -590"/>
                            <Edge fillStyle1="2" edges="
!1311 -590|1401 -590!1473 -590|1563 -590"/>
                            <Edge fillStyle1="1" edges="
!987 -322|915 -322!915 -322|915 -590!915 -590|987 -590!1077 -590|1149 -590"/>
                            <Edge fillStyle1="2" edges="
!987 -590|1077 -590!1077 -322|987 -322"/>
                            <Edge fillStyle1="1" edges="
!1149 -322|1077 -322!1473 -322|1401 -322!1311 -322|1239 -322"/>
                            <Edge fillStyle1="2" edges="
!1401 -322|1311 -322!1563 -322|1473 -322!1149 -590|1239 -590!1239 -322|1149 -322"/>
                            <Edge fillStyle0="1" fillStyle1="2" edges="
!987 -322|987 -590!1239 -590|1239 -322!1563 -590|1563 -322!1311 -322|1311 -590!1401 -590|1401 -322!1473 -322|1473 -590!1077 -590|1077 -322"/>
                            <Edge fillStyle0="2" fillStyle1="1" edges="
!1149 -590|1149 -322"/>
                            <Edge fillStyle1="2" edges="
!2121 -590|2211 -590"/>
                            <Edge fillStyle1="1" edges="
!2211 -590|2283 -590"/>
                            <Edge fillStyle1="2" edges="
!2283 -590|2373 -590"/>
                            <Edge fillStyle1="1" edges="
!2049 -590|2121 -590"/>
                            <Edge fillStyle1="2" edges="
!1635 -590|1725 -590"/>
                            <Edge fillStyle1="1" edges="
!1725 -590|1797 -590!1887 -590|1959 -590"/>
                            <Edge fillStyle1="2" edges="
!1797 -590|1887 -590"/>
                            <Edge fillStyle1="1" edges="
!1959 -322|1887 -322"/>
                            <Edge fillStyle1="2" edges="
!1725 -322|1635 -322"/>
                            <Edge fillStyle1="1" edges="
!1797 -322|1725 -322"/>
                            <Edge fillStyle1="2" edges="
!1887 -322|1797 -322!2211 -322|2121 -322"/>
                            <Edge fillStyle1="1" edges="
!2121 -322|2049 -322!2283 -322|2211 -322"/>
                            <Edge fillStyle1="2" edges="
!2373 -322|2283 -322!1959 -590|2049 -590!2049 -322|1959 -322"/>
                            <Edge fillStyle0="1" fillStyle1="2" edges="
!1725 -590|1725 -322!2049 -590|2049 -322!2121 -322|2121 -590!2373 -590|2373 -322!2211 -590|2211 -322!2283 -322|2283 -590!1887 -590|1887 -322"/>
                            <Edge fillStyle0="2" fillStyle1="1" edges="
!1959 -590|1959 -322"/>
                            <Edge fillStyle0="1" fillStyle1="2" edges="
!1797 -322|1797 -590!1635 -322|1635 -590"/>
                            <Edge fillStyle1="1" edges="
!2373 -590|2445 -590!2445 -590|2445 -322!2445 -322|2373 -322!1563 -590|1635 -590!1635 -322|1563 -322"/>
                            <Edge cubics="!1149 -322(;1149,-322 1149,-590 1149,-590q1149 -322 1149 -590);"/>
                            <Edge cubics="!915 -590(;915,-590 915,-322 915,-322q915 -590 915 -322);"/>
                            <Edge cubics="!987 -322(;987,-322 987,-590 987,-590q987 -322 987 -590);"/>
                            <Edge cubics="!1077 -322(;1077,-322 987,-322 987,-322q1077 -322 987 -322);"/>
                            <Edge cubics="!1077 -590(;1077,-590 1077,-322 1077,-322q1077 -590 1077 -322);"/>
                            <Edge cubics="!987 -590(;987,-590 1077,-590 1077,-590q987 -590 1077 -590);"/>
                            <Edge cubics="!915 -590(;915,-590 987,-590 987,-590q915 -590 987 -590);"/>
                            <Edge cubics="!1077 -590(;1077,-590 1149,-590 1149,-590q1077 -590 1149 -590);"/>
                            <Edge cubics="!1149 -322(;1149,-322 1077,-322 1077,-322q1149 -322 1077 -322);"/>
                            <Edge cubics="!987 -322(;987,-322 915,-322 915,-322q987 -322 915 -322);"/>
                            <Edge cubics="!1149 -590(;1149,-590 1239,-590 1239,-590q1149 -590 1239 -590);"/>
                            <Edge cubics="!1311 -590(;1311,-590 1401,-590 1401,-590q1311 -590 1401 -590);"/>
                            <Edge cubics="!1239 -322(;1239,-322 1149,-322 1149,-322q1239 -322 1149 -322);"/>
                            <Edge cubics="!1401 -322(;1401,-322 1311,-322 1311,-322q1401 -322 1311 -322);"/>
                            <Edge cubics="!1239 -590(;1239,-590 1239,-322 1239,-322q1239 -590 1239 -322);"/>
                            <Edge cubics="!1401 -590(;1401,-590 1401,-322 1401,-322q1401 -590 1401 -322);"/>
                            <Edge cubics="!1311 -322(;1311,-322 1311,-590 1311,-590q1311 -322 1311 -590);"/>
                            <Edge cubics="!1473 -590(;1473,-590 1563,-590 1563,-590q1473 -590 1563 -590);"/>
                            <Edge cubics="!1635 -590(;1635,-590 1725,-590 1725,-590q1635 -590 1725 -590);"/>
                            <Edge cubics="!1563 -322(;1563,-322 1473,-322 1473,-322q1563 -322 1473 -322);"/>
                            <Edge cubics="!1725 -322(;1725,-322 1635,-322 1635,-322q1725 -322 1635 -322);"/>
                            <Edge cubics="!1473 -322(;1473,-322 1473,-590 1473,-590q1473 -322 1473 -590);"/>
                            <Edge cubics="!1563 -590(;1563,-590 1563,-322 1563,-322q1563 -590 1563 -322);"/>
                            <Edge cubics="!1635 -322(;1635,-322 1635,-590 1635,-590q1635 -322 1635 -590);"/>
                            <Edge cubics="!1725 -590(;1725,-590 1725,-322 1725,-322q1725 -590 1725 -322);"/>
                            <Edge cubics="!1797 -322(;1797,-322 1797,-590 1797,-590q1797 -322 1797 -590);"/>
                            <Edge cubics="!1887 -322(;1887,-322 1797,-322 1797,-322q1887 -322 1797 -322);"/>
                            <Edge cubics="!1887 -590(;1887,-590 1887,-322 1887,-322q1887 -590 1887 -322);"/>
                            <Edge cubics="!1797 -590(;1797,-590 1887,-590 1887,-590q1797 -590 1887 -590);"/>
                            <Edge cubics="!1239 -590(;1239,-590 1311,-590 1311,-590q1239 -590 1311 -590);"/>
                            <Edge cubics="!1401 -590(;1401,-590 1473,-590 1473,-590q1401 -590 1473 -590);"/>
                            <Edge cubics="!1725 -590(;1725,-590 1797,-590 1797,-590q1725 -590 1797 -590);"/>
                            <Edge cubics="!1563 -590(;1563,-590 1635,-590 1635,-590q1563 -590 1635 -590);"/>
                            <Edge cubics="!1797 -322(;1797,-322 1725,-322 1725,-322q1797 -322 1725 -322);"/>
                            <Edge cubics="!1473 -322(;1473,-322 1401,-322 1401,-322q1473 -322 1401 -322);"/>
                            <Edge cubics="!1311 -322(;1311,-322 1239,-322 1239,-322q1311 -322 1239 -322);"/>
                            <Edge cubics="!1635 -322(;1635,-322 1563,-322 1563,-322q1635 -322 1563 -322);"/>
                            <Edge cubics="!1959 -322(;1959,-322 1959,-590 1959,-590q1959 -322 1959 -590);"/>
                            <Edge cubics="!1887 -590(;1887,-590 1959,-590 1959,-590q1887 -590 1959 -590);"/>
                            <Edge cubics="!1959 -322(;1959,-322 1887,-322 1887,-322q1959 -322 1887 -322);"/>
                            <Edge cubics="!1959 -590(;1959,-590 2049,-590 2049,-590q1959 -590 2049 -590);"/>
                            <Edge cubics="!2121 -590(;2121,-590 2211,-590 2211,-590q2121 -590 2211 -590);"/>
                            <Edge cubics="!2049 -322(;2049,-322 1959,-322 1959,-322q2049 -322 1959 -322);"/>
                            <Edge cubics="!2211 -322(;2211,-322 2121,-322 2121,-322q2211 -322 2121 -322);"/>
                            <Edge cubics="!2049 -590(;2049,-590 2049,-322 2049,-322q2049 -590 2049 -322);"/>
                            <Edge cubics="!2211 -590(;2211,-590 2211,-322 2211,-322q2211 -590 2211 -322);"/>
                            <Edge cubics="!2121 -322(;2121,-322 2121,-590 2121,-590q2121 -322 2121 -590);"/>
                            <Edge cubics="!2283 -590(;2283,-590 2373,-590 2373,-590q2283 -590 2373 -590);"/>
                            <Edge cubics="!2373 -322(;2373,-322 2283,-322 2283,-322q2373 -322 2283 -322);"/>
                            <Edge cubics="!2283 -322(;2283,-322 2283,-590 2283,-590q2283 -322 2283 -590);"/>
                            <Edge cubics="!2373 -590(;2373,-590 2373,-322 2373,-322q2373 -590 2373 -322);"/>
                            <Edge cubics="!2445 -322(;2445,-322 2445,-590 2445,-590q2445 -322 2445 -590);"/>
                            <Edge cubics="!2049 -590(;2049,-590 2121,-590 2121,-590q2049 -590 2121 -590);"/>
                            <Edge cubics="!2211 -590(;2211,-590 2283,-590 2283,-590q2211 -590 2283 -590);"/>
                            <Edge cubics="!2373 -590(;2373,-590 2445,-590 2445,-590q2373 -590 2445 -590);"/>
                            <Edge cubics="!2283 -322(;2283,-322 2211,-322 2211,-322q2283 -322 2211 -322);"/>
                            <Edge cubics="!2121 -322(;2121,-322 2049,-322 2049,-322q2121 -322 2049 -322);"/>
                            <Edge cubics="!2445 -322(;2445,-322 2373,-322 2373,-322q2445 -322 2373 -322);"/>
                          </edges>
                        </DOMShape>
                      </members>
                    </DOMGroup>
                    <DOMOvalObject objectWidth="6.3" objectHeight="6.3" x="-230.8" y="39.5" endAngle="0">
                      <matrix>
                        <Matrix tx="-128.5" ty="12.75"/>
                      </matrix>
                      <fill>
                        <SolidColor color="#141414"/>
                      </fill>
                      <stroke>
                        <SolidStroke scaleMode="normal" weight="0.05" solidStyle="hairline">
                          <fill>
                            <SolidColor alpha="0.498039215686275"/>
                          </fill>
                        </SolidStroke>
                      </stroke>
                    </DOMOvalObject>
                    <DOMOvalObject objectWidth="6.3" objectHeight="6.3" x="-230.8" y="39.5" endAngle="0">
                      <matrix>
                        <Matrix tx="-62.8" ty="4.75"/>
                      </matrix>
                      <fill>
                        <SolidColor color="#141414"/>
                      </fill>
                      <stroke>
                        <SolidStroke scaleMode="normal" weight="0.05" solidStyle="hairline">
                          <fill>
                            <SolidColor alpha="0.498039215686275"/>
                          </fill>
                        </SolidStroke>
                      </stroke>
                    </DOMOvalObject>
                    <DOMOvalObject objectWidth="6.3" objectHeight="6.3" x="-230.8" y="39.5" endAngle="0">
                      <matrix>
                        <Matrix tx="-133.8" ty="-48"/>
                      </matrix>
                      <fill>
                        <SolidColor color="#141414"/>
                      </fill>
                      <stroke>
                        <SolidStroke scaleMode="normal" weight="0.05" solidStyle="hairline">
                          <fill>
                            <SolidColor alpha="0.498039215686275"/>
                          </fill>
                        </SolidStroke>
                      </stroke>
                    </DOMOvalObject>
                    <DOMOvalObject objectWidth="6.3" objectHeight="6.3" x="-230.8" y="39.5" endAngle="0">
                      <matrix>
                        <Matrix tx="10.2" ty="-66.6"/>
                      </matrix>
                      <fill>
                        <SolidColor color="#141414"/>
                      </fill>
                      <stroke>
                        <SolidStroke scaleMode="normal" weight="0.05" solidStyle="hairline">
                          <fill>
                            <SolidColor alpha="0.498039215686275"/>
                          </fill>
                        </SolidStroke>
                      </stroke>
                    </DOMOvalObject>
                    <DOMOvalObject objectWidth="6.3" objectHeight="6.3" x="-230.8" y="39.5" endAngle="0">
                      <matrix>
                        <Matrix tx="-60.8" ty="-59.6"/>
                      </matrix>
                      <fill>
                        <SolidColor color="#141414"/>
                      </fill>
                      <stroke>
                        <SolidStroke scaleMode="normal" weight="0.05" solidStyle="hairline">
                          <fill>
                            <SolidColor alpha="0.498039215686275"/>
                          </fill>
                        </SolidStroke>
                      </stroke>
                    </DOMOvalObject>
                  </members>
                </DOMGroup>
              </elements>
            </DOMFrame>
          </frames>
        </DOMLayer>
      </layers>
    </DOMTimeline>
  </timeline>
</DOMSymbolItem>