<DOMSymbolItem xmlns:xsi="http://www.w3.org/2001/XMLSchema-instance" xmlns="http://ns.adobe.com/xfl/2008/" name="MC.Weapon.FMG9.Base" itemID="5c7b03c8-000004ab" lastModified="1551724337">
  <timeline>
    <DOMTimeline name="MC.Weapon.FMG9.Base">
      <layers>
        <DOMLayer name="Layer 1" color="#4F80FF" current="true" isSelected="true">
          <frames>
            <DOMFrame index="0" keyMode="9728">
              <elements>
                <DOMGroup>
                  <members>
                    <DOMGroup>
                      <members>
                        <DOMGroup selected="true">
                          <members>
                            <DOMShape selected="true">
                              <fills>
                                <FillStyle index="1">
                                  <SolidColor color="#141414"/>
                                </FillStyle>
                              </fills>
                              <strokes>
                                <StrokeStyle index="1">
                                  <SolidStroke scaleMode="normal" weight="0.05" solidStyle="hairline">
                                    <fill>
                                      <SolidColor alpha="0.498039215686275"/>
                                    </fill>
                                  </SolidStroke>
                                </StrokeStyle>
                              </strokes>
                              <edges>
                                <Edge fillStyle1="1" strokeStyle="1" edges="!1708 89S6[1630 155 1620 261!1620 261[1620 333 1652 387!1652 387[1682 437 1738 471!1738 471|1746 501!1746 501|1686 485!1686 485[1616 473 1576 407!1576 407[1566 393 1558 375!1558 375|1492 133!1492 133|1494 133!1494 133|1494 89!1494 89
|1708 89"/>
                                <Edge cubics="!1746 501(;1746,501 1686,485 1686,485q1746 501 1686 485);"/>
                                <Edge cubics="!1738 471(;1738,471 1746,501 1746,501q1738 471 1746 501);"/>
                                <Edge cubics="!1558 375(;1558,375 1492,133 1492,133q1558 375 1492 133);"/>
                                <Edge cubics="!1652 387(;1672,419 1700,449 1738,471q1652 387Q1682 437q1738 471);"/>
                                <Edge cubics="!1620 261(;1618,309 1630,351 1652,387q1620 261Q1620 333q1652 387);"/>
                                <Edge cubics="!1576 407(;1568,399 1562,387 1558,375q1576 407Q1566 393q1558 375);"/>
                                <Edge cubics="!1686 485(;1640,477 1602,451 1576,407q1686 485Q1616 473q1576 407);"/>
                                <Edge cubics="!1492 133(;1492,133 1494,133 1494,133q1492 133 1494 133);"/>
                                <Edge cubics="!1708 89(;1708,89 1494,89 1494,89q1708 89 1494 89);"/>
                                <Edge cubics="!1494 133(;1494,133 1494,89 1494,89q1494 133 1494 89)1494,89;"/>
                                <Edge cubics="!1708 89(;1656,133 1626,191 1620,261q1708 89Q1630 155q1620 261);"/>
                              </edges>
                            </DOMShape>
                          </members>
                        </DOMGroup>
                      </members>
                    </DOMGroup>
                    <DOMGroup>
                      <members>
                        <DOMShape>
                          <fills>
                            <FillStyle index="1">
                              <SolidColor color="#141414"/>
                            </FillStyle>
                          </fills>
                          <strokes>
                            <StrokeStyle index="1">
                              <SolidStroke scaleMode="normal" weight="0.05" solidStyle="hairline">
                                <fill>
                                  <SolidColor alpha="0.498039215686275"/>
                                </fill>
                              </SolidStroke>
                            </StrokeStyle>
                          </strokes>
                          <edges>
                            <Edge fillStyle1="1" strokeStyle="1" edges="
!4195 173|4195 213!4195 213|4115 213!4115 213|4115 173!4115 173|4195 173!4047 173|4047 213!4047 213|3967 213!3967 213|3967 173!3967 173|4047 173!3899 213|3819 213!3819 213|3819 173!3819 173|3899 173!3899 173|3899 213!3671 173|3751 173
!3751 173|3751 213!3751 213|3671 213!3671 213|3671 173!3523 173|3603 173!3603 173|3603 213!3603 213|3523 213!3523 213|3523 173!3455 173|3455 213!3455 213|3375 213!3375 213|3375 173!3375 173|3455 173!3307 173|3307 213!3307 213|3227 213
!3227 213|3227 173!3227 173|3307 173!3159 213|3079 213!3079 213|3079 173!3079 173|3159 173!3159 173|3159 213!2931 173|3011 173!3011 173|3011 213!3011 213|2931 213!2931 213|2931 173!2783 173|2863 173!2863 173|2863 213!2863 213|2783 213
!2783 213|2783 173!2715 173|2715 213!2715 213|2635 213!2635 213|2635 173!2635 173|2715 173!2567 173|2567 213!2567 213|2487 213!2487 213|2487 173!2487 173|2567 173!2419 213|2339 213!2339 213|2339 173!2339 173|2419 173!2419 173|2419 213
!2191 173|2271 173!2271 173|2271 213!2271 213|2191 213!2191 213|2191 173"/>
                            <Edge cubics="!2271 213(;2271,213 2191,213 2191,213q2271 213 2191 213);"/>
                            <Edge cubics="!2191 213(;2191,213 2191,173 2191,173q2191 213 2191 173);"/>
                            <Edge cubics="!2191 173(;2191,173 2271,173 2271,173q2191 173 2271 173);"/>
                            <Edge cubics="!2271 173(;2271,173 2271,213 2271,213q2271 173 2271 213);"/>
                            <Edge cubics="!4195 173(;4195,173 4195,213 4195,213q4195 173 4195 213);"/>
                            <Edge cubics="!3967 213(;3967,213 3967,173 3967,173q3967 213 3967 173);"/>
                            <Edge cubics="!4047 213(;4047,213 3967,213 3967,213q4047 213 3967 213);"/>
                            <Edge cubics="!4047 173(;4047,173 4047,213 4047,213q4047 173 4047 213);"/>
                            <Edge cubics="!3967 173(;3967,173 4047,173 4047,173q3967 173 4047 173);"/>
                            <Edge cubics="!4115 213(;4115,213 4115,173 4115,173q4115 213 4115 173);"/>
                            <Edge cubics="!4115 173(;4115,173 4195,173 4195,173q4115 173 4195 173);"/>
                            <Edge cubics="!4195 213(;4195,213 4115,213 4115,213q4195 213 4115 213);"/>
                            <Edge cubics="!3899 213(;3899,213 3819,213 3819,213q3899 213 3819 213);"/>
                            <Edge cubics="!3819 173(;3819,173 3899,173 3899,173q3819 173 3899 173);"/>
                            <Edge cubics="!3819 213(;3819,213 3819,173 3819,173q3819 213 3819 173);"/>
                            <Edge cubics="!3751 173(;3751,173 3751,213 3751,213q3751 173 3751 213);"/>
                            <Edge cubics="!3899 173(;3899,173 3899,213 3899,213q3899 173 3899 213);"/>
                            <Edge cubics="!3671 213(;3671,213 3671,173 3671,173q3671 213 3671 173);"/>
                            <Edge cubics="!3523 173(;3523,173 3603,173 3603,173q3523 173 3603 173);"/>
                            <Edge cubics="!3603 173(;3603,173 3603,213 3603,213q3603 173 3603 213);"/>
                            <Edge cubics="!3603 213(;3603,213 3523,213 3523,213q3603 213 3523 213);"/>
                            <Edge cubics="!3523 213(;3523,213 3523,173 3523,173q3523 213 3523 173);"/>
                            <Edge cubics="!3671 173(;3671,173 3751,173 3751,173q3671 173 3751 173);"/>
                            <Edge cubics="!3751 213(;3751,213 3671,213 3671,213q3751 213 3671 213);"/>
                            <Edge cubics="!3455 173(;3455,173 3455,213 3455,213q3455 173 3455 213);"/>
                            <Edge cubics="!3455 213(;3455,213 3375,213 3375,213q3455 213 3375 213);"/>
                            <Edge cubics="!3375 213(;3375,213 3375,173 3375,173q3375 213 3375 173);"/>
                            <Edge cubics="!3375 173(;3375,173 3455,173 3455,173q3375 173 3455 173);"/>
                            <Edge cubics="!3307 173(;3307,173 3307,213 3307,213q3307 173 3307 213);"/>
                            <Edge cubics="!3159 173(;3159,173 3159,213 3159,213q3159 173 3159 213);"/>
                            <Edge cubics="!3227 213(;3227,213 3227,173 3227,173q3227 213 3227 173);"/>
                            <Edge cubics="!3307 213(;3307,213 3227,213 3227,213q3307 213 3227 213);"/>
                            <Edge cubics="!3227 173(;3227,173 3307,173 3307,173q3227 173 3307 173);"/>
                            <Edge cubics="!2931 173(;2931,173 3011,173 3011,173q2931 173 3011 173);"/>
                            <Edge cubics="!3011 173(;3011,173 3011,213 3011,213q3011 173 3011 213);"/>
                            <Edge cubics="!3011 213(;3011,213 2931,213 2931,213q3011 213 2931 213);"/>
                            <Edge cubics="!2931 213(;2931,213 2931,173 2931,173q2931 213 2931 173);"/>
                            <Edge cubics="!3079 213(;3079,213 3079,173 3079,173q3079 213 3079 173);"/>
                            <Edge cubics="!2783 173(;2783,173 2863,173 2863,173q2783 173 2863 173);"/>
                            <Edge cubics="!2863 173(;2863,173 2863,213 2863,213q2863 173 2863 213);"/>
                            <Edge cubics="!2863 213(;2863,213 2783,213 2783,213q2863 213 2783 213);"/>
                            <Edge cubics="!2783 213(;2783,213 2783,173 2783,173q2783 213 2783 173);"/>
                            <Edge cubics="!2715 173(;2715,173 2715,213 2715,213q2715 173 2715 213);"/>
                            <Edge cubics="!2635 213(;2635,213 2635,173 2635,173q2635 213 2635 173);"/>
                            <Edge cubics="!2567 173(;2567,173 2567,213 2567,213q2567 173 2567 213);"/>
                            <Edge cubics="!2487 213(;2487,213 2487,173 2487,173q2487 213 2487 173);"/>
                            <Edge cubics="!2419 173(;2419,173 2419,213 2419,213q2419 173 2419 213);"/>
                            <Edge cubics="!2419 213(;2419,213 2339,213 2339,213q2419 213 2339 213);"/>
                            <Edge cubics="!2339 213(;2339,213 2339,173 2339,173q2339 213 2339 173);"/>
                            <Edge cubics="!2339 173(;2339,173 2419,173 2419,173q2339 173 2419 173);"/>
                            <Edge cubics="!2567 213(;2567,213 2487,213 2487,213q2567 213 2487 213);"/>
                            <Edge cubics="!2487 173(;2487,173 2567,173 2567,173q2487 173 2567 173);"/>
                            <Edge cubics="!2715 213(;2715,213 2635,213 2635,213q2715 213 2635 213);"/>
                            <Edge cubics="!2635 173(;2635,173 2715,173 2715,173q2635 173 2715 173);"/>
                            <Edge cubics="!3159 213(;3159,213 3079,213 3079,213q3159 213 3079 213);"/>
                            <Edge cubics="!3079 173(;3079,173 3159,173 3159,173q3079 173 3159 173);"/>
                          </edges>
                        </DOMShape>
                      </members>
                    </DOMGroup>
                    <DOMGroup>
                      <members>
                        <DOMShape>
                          <fills>
                            <FillStyle index="1">
                              <SolidColor color="#141414"/>
                            </FillStyle>
                          </fills>
                          <strokes>
                            <StrokeStyle index="1">
                              <SolidStroke scaleMode="normal" weight="0.05" solidStyle="hairline">
                                <fill>
                                  <SolidColor alpha="0.498039215686275"/>
                                </fill>
                              </SolidStroke>
                            </StrokeStyle>
                          </strokes>
                          <edges>
                            <Edge fillStyle1="1" strokeStyle="1" edges="
!405 -993|966 -1611!966 -1611[1136 -1738 1308 -1719!1308 -1719|4019 -1820!4019 -1820[4123 -1762 4164 -1661!4164 -1661[4140 -1527 3910 -1508"/>
                            <Edge fillStyle0="1" strokeStyle="1" edges="
!1155 -993[1067 -1033 1054 -1102!1054 -1102|1054 -1378!1054 -1378[1078 -1459 1162 -1495!1162 -1495|3022 -1495!3022 -1495[3071 -1472 3080 -1378!3080 -1378|3080 -1122!3080 -1122[3065 -1026 2994 -993"/>
                            <Edge fillStyle0="1" fillStyle1="1" strokeStyle="1" edges="
!319 -165|720 -165"/>
                            <Edge fillStyle1="1" strokeStyle="1" edges="
!86 -790|86 -876!86 -876|196 -876!196 -876|405 -993"/>
                            <Edge fillStyle0="1" fillStyle1="1" strokeStyle="1" edges="
!24 -745|319 -165"/>
                            <Edge fillStyle1="1" strokeStyle="1" edges="
!86 -745|86 -790!24 -745|86 -745"/>
                            <Edge fillStyle0="1" fillStyle1="1" strokeStyle="1" edges="
!405 -993|1155 -993!720 -165|1017 -165!86 -745|1707 -745!1707 -745|1752 -607!1752 -607|1978 -607!1978 -607|2043 -745!2043 -745|3707 -745"/>
                            <Edge fillStyle1="1" strokeStyle="1" edges="
!1155 -993|2994 -993!4493 -1508|4798 -1508!4798 -1508|4798 -1441"/>
                            <Edge fillStyle0="1" strokeStyle="1" edges="
!4798 -1303|4798 -1370!4798 -1370|4798 -1441"/>
                            <Edge fillStyle0="1" fillStyle1="1" strokeStyle="1" edges="
!4493 -1303|4493 -1370!4493 -1370|4493 -1441!4493 -1096|4493 -1165!4493 -1027|4493 -1096!4493 -1165|4493 -1234"/>
                            <Edge fillStyle0="1" strokeStyle="1" edges="
!4798 -1165|4798 -1234!4798 -1027|4798 -1096!4798 -1096|4798 -1165"/>
                            <Edge fillStyle0="1" fillStyle1="1" strokeStyle="1" edges="
!4798 -1096|4493 -1096!4493 -1165|4798 -1165!4798 -1027|4493 -1027!4798 -1234|4493 -1234!4493 -1303|4798 -1303!4493 -1234|4493 -1303"/>
                            <Edge fillStyle0="1" strokeStyle="1" edges="
!4798 -1234|4798 -1303"/>
                            <Edge fillStyle0="1" fillStyle1="1" strokeStyle="1" edges="
!4798 -1370|4493 -1370!4493 -1441|4798 -1441!4493 -1441|4493 -1508!3459 -1508|3459 -993!3459 -993|3728 -993!3728 -993|3728 -790!3910 -1508|3459 -1508!3293 -993|3293 -1508!3293 -1508|3459 -1508!3293 -790|3728 -790!4302 -645|3707 -645!3707
 -645|3707 -745"/>
                            <Edge fillStyle0="1" strokeStyle="1" edges="
!4493 -790|4493 -956"/>
                            <Edge fillStyle0="1" fillStyle1="1" strokeStyle="1" edges="
!4493 -956|4493 -960"/>
                            <Edge fillStyle0="1" strokeStyle="1" edges="
!4493 -745|4493 -790"/>
                            <Edge fillStyle0="1" fillStyle1="1" strokeStyle="1" edges="
!4493 -960|4798 -960"/>
                            <Edge fillStyle0="1" edges="
!4493 -956|4798 -956"/>
                            <Edge fillStyle0="1" strokeStyle="1" edges="
!4798 -956|4798 -960"/>
                            <Edge fillStyle0="1" fillStyle1="1" strokeStyle="1" edges="
!4302 -645|4302 -745!4302 -745|4493 -745!4215 -165|4302 -645!3728 -790|4493 -790"/>
                            <Edge fillStyle1="1" strokeStyle="1" edges="
!3910 -1508|4493 -1508"/>
                            <Edge fillStyle0="1" fillStyle1="1" strokeStyle="1" edges="
!3707 -745|4302 -745"/>
                            <Edge fillStyle0="1" strokeStyle="1" edges="
!4798 -960|4798 -1027"/>
                            <Edge fillStyle0="1" fillStyle1="1" strokeStyle="1" edges="
!4493 -960|4493 -1027!3293 -993|3293 -790!3293 -790|86 -790!1017 -165|4215 -165!2994 -993|3293 -993"/>
                            <Edge fillStyle0="1" strokeStyle="1" edges="
!4114 173|4237 173!4237 173[4360 286 4340 480!4340 480|4442 480!4442 480|4493 242!4493 242|4493 40"/>
                            <Edge fillStyle0="1" fillStyle1="1" strokeStyle="1" edges="
!4153 40|4114 173!4153 40|4493 40!4160 18|4153 40"/>
                            <Edge fillStyle0="1" strokeStyle="1" edges="
!1291 120|1938 120!1938 120|2015 173!2015 173|2080 173"/>
                            <Edge strokeStyle="1" edges="
!2080 173|2080 525!2080 525|1961 618!1961 618|1403 618!1403 618|1185 576"/>
                            <Edge fillStyle0="1" strokeStyle="1" edges="
!1185 576|1108 452!1108 452[1116 217 1291 120!868 816|907 697!907 697|1185 576"/>
                            <Edge fillStyle0="1" fillStyle1="1" strokeStyle="1" edges="
!1291 120|989 120"/>
                            <Edge fillStyle0="1" strokeStyle="1" edges="
!21 120[132 208 132 383!132 383|82 525"/>
                            <Edge fillStyle0="1" fillStyle1="1" strokeStyle="1" edges="
!82 525|181 525!181 525|326 120!123 120|21 120!326 120|123 120!319 -165[381 -1 494 16!494 16|720 16!720 16|720 -165!13 1439[13 1531 78 1594!78 1594[142 1660 231 1660!231 1660[323 1660 386 1594!386 1594[450 1531 450 1439!450 1439[450 1350
 386 1285!386 1285[323 1223 231 1223!231 1223[142 1223 78 1285!78 1285[13 1350 13 1439"/>
                            <Edge fillStyle0="1" strokeStyle="1" edges="
!82 525|-287 1568!-287 1568[-302 1734 -144 1770!-144 1770[-125 1775 -104 1777!-104 1777|410 1820!410 1820[631 1824 646 1777!646 1777|603 1656!603 1656|868 816"/>
                            <Edge fillStyle0="1" fillStyle1="1" strokeStyle="1" edges="
!989 120|326 120!989 120|785 714!785 714|868 816"/>
                            <Edge fillStyle0="1" strokeStyle="1" edges="
!2080 173|4114 173"/>
                            <Edge fillStyle0="1" fillStyle1="1" strokeStyle="1" edges="
!1017 -165|1017 16!1017 16|4160 18!-104 -92|123 -92!123 -92|123 120"/>
                            <Edge fillStyle0="1" strokeStyle="1" edges="
!4493 40|4493 -745"/>
                            <Edge fillStyle0="1" fillStyle1="1" strokeStyle="1" edges="
!4215 -165|4160 18"/>
                            <Edge fillStyle1="1" strokeStyle="1" edges="
!-4798 -165|-4798 -790!-4798 -790|-4720 -790"/>
                            <Edge fillStyle0="1" fillStyle1="1" strokeStyle="1" edges="
!-4720 -165|-4720 -790!-4720 -165|-4798 -165"/>
                            <Edge fillStyle0="1" strokeStyle="1" edges="
!-39 -745[-67 -938 -241 -956!-241 -956|-1782 -893!-1782 -893[-1931 -880 -1927 -790"/>
                            <Edge fillStyle0="1" fillStyle1="1" strokeStyle="1" edges="
!-1927 -790[-1884 -680 -1737 -695!-1737 -695|-213 -695!-213 -695|-213 -622!-213 -622|-104 -622!-104 -622|-104 -165!-104 -92|-343 -92!-343 -92|-343 120!-104 -165|-104 -92!-104 -622|-39 -745!-104 -165|-4720 -165"/>
                            <Edge fillStyle1="1" strokeStyle="1" edges="
!-4720 -790|-1927 -790!-343 120|-4312 120!-4312 120|-4364 219!-4364 219|-4500 939!-4500 939[-4612 949 -4720 1063!-4720 1063|-4720 1178!-4720 1178|-4798 1229!-4798 1229|-4798 -165"/>
                            <Edge fillStyle0="1" fillStyle1="1" strokeStyle="1" edges="
!-4720 1063|-4720 -165!-104 -165|319 -165"/>
                            <Edge fillStyle1="1" strokeStyle="1" edges="
!21 120|-343 120!-39 -745|24 -745"/>
                          </edges>
                        </DOMShape>
                      </members>
                    </DOMGroup>
                    <DOMGroup>
                      <transformationPoint>
                        <Point x="173.4" y="-22.15"/>
                      </transformationPoint>
                      <members>
                        <DOMShape>
                          <transformationPoint>
                            <Point x="173.4" y="-22.15"/>
                          </transformationPoint>
                          <fills>
                            <FillStyle index="1">
                              <SolidColor alpha="0.498039215686275"/>
                            </FillStyle>
                          </fills>
                          <edges>
                            <Edge fillStyle1="1" edges="
!3054 -567|3182 -567!3182 -567|3272 -389!3272 -389|3364 -567!3364 -567|3484 -567!3484 -567|3484 -319!3484 -319|3404 -319!3404 -319|3404 -503!3404 -503|3402 -503!3402 -503|3308 -319!3308 -319|3236 -319!3236 -319|3138 -503!3138 -503|3136
 -503!3136 -503|3136 -319!3136 -319|3054 -319!3054 -319|3054 -567!2702 -567|2994 -567!2994 -567|2994 -525!2994 -525|2794 -525!2794 -525|2794 -465!2794 -465|2974 -465!2974 -465|2974 -421!2974 -421|2794 -421!2794 -421|2794 -319!2794 -319
|2702 -319!2702 -319|2702 -567!3742 -315[3712 -315 3686 -317!3686 -317[3660 -319 3636 -325!3636 -325[3610 -329 3594 -337!3594 -337[3576 -345 3568 -357!3568 -357[3556 -371 3556 -387!3556 -387|3556 -491!3556 -491[3556 -509 3568 -525!3568
 -525[3580 -539 3598 -547!3598 -547[3618 -555 3644 -561!3644 -561[3670 -567 3694 -569!3694 -569[3714 -571 3744 -571!3744 -571[3824 -571 3896 -563!3896 -563|3896 -519!3896 -519[3830 -529 3744 -529!3744 -529[3646 -529 3646 -491!3646 -491
|3646 -391!3646 -391[3646 -373 3672 -365!3672 -365[3698 -359 3752 -359!3752 -359[3780 -359 3812 -365!3812 -365|3812 -421!3812 -421|3750 -421!3750 -421|3750 -459!3750 -459|3898 -459!3898 -459|3898 -331!3898 -331[3870 -325 3824 -319!3824
 -319[3780 -315 3742 -315!4086 -315[4036 -315 3978 -319!3978 -319|3978 -359!3978 -359[4052 -353 4084 -353!4084 -353[4114 -353 4126 -357!4126 -357[4140 -359 4144 -367!4144 -367[4148 -373 4148 -389!4148 -389|4148 -413!4148 -413|4086 -413
!4086 -413[4054 -413 4040 -413!4040 -413[4028 -413 4010 -417!4010 -417[3992 -421 3984 -427!3984 -427[3974 -431 3968 -443!3968 -443[3962 -455 3962 -469!3962 -469|3962 -503!3962 -503[3962 -521 3970 -533!3970 -533[3976 -547 3990 -553!3990
 -553[4002 -561 4020 -565!4020 -565[4038 -569 4058 -569!4058 -569[4080 -571 4096 -571!4096 -571[4124 -571 4140 -569!4140 -569[4156 -569 4172 -565!4172 -565[4192 -561 4204 -553!4204 -553[4216 -547 4224 -533!4224 -533[4232 -521 4232 -503
!4232 -503|4232 -387!4232 -387[4232 -349 4196 -333!4196 -333[4162 -315 4086 -315!4148 -449|4148 -507!4148 -507[4148 -521 4144 -525!4144 -525[4142 -531 4132 -533!4132 -533[4122 -533 4096 -533!4096 -533[4072 -533 4062 -533!4062 -533[4052
 -531 4048 -525!4048 -525[4044 -519 4044 -507!4044 -507|4044 -469!4044 -469[4044 -461 4048 -457!4048 -457[4052 -453 4062 -451!4062 -451[4072 -449 4096 -449!4096 -449|4148 -449"/>
                          </edges>
                        </DOMShape>
                      </members>
                    </DOMGroup>
                  </members>
                </DOMGroup>
              </elements>
            </DOMFrame>
          </frames>
        </DOMLayer>
      </layers>
    </DOMTimeline>
  </timeline>
</DOMSymbolItem>